Workbook
Name Slicer_Date: #N/A
Name Slicer_Date1: #N/A
Name Slicer_Party: #N/A
Name Slicer_Party_Name: #N/A
Name Slicer_Party_Name1: #N/A
Name Slicer_Party_Name2: #N/A
Name Slicer_Person: #N/A
Name Slicer_Shipment_Number: #N/A

Sheet Billing
B1: Party Name | C1: Tiyaar | D1: Rate | E1: Total | G1: Billing
B2: =B49 -> BSC | C2: =SUMIFS(ledger!G:G, ledger!B:B, B2, ledger!E:E, "<>*RD*") / 1.0936 -> 492130.58 | D2: 10 | E2: =(SUMIFS(ledger!G:G, ledger!B:B, B2, ledger!E:E, "<>*RD*",ledger!D:D, "Silky") / 1.0936)*12 + (SUMIFS(ledger!G:G, ledger!B:B, B2, ledger!E:E, "<>*RD*",ledger!D:D, "Chamki") / 1.0936)*10 -> 5168350.4 | I2: BSC | Q2: Billing Total
B3: =B50 -> Ejaz Sahab | C3: =SUMIFS(ledger!G:G, ledger!B:B, B3, ledger!E:E, "<>*RD*") / 1.0936 -> 92419.532 | D3: 10 | E3: =(SUMIFS(ledger!G:G, ledger!B:B, B3, ledger!E:E, "<>*RD*",ledger!D:D, "Silky") / 1.0936)*12 + (SUMIFS(ledger!G:G, ledger!B:B, B3, ledger!E:E, "<>*RD*",ledger!D:D, "Chamki") / 1.0936)*10 -> 1109034.4 | I3: Ejaz Sahab
B4: =B51 -> Arshad | C4: =SUMIFS(ledger!G:G, ledger!B:B, B4, ledger!E:E, "<>*RD*") / 1.0936 -> 64937.82 | D4: 10 | E4: =(SUMIFS(ledger!G:G, ledger!B:B, B4, ledger!E:E, "<>*RD*",ledger!D:D, "Silky") / 1.0936)*12 + (SUMIFS(ledger!G:G, ledger!B:B, B4, ledger!E:E, "<>*RD*",ledger!D:D, "Chamki") / 1.0936)*10 -> 688332.11 | I4: Arshad | R4: Gaz | S4: Total Metres | T4: Total Chamki | U4: Total Super Silky | V4: Billing (Chamki/Crinkle) | W4: Billing (Super Chamki) | X4: Billing (Slub) | Y4: Billing (Satin) | Z4: Billing (Black-chamki) | AA4: Billing (Kataan) | AB4: Billing (Munaar) | AC4: Adjusted Bill | AD4: Amount Paid | AE4: Balance | AF4: Rate (Chamki) | AG4: Rate (Super Silky)
B5: =B52 -> Shehzad Kamoki | C5: =SUMIFS(ledger!G:G, ledger!B:B, B5, ledger!E:E, "<>*RD*") / 1.0936 -> 0 | D5: 10.5 | E5: =(SUMIFS(ledger!G:G, ledger!B:B, B5, ledger!E:E, "<>*RD*",ledger!D:D, "Silky") / 1.0936)*12 + (SUMIFS(ledger!G:G, ledger!B:B, B5, ledger!E:E, "<>*RD*",ledger!D:D, "Chamki") / 1.0936)*10.5 -> 0 | I5: Shehzad Kamoki | Q5: {=_xlfn.UNIQUE(Table1[Party Name])} -> BSC | R5: {=_xlfn.BYROW(B49,_xlfn.LAMBDA(_xlpm.party,SUMIFS(ledger!G:G,ledger!B:B,_xlpm.party,ledger!E:E,"<>*RD*")))+_xlfn.IFNA(C84,0)} -> 3652766.9 | S5: {=_xlfn.BYROW(B49, _xlfn.LAMBDA(_xlpm.party, SUMIFS(ledger!G:G, ledger!B:B, _xlpm.party, ledger!E:E, "<>*RD*") / 1.0936 ))+_xlfn.IFNA(D84,0)} -> 3340130.7 | T5: {=(_xlfn.BYROW(B49,_xlfn.LAMBDA(_xlpm.party,SUMIFS(ledger!G:G,ledger!B:B,_xlpm.party,ledger!E:E,"<>*RD*",ledger!D:D,"Chamki")+SUMIFS(ledger!G:G, ledger!B:B, _xlpm.party, ledger!E:E, "<>*RD*", ledger!D:D, "Crinkle")))/1.0936)+_xlfn.IFNA(E84,0)} -> 2767584 | U5: {=(_xlfn.BYROW(B49,_xlfn.LAMBDA(_xlpm.party,SUMIFS(ledger!G:G,ledger!B:B,_xlpm.party,ledger!E:E,"<>*RD*",ledger!D:D,"Silky")))/1.0936)+_xlfn.IFNA(F84,0)} -> 561031.46 | V5: {=(_xlfn.BYROW(B49,_xlfn.LAMBDA(_xlpm.party, (SUMIFS(ledger!J:J,ledger!B:B,_xlpm.party,ledger!E:E,"<>*RD*",ledger!D:D,"Chamki",ledger!C:C,"<>December Closing CF")+ SUMIFS(ledger!J:J,ledger!B:B,_xlpm.party,ledger!E:E,"<>*RD*",ledger!D:D,"Crinkle",ledger!C:C,"<>December Closing CF") )+_xlfn.IFNA(G84,0))))} -> 27675840 | W5: {=_xlfn.BYROW(B49, _xlfn.LAMBDA(_xlpm.party, SUMIFS(ledger!J:J, ledger!B:B, _xlpm.party, ledger!E:E, "<>*RD*", ledger!D:D, "Silky", ledger!C:C, "<>December Closing CF") )) + _xlfn.IFNA(H84, 0)} -> 7205053 | X5: {=_xlfn.BYROW(B49, _xlfn.LAMBDA(_xlpm.party, SUMIFS(ledger!J:J, ledger!B:B, _xlpm.party, ledger!E:E, "<>*RD*", ledger!D:D, "Slub", ledger!C:C, "<>December Closing CF") ))+ _xlfn.IFNA(I84, 0)} -> 0 | Y5: {=_xlfn.BYROW(B49, _xlfn.LAMBDA(_xlpm.party, SUMIFS(ledger!J:J, ledger!B:B, _xlpm.party, ledger!E:E, "<>*RD*", ledger!D:D, "Satin", ledger!C:C, "<>December Closing CF") ))+ _xlfn.IFNA(J84, 0)} -> 0 | Z5: {=_xlfn.BYROW(B49, _xlfn.LAMBDA(_xlpm.party, SUMIFS(ledger!J:J, ledger!B:B, _xlpm.party, ledger!E:E, "<>*RD*", ledger!D:D, "Black-Chamki", ledger!C:C, "<>December Closing CF") ))+ _xlfn.IFNA(K84, 0)} -> 0 | AA5: {=_xlfn.BYROW(B49, _xlfn.LAMBDA(_xlpm.party, SUMIFS(ledger!J:J, ledger!B:B, _xlpm.party, ledger!E:E, "<>*RD*", ledger!D:D, "Kataan", ledger!C:C, "<>December Closing CF") ))+ _xlfn.IFNA(L84, 0)} -> 126666.97 | AB5: {=_xlfn.BYROW(B49, _xlfn.LAMBDA(_xlpm.party, SUMIFS(ledger!J:J, ledger!B:B, _xlpm.party, ledger!E:E, "<>*RD*", ledger!D:D, "Munaar", ledger!C:C, "<>December Closing CF") ))+ _xlfn.IFNA(M84, 0)} -> 0 | AC5: =V5+W5+X5+Y5+Z5+AA5+AB5 -> 35007560 | AD5: =(SUMIF(Table14[Party],Q5,Table14[Credit]))+_xlfn.IFNA(O84,0) -> 19750734 | AE5: =AC5-AD5 -> 15256826 | AF5: 10 | AG5: 13
B6: =B53 -> Sufi Nawaz Sahab | C6: =SUMIFS(ledger!G:G, ledger!B:B, B6, ledger!E:E, "<>*RD*") / 1.0936 -> 0 | D6: 10 | E6: =((SUMIFS(ledger!G:G, ledger!B:B, B6, ledger!E:E, "<>*RD*",ledger!D:D, "Silky") / 1.0936) *12) + ((SUMIFS(ledger!G:G, ledger!B:B, B6, ledger!E:E, "<>*RD*",ledger!D:D, "Chamki") / 1.0936)* 9) -> 0 | I6: Sufi Nawaz Sahab | Q6: Ejaz Sahab | R6: {=_xlfn.BYROW(B50,_xlfn.LAMBDA(_xlpm.party,SUMIFS(ledger!G:G,ledger!B:B,_xlpm.party,ledger!E:E,"<>*RD*")))+_xlfn.IFNA(C85,0)} -> 580479 | S6: {=_xlfn.BYROW(B50, _xlfn.LAMBDA(_xlpm.party, SUMIFS(ledger!G:G, ledger!B:B, _xlpm.party, ledger!E:E, "<>*RD*") / 1.0936 ))+_xlfn.IFNA(D85,0)} -> 530796.45 | T6: {=(_xlfn.BYROW(B50,_xlfn.LAMBDA(_xlpm.party,SUMIFS(ledger!G:G,ledger!B:B,_xlpm.party,ledger!E:E,"<>*RD*",ledger!D:D,"Chamki")+SUMIFS(ledger!G:G, ledger!B:B, _xlpm.party, ledger!E:E, "<>*RD*", ledger!D:D, "Crinkle")))/1.0936)+_xlfn.IFNA(E85,0)} -> 148145.57 | U6: {=(_xlfn.BYROW(B50,_xlfn.LAMBDA(_xlpm.party,SUMIFS(ledger!G:G,ledger!B:B,_xlpm.party,ledger!E:E,"<>*RD*",ledger!D:D,"Silky")))/1.0936)+_xlfn.IFNA(F85,0)} -> 382650.88 | V6: {=(_xlfn.BYROW(B50,_xlfn.LAMBDA(_xlpm.party, (SUMIFS(ledger!J:J,ledger!B:B,_xlpm.party,ledger!E:E,"<>*RD*",ledger!D:D,"Chamki",ledger!C:C,"<>December Closing CF")+ SUMIFS(ledger!J:J,ledger!B:B,_xlpm.party,ledger!E:E,"<>*RD*",ledger!D:D,"Crinkle",ledger!C:C,"<>December Closing CF") )+_xlfn.IFNA(G85,0))))} -> 1481455.7 | W6: {=_xlfn.BYROW(B50, _xlfn.LAMBDA(_xlpm.party, SUMIFS(ledger!J:J, ledger!B:B, _xlpm.party, ledger!E:E, "<>*RD*", ledger!D:D, "Silky", ledger!C:C, "<>December Closing CF") )) + _xlfn.IFNA(H85, 0)} -> 4915317.3 | X6: {=_xlfn.BYROW(B50, _xlfn.LAMBDA(_xlpm.party, SUMIFS(ledger!J:J, ledger!B:B, _xlpm.party, ledger!E:E, "<>*RD*", ledger!D:D, "Slub", ledger!C:C, "<>December Closing CF") ))+ _xlfn.IFNA(I85, 0)} -> 0 | Y6: {=_xlfn.BYROW(B50, _xlfn.LAMBDA(_xlpm.party, SUMIFS(ledger!J:J, ledger!B:B, _xlpm.party, ledger!E:E, "<>*RD*", ledger!D:D, "Satin", ledger!C:C, "<>December Closing CF") ))+ _xlfn.IFNA(J85, 0)} -> 0 | Z6: {=_xlfn.BYROW(B50, _xlfn.LAMBDA(_xlpm.party, SUMIFS(ledger!J:J, ledger!B:B, _xlpm.party, ledger!E:E, "<>*RD*", ledger!D:D, "Black-Chamki", ledger!C:C, "<>December Closing CF") ))+ _xlfn.IFNA(K85, 0)} -> 0 | AA6: {=_xlfn.BYROW(B50, _xlfn.LAMBDA(_xlpm.party, SUMIFS(ledger!J:J, ledger!B:B, _xlpm.party, ledger!E:E, "<>*RD*", ledger!D:D, "Kataan", ledger!C:C, "<>December Closing CF") ))+ _xlfn.IFNA(L85, 0)} -> 0 | AB6: {=_xlfn.BYROW(B50, _xlfn.LAMBDA(_xlpm.party, SUMIFS(ledger!J:J, ledger!B:B, _xlpm.party, ledger!E:E, "<>*RD*", ledger!D:D, "Munaar", ledger!C:C, "<>December Closing CF") ))+ _xlfn.IFNA(M85, 0)} -> 0 | AC6: =V6+W6+X6+Y6+Z6+AA6+AB6 -> 6396773 | AD6: =(SUMIF(Table14[Party],Q6,Table14[Credit]))+_xlfn.IFNA(O85,0) -> 6067319 | AE6: =AC6-AD6 -> 329454.04 | AF6: 10 | AG6: 13
B7: =B54 -> Sajad Khan | C7: =SUMIFS(ledger!G:G, ledger!B:B, B7, ledger!E:E, "<>*RD*") / 1.0936 -> 131296.63 | D7: 10 | E7: {=(SUMIFS(ledger!G:G, ledger!B:B, B7, ledger!E:E, "<>*RD*",ledger!D:D, "Silky") / 1.0936)*12 + (SUMIFS(ledger!G:G, ledger!B:B, B7, ledger!E:E, "<>*RD*",ledger!D:D, "Chamki") / 1.0936)*10 +(SUMIFS(ledger!G:G, ledger!B:B, party, ledger!E:E, "<>*RD*", ledger!D:D, "Crinkle")/ 1.0936)*10} -> 1044385.5 | I7: Sajad Khan | Q7: Arshad | R7: {=_xlfn.BYROW(B51,_xlfn.LAMBDA(_xlpm.party,SUMIFS(ledger!G:G,ledger!B:B,_xlpm.party,ledger!E:E,"<>*RD*")))+_xlfn.IFNA(C86,0)} -> 894593 | S7: {=_xlfn.BYROW(B51, _xlfn.LAMBDA(_xlpm.party, SUMIFS(ledger!G:G, ledger!B:B, _xlpm.party, ledger!E:E, "<>*RD*") / 1.0936 ))+_xlfn.IFNA(D86,0)} -> 818025.79 | T7: {=(_xlfn.BYROW(B51,_xlfn.LAMBDA(_xlpm.party,SUMIFS(ledger!G:G,ledger!B:B,_xlpm.party,ledger!E:E,"<>*RD*",ledger!D:D,"Chamki")+SUMIFS(ledger!G:G, ledger!B:B, _xlpm.party, ledger!E:E, "<>*RD*", ledger!D:D, "Crinkle")))/1.0936)+_xlfn.IFNA(E86,0)} -> 671848.94 | U7: {=(_xlfn.BYROW(B51,_xlfn.LAMBDA(_xlpm.party,SUMIFS(ledger!G:G,ledger!B:B,_xlpm.party,ledger!E:E,"<>*RD*",ledger!D:D,"Silky")))/1.0936)+_xlfn.IFNA(F86,0)} -> 146176.85 | V7: {=(_xlfn.BYROW(B51,_xlfn.LAMBDA(_xlpm.party, (SUMIFS(ledger!J:J,ledger!B:B,_xlpm.party,ledger!E:E,"<>*RD*",ledger!D:D,"Chamki",ledger!C:C,"<>December Closing CF")+ SUMIFS(ledger!J:J,ledger!B:B,_xlpm.party,ledger!E:E,"<>*RD*",ledger!D:D,"Crinkle",ledger!C:C,"<>December Closing CF") )+_xlfn.IFNA(G86,0))))} -> 6718489.4 | W7: {=_xlfn.BYROW(B51, _xlfn.LAMBDA(_xlpm.party, SUMIFS(ledger!J:J, ledger!B:B, _xlpm.party, ledger!E:E, "<>*RD*", ledger!D:D, "Silky", ledger!C:C, "<>December Closing CF") )) + _xlfn.IFNA(H86, 0)} -> 1885504.8 | X7: {=_xlfn.BYROW(B51, _xlfn.LAMBDA(_xlpm.party, SUMIFS(ledger!J:J, ledger!B:B, _xlpm.party, ledger!E:E, "<>*RD*", ledger!D:D, "Slub", ledger!C:C, "<>December Closing CF") ))+ _xlfn.IFNA(I86, 0)} -> 0 | Y7: {=_xlfn.BYROW(B51, _xlfn.LAMBDA(_xlpm.party, SUMIFS(ledger!J:J, ledger!B:B, _xlpm.party, ledger!E:E, "<>*RD*", ledger!D:D, "Satin", ledger!C:C, "<>December Closing CF") ))+ _xlfn.IFNA(J86, 0)} -> 0 | Z7: {=_xlfn.BYROW(B51, _xlfn.LAMBDA(_xlpm.party, SUMIFS(ledger!J:J, ledger!B:B, _xlpm.party, ledger!E:E, "<>*RD*", ledger!D:D, "Black-Chamki", ledger!C:C, "<>December Closing CF") ))+ _xlfn.IFNA(K86, 0)} -> 0 | AA7: {=_xlfn.BYROW(B51, _xlfn.LAMBDA(_xlpm.party, SUMIFS(ledger!J:J, ledger!B:B, _xlpm.party, ledger!E:E, "<>*RD*", ledger!D:D, "Kataan", ledger!C:C, "<>December Closing CF") ))+ _xlfn.IFNA(L86, 0)} -> 0 | AB7: {=_xlfn.BYROW(B51, _xlfn.LAMBDA(_xlpm.party, SUMIFS(ledger!J:J, ledger!B:B, _xlpm.party, ledger!E:E, "<>*RD*", ledger!D:D, "Munaar", ledger!C:C, "<>December Closing CF") ))+ _xlfn.IFNA(M86, 0)} -> 0 | AC7: =V7+W7+X7+Y7+Z7+AA7+AB7 -> 8603994.1 | AD7: =(SUMIF(Table14[Party],Q7,Table14[Credit]))+_xlfn.IFNA(O86,0) -> 8492501 | AE7: =AC7-AD7 -> 111493.15 | AF7: 10 | AG7: 13
B8: =B55 -> Raaz Fabrics | C8: =SUMIFS(ledger!G:G, ledger!B:B, B8, ledger!E:E, "<>*RD*") / 1.0936 -> 0 | D8: 10 | E8: =(SUMIFS(ledger!G:G, ledger!B:B, B8, ledger!E:E, "<>*RD*",ledger!D:D, "Silky") / 1.0936)*12 + (SUMIFS(ledger!G:G, ledger!B:B, B8, ledger!E:E, "<>*RD*",ledger!D:D, "chamki") / 1.0936)*10 +(SUMIFS(ledger!G:G, ledger!B:B, B8, ledger!E:E, "<>*RD*",ledger!D:D, "Crinkle") / 1.0936)*10 -> 0 | I8: Raaz Fabrics | Q8: Shehzad Kamoki | R8: {=_xlfn.BYROW(B52,_xlfn.LAMBDA(_xlpm.party,SUMIFS(ledger!G:G,ledger!B:B,_xlpm.party,ledger!E:E,"<>*RD*")))+_xlfn.IFNA(C87,0)} -> 143457 | S8: {=_xlfn.BYROW(B52, _xlfn.LAMBDA(_xlpm.party, SUMIFS(ledger!G:G, ledger!B:B, _xlpm.party, ledger!E:E, "<>*RD*") / 1.0936 ))+_xlfn.IFNA(D87,0)} -> 131178.68 | T8: {=(_xlfn.BYROW(B52,_xlfn.LAMBDA(_xlpm.party,SUMIFS(ledger!G:G,ledger!B:B,_xlpm.party,ledger!E:E,"<>*RD*",ledger!D:D,"Chamki")+SUMIFS(ledger!G:G, ledger!B:B, _xlpm.party, ledger!E:E, "<>*RD*", ledger!D:D, "Crinkle")))/1.0936)+_xlfn.IFNA(E87,0)} -> 131178.68 | U8: {=(_xlfn.BYROW(B52,_xlfn.LAMBDA(_xlpm.party,SUMIFS(ledger!G:G,ledger!B:B,_xlpm.party,ledger!E:E,"<>*RD*",ledger!D:D,"Silky")))/1.0936)+_xlfn.IFNA(F87,0)} -> 0 | V8: {=(_xlfn.BYROW(B52,_xlfn.LAMBDA(_xlpm.party, (SUMIFS(ledger!J:J,ledger!B:B,_xlpm.party,ledger!E:E,"<>*RD*",ledger!D:D,"Chamki",ledger!C:C,"<>December Closing CF")+ SUMIFS(ledger!J:J,ledger!B:B,_xlpm.party,ledger!E:E,"<>*RD*",ledger!D:D,"Crinkle",ledger!C:C,"<>December Closing CF") )+_xlfn.IFNA(G87,0))))} -> 1354242 | W8: {=_xlfn.BYROW(B52, _xlfn.LAMBDA(_xlpm.party, SUMIFS(ledger!J:J, ledger!B:B, _xlpm.party, ledger!E:E, "<>*RD*", ledger!D:D, "Silky", ledger!C:C, "<>December Closing CF") )) + _xlfn.IFNA(H87, 0)} -> 0 | X8: {=_xlfn.BYROW(B52, _xlfn.LAMBDA(_xlpm.party, SUMIFS(ledger!J:J, ledger!B:B, _xlpm.party, ledger!E:E, "<>*RD*", ledger!D:D, "Slub", ledger!C:C, "<>December Closing CF") ))+ _xlfn.IFNA(I87, 0)} -> 0 | Y8: {=_xlfn.BYROW(B52, _xlfn.LAMBDA(_xlpm.party, SUMIFS(ledger!J:J, ledger!B:B, _xlpm.party, ledger!E:E, "<>*RD*", ledger!D:D, "Satin", ledger!C:C, "<>December Closing CF") ))+ _xlfn.IFNA(J87, 0)} -> 0 | Z8: {=_xlfn.BYROW(B52, _xlfn.LAMBDA(_xlpm.party, SUMIFS(ledger!J:J, ledger!B:B, _xlpm.party, ledger!E:E, "<>*RD*", ledger!D:D, "Black-Chamki", ledger!C:C, "<>December Closing CF") ))+ _xlfn.IFNA(K87, 0)} -> 0 | AA8: {=_xlfn.BYROW(B52, _xlfn.LAMBDA(_xlpm.party, SUMIFS(ledger!J:J, ledger!B:B, _xlpm.party, ledger!E:E, "<>*RD*", ledger!D:D, "Kataan", ledger!C:C, "<>December Closing CF") ))+ _xlfn.IFNA(L87, 0)} -> 0 | AB8: {=_xlfn.BYROW(B52, _xlfn.LAMBDA(_xlpm.party, SUMIFS(ledger!J:J, ledger!B:B, _xlpm.party, ledger!E:E, "<>*RD*", ledger!D:D, "Munaar", ledger!C:C, "<>December Closing CF") ))+ _xlfn.IFNA(M87, 0)} -> 0 | AC8: =V8+W8+X8+Y8+Z8+AA8+AB8 -> 1354242 | AD8: =(SUMIF(Table14[Party],Q8,Table14[Credit]))+_xlfn.IFNA(O87,0) -> 1353710 | AE8: =AC8-AD8 -> 531.99729 | AF8: 10.5 | AG8: 13
B9: =B56 -> Azam | C9: =SUMIFS(ledger!G:G, ledger!B:B, B9, ledger!E:E, "<>*RD*") / 1.0936 -> 188184.89 | D9: 10 | E9: =(SUMIFS(ledger!G:G, ledger!B:B, B9, ledger!E:E, "<>*RD*",ledger!D:D, "Silky") / 1.0936)*12 + (SUMIFS(ledger!G:G, ledger!B:B, B9, ledger!E:E, "<>*RD*",ledger!D:D, "Chamki") / 1.0936)*10 -> 2056600.2 | I9: Azam | Q9: Sufi Nawaz Sahab | R9: {=_xlfn.BYROW(B53,_xlfn.LAMBDA(_xlpm.party,SUMIFS(ledger!G:G,ledger!B:B,_xlpm.party,ledger!E:E,"<>*RD*")))+_xlfn.IFNA(C88,0)} -> 1212967 | S9: {=_xlfn.BYROW(B53, _xlfn.LAMBDA(_xlpm.party, SUMIFS(ledger!G:G, ledger!B:B, _xlpm.party, ledger!E:E, "<>*RD*") / 1.0936 ))+_xlfn.IFNA(D88,0)} -> 1109150.5 | T9: {=(_xlfn.BYROW(B53,_xlfn.LAMBDA(_xlpm.party,SUMIFS(ledger!G:G,ledger!B:B,_xlpm.party,ledger!E:E,"<>*RD*",ledger!D:D,"Chamki")+SUMIFS(ledger!G:G, ledger!B:B, _xlpm.party, ledger!E:E, "<>*RD*", ledger!D:D, "Crinkle")))/1.0936)+_xlfn.IFNA(E88,0)} -> 599330.65 | U9: {=(_xlfn.BYROW(B53,_xlfn.LAMBDA(_xlpm.party,SUMIFS(ledger!G:G,ledger!B:B,_xlpm.party,ledger!E:E,"<>*RD*",ledger!D:D,"Silky")))/1.0936)+_xlfn.IFNA(F88,0)} -> 485823.88 | V9: {=(_xlfn.BYROW(B53,_xlfn.LAMBDA(_xlpm.party, (SUMIFS(ledger!J:J,ledger!B:B,_xlpm.party,ledger!E:E,"<>*RD*",ledger!D:D,"Chamki",ledger!C:C,"<>December Closing CF")+ SUMIFS(ledger!J:J,ledger!B:B,_xlpm.party,ledger!E:E,"<>*RD*",ledger!D:D,"Crinkle",ledger!C:C,"<>December Closing CF") )+_xlfn.IFNA(G88,0))))} -> 5408917.9 | W9: {=_xlfn.BYROW(B53, _xlfn.LAMBDA(_xlpm.party, SUMIFS(ledger!J:J, ledger!B:B, _xlpm.party, ledger!E:E, "<>*RD*", ledger!D:D, "Silky", ledger!C:C, "<>December Closing CF") )) + _xlfn.IFNA(H88, 0)} -> 5829886.6 | X9: {=_xlfn.BYROW(B53, _xlfn.LAMBDA(_xlpm.party, SUMIFS(ledger!J:J, ledger!B:B, _xlpm.party, ledger!E:E, "<>*RD*", ledger!D:D, "Slub", ledger!C:C, "<>December Closing CF") ))+ _xlfn.IFNA(I88, 0)} -> 0 | Y9: {=_xlfn.BYROW(B53, _xlfn.LAMBDA(_xlpm.party, SUMIFS(ledger!J:J, ledger!B:B, _xlpm.party, ledger!E:E, "<>*RD*", ledger!D:D, "Satin", ledger!C:C, "<>December Closing CF") ))+ _xlfn.IFNA(J88, 0)} -> 239959.77 | Z9: {=_xlfn.BYROW(B53, _xlfn.LAMBDA(_xlpm.party, SUMIFS(ledger!J:J, ledger!B:B, _xlpm.party, ledger!E:E, "<>*RD*", ledger!D:D, "Black-Chamki", ledger!C:C, "<>December Closing CF") ))+ _xlfn.IFNA(K88, 0)} -> 0 | AA9: {=_xlfn.BYROW(B53, _xlfn.LAMBDA(_xlpm.party, SUMIFS(ledger!J:J, ledger!B:B, _xlpm.party, ledger!E:E, "<>*RD*", ledger!D:D, "Kataan", ledger!C:C, "<>December Closing CF") ))+ _xlfn.IFNA(L88, 0)} -> 0 | AB9: {=_xlfn.BYROW(B53, _xlfn.LAMBDA(_xlpm.party, SUMIFS(ledger!J:J, ledger!B:B, _xlpm.party, ledger!E:E, "<>*RD*", ledger!D:D, "Munaar", ledger!C:C, "<>December Closing CF") ))+ _xlfn.IFNA(M88, 0)} -> 0 | AC9: =V9+W9+X9+Y9+Z9+AA9+AB9 -> 11478764 | AD9: =(SUMIF(Table14[Party],Q9,Table14[Credit]))+_xlfn.IFNA(O88,0) -> 11478764 | AE9: =AC9-AD9 -> 0.23847842 | AF9: 10 | AG9: 13
B10: =B57 -> Ubaidullah | C10: =SUMIFS(ledger!G:G, ledger!B:B, B10, ledger!E:E, "<>*RD*") / 1.0936 -> 43055.962 | D10: 10 | E10: =(SUMIFS(ledger!G:G, ledger!B:B, B10, ledger!E:E, "<>*RD*",ledger!D:D, "Silky") / 1.0936)*12 + (SUMIFS(ledger!G:G, ledger!B:B, B10, ledger!E:E, "<>*RD*",ledger!D:D, "Chamki") / 1.0936)*10 -> 516671.54 | I10: Ubaidullah | Q10: Sajad Khan | R10: {=_xlfn.BYROW(B54,_xlfn.LAMBDA(_xlpm.party,SUMIFS(ledger!G:G,ledger!B:B,_xlpm.party,ledger!E:E,"<>*RD*")))+_xlfn.IFNA(C89,0)} -> 1065869 | S10: {=_xlfn.BYROW(B54, _xlfn.LAMBDA(_xlpm.party, SUMIFS(ledger!G:G, ledger!B:B, _xlpm.party, ledger!E:E, "<>*RD*") / 1.0936 ))+_xlfn.IFNA(D89,0)} -> 974642.47 | T10: {=(_xlfn.BYROW(B54,_xlfn.LAMBDA(_xlpm.party,SUMIFS(ledger!G:G,ledger!B:B,_xlpm.party,ledger!E:E,"<>*RD*",ledger!D:D,"Chamki")+SUMIFS(ledger!G:G, ledger!B:B, _xlpm.party, ledger!E:E, "<>*RD*", ledger!D:D, "Crinkle")))/1.0936)+_xlfn.IFNA(E89,0)} -> 942295.17 | U10: {=(_xlfn.BYROW(B54,_xlfn.LAMBDA(_xlpm.party,SUMIFS(ledger!G:G,ledger!B:B,_xlpm.party,ledger!E:E,"<>*RD*",ledger!D:D,"Silky")))/1.0936)+_xlfn.IFNA(F89,0)} -> 0 | V10: {=(_xlfn.BYROW(B54,_xlfn.LAMBDA(_xlpm.party, (SUMIFS(ledger!J:J,ledger!B:B,_xlpm.party,ledger!E:E,"<>*RD*",ledger!D:D,"Chamki",ledger!C:C,"<>December Closing CF")+ SUMIFS(ledger!J:J,ledger!B:B,_xlpm.party,ledger!E:E,"<>*RD*",ledger!D:D,"Crinkle",ledger!C:C,"<>December Closing CF") )+_xlfn.IFNA(G89,0))))} -> 9422951.7 | W10: {=_xlfn.BYROW(B54, _xlfn.LAMBDA(_xlpm.party, SUMIFS(ledger!J:J, ledger!B:B, _xlpm.party, ledger!E:E, "<>*RD*", ledger!D:D, "Silky", ledger!C:C, "<>December Closing CF") )) + _xlfn.IFNA(H89, 0)} -> 0 | X10: {=_xlfn.BYROW(B54, _xlfn.LAMBDA(_xlpm.party, SUMIFS(ledger!J:J, ledger!B:B, _xlpm.party, ledger!E:E, "<>*RD*", ledger!D:D, "Slub", ledger!C:C, "<>December Closing CF") ))+ _xlfn.IFNA(I89, 0)} -> 71359.729 | Y10: {=_xlfn.BYROW(B54, _xlfn.LAMBDA(_xlpm.party, SUMIFS(ledger!J:J, ledger!B:B, _xlpm.party, ledger!E:E, "<>*RD*", ledger!D:D, "Satin", ledger!C:C, "<>December Closing CF") ))+ _xlfn.IFNA(J89, 0)} -> 0 | Z10: {=_xlfn.BYROW(B54, _xlfn.LAMBDA(_xlpm.party, SUMIFS(ledger!J:J, ledger!B:B, _xlpm.party, ledger!E:E, "<>*RD*", ledger!D:D, "Black-Chamki", ledger!C:C, "<>December Closing CF") ))+ _xlfn.IFNA(K89, 0)} -> 322297 | AA10: {=_xlfn.BYROW(B54, _xlfn.LAMBDA(_xlpm.party, SUMIFS(ledger!J:J, ledger!B:B, _xlpm.party, ledger!E:E, "<>*RD*", ledger!D:D, "Kataan", ledger!C:C, "<>December Closing CF") ))+ _xlfn.IFNA(L89, 0)} -> 0 | AB10: {=_xlfn.BYROW(B54, _xlfn.LAMBDA(_xlpm.party, SUMIFS(ledger!J:J, ledger!B:B, _xlpm.party, ledger!E:E, "<>*RD*", ledger!D:D, "Munaar", ledger!C:C, "<>December Closing CF") ))+ _xlfn.IFNA(M89, 0)} -> 0 | AC10: =V10+W10+X10+Y10+Z10+AA10+AB10 -> 9816608.4 | AD10: =(SUMIF(Table14[Party],Q10,Table14[Credit]))+_xlfn.IFNA(O89,0) -> 9609871 | AE10: =AC10-AD10 -> 206737.45 | AF10: 10 | AG10: 13
B11: =B58 -> Ashraf Zia | C11: =SUMIFS(ledger!G:G, ledger!B:B, B11, ledger!E:E, "<>*RD*") / 1.0936 -> 0 | D11: 12 | E11: =(SUMIFS(ledger!G:G, ledger!B:B, B11, ledger!E:E, "<>*RD*",ledger!D:D, "Silky") / 1.0936)*12 + (SUMIFS(ledger!G:G, ledger!B:B, B11, ledger!E:E, "<>*RD*",ledger!D:D, "Chamki") / 1.0936)*10 -> 0 | I11: Ashraf Zia | Q11: Raaz Fabrics | R11: {=_xlfn.BYROW(B55,_xlfn.LAMBDA(_xlpm.party,SUMIFS(ledger!G:G,ledger!B:B,_xlpm.party,ledger!E:E,"<>*RD*")))+_xlfn.IFNA(C90,0)} -> 177861 | S11: {=_xlfn.BYROW(B55, _xlfn.LAMBDA(_xlpm.party, SUMIFS(ledger!G:G, ledger!B:B, _xlpm.party, ledger!E:E, "<>*RD*") / 1.0936 ))+_xlfn.IFNA(D90,0)} -> 162638.08 | T11: {=(_xlfn.BYROW(B55,_xlfn.LAMBDA(_xlpm.party,SUMIFS(ledger!G:G,ledger!B:B,_xlpm.party,ledger!E:E,"<>*RD*",ledger!D:D,"Chamki")+SUMIFS(ledger!G:G, ledger!B:B, _xlpm.party, ledger!E:E, "<>*RD*", ledger!D:D, "Crinkle")))/1.0936)+_xlfn.IFNA(E90,0)} -> 162638.08 | U11: {=(_xlfn.BYROW(B55,_xlfn.LAMBDA(_xlpm.party,SUMIFS(ledger!G:G,ledger!B:B,_xlpm.party,ledger!E:E,"<>*RD*",ledger!D:D,"Silky")))/1.0936)+_xlfn.IFNA(F90,0)} -> 0 | V11: {=(_xlfn.BYROW(B55,_xlfn.LAMBDA(_xlpm.party, (SUMIFS(ledger!J:J,ledger!B:B,_xlpm.party,ledger!E:E,"<>*RD*",ledger!D:D,"Chamki",ledger!C:C,"<>December Closing CF")+ SUMIFS(ledger!J:J,ledger!B:B,_xlpm.party,ledger!E:E,"<>*RD*",ledger!D:D,"Crinkle",ledger!C:C,"<>December Closing CF") )+_xlfn.IFNA(G90,0))))} -> 1626380.8 | W11: {=_xlfn.BYROW(B55, _xlfn.LAMBDA(_xlpm.party, SUMIFS(ledger!J:J, ledger!B:B, _xlpm.party, ledger!E:E, "<>*RD*", ledger!D:D, "Silky", ledger!C:C, "<>December Closing CF") )) + _xlfn.IFNA(H90, 0)} -> 0 | X11: {=_xlfn.BYROW(B55, _xlfn.LAMBDA(_xlpm.party, SUMIFS(ledger!J:J, ledger!B:B, _xlpm.party, ledger!E:E, "<>*RD*", ledger!D:D, "Slub", ledger!C:C, "<>December Closing CF") ))+ _xlfn.IFNA(I90, 0)} -> 0 | Y11: {=_xlfn.BYROW(B55, _xlfn.LAMBDA(_xlpm.party, SUMIFS(ledger!J:J, ledger!B:B, _xlpm.party, ledger!E:E, "<>*RD*", ledger!D:D, "Satin", ledger!C:C, "<>December Closing CF") ))+ _xlfn.IFNA(J90, 0)} -> 0 | Z11: {=_xlfn.BYROW(B55, _xlfn.LAMBDA(_xlpm.party, SUMIFS(ledger!J:J, ledger!B:B, _xlpm.party, ledger!E:E, "<>*RD*", ledger!D:D, "Black-Chamki", ledger!C:C, "<>December Closing CF") ))+ _xlfn.IFNA(K90, 0)} -> 0 | AA11: {=_xlfn.BYROW(B55, _xlfn.LAMBDA(_xlpm.party, SUMIFS(ledger!J:J, ledger!B:B, _xlpm.party, ledger!E:E, "<>*RD*", ledger!D:D, "Kataan", ledger!C:C, "<>December Closing CF") ))+ _xlfn.IFNA(L90, 0)} -> 0 | AB11: {=_xlfn.BYROW(B55, _xlfn.LAMBDA(_xlpm.party, SUMIFS(ledger!J:J, ledger!B:B, _xlpm.party, ledger!E:E, "<>*RD*", ledger!D:D, "Munaar", ledger!C:C, "<>December Closing CF") ))+ _xlfn.IFNA(M90, 0)} -> 0 | AC11: =V11+W11+X11+Y11+Z11+AA11+AB11 -> 1626380.8 | AD11: =(SUMIF(Table14[Party],Q11,Table14[Credit]))+_xlfn.IFNA(O90,0) -> 1526321 | AE11: =AC11-AD11 -> 100059.76 | AF11: 10 | AG11: 13
B12: =B59 -> Hafiz Qureshi | C12: =SUMIFS(ledger!G:G, ledger!B:B, B12, ledger!E:E, "<>*RD*") / 1.0936 -> 127745.98 | E12: =(SUMIFS(ledger!G:G, ledger!B:B, B12, ledger!E:E, "<>*RD*",ledger!D:D, "Silky") / 1.0936)*12 + (SUMIFS(ledger!G:G, ledger!B:B, B12, ledger!E:E, "<>*RD*",ledger!D:D, "Chamki") / 1.0936)*10 -> 1277459.8 | I12: Hafiz Qureshi | Q12: Azam | R12: {=_xlfn.BYROW(B56,_xlfn.LAMBDA(_xlpm.party,SUMIFS(ledger!G:G,ledger!B:B,_xlpm.party,ledger!E:E,"<>*RD*")))+_xlfn.IFNA(C91,0)} -> 749236 | S12: {=_xlfn.BYROW(B56, _xlfn.LAMBDA(_xlpm.party, SUMIFS(ledger!G:G, ledger!B:B, _xlpm.party, ledger!E:E, "<>*RD*") / 1.0936 ))+_xlfn.IFNA(D91,0)} -> 685109.73 | T12: {=(_xlfn.BYROW(B56,_xlfn.LAMBDA(_xlpm.party,SUMIFS(ledger!G:G,ledger!B:B,_xlpm.party,ledger!E:E,"<>*RD*",ledger!D:D,"Chamki")+SUMIFS(ledger!G:G, ledger!B:B, _xlpm.party, ledger!E:E, "<>*RD*", ledger!D:D, "Crinkle")))/1.0936)+_xlfn.IFNA(E91,0)} -> 501118.32 | U12: {=(_xlfn.BYROW(B56,_xlfn.LAMBDA(_xlpm.party,SUMIFS(ledger!G:G,ledger!B:B,_xlpm.party,ledger!E:E,"<>*RD*",ledger!D:D,"Silky")))/1.0936)+_xlfn.IFNA(F91,0)} -> 183991.4 | V12: {=(_xlfn.BYROW(B56,_xlfn.LAMBDA(_xlpm.party, (SUMIFS(ledger!J:J,ledger!B:B,_xlpm.party,ledger!E:E,"<>*RD*",ledger!D:D,"Chamki",ledger!C:C,"<>December Closing CF")+ SUMIFS(ledger!J:J,ledger!B:B,_xlpm.party,ledger!E:E,"<>*RD*",ledger!D:D,"Crinkle",ledger!C:C,"<>December Closing CF") )+_xlfn.IFNA(G91,0))))} -> 5011183.2 | W12: {=_xlfn.BYROW(B56, _xlfn.LAMBDA(_xlpm.party, SUMIFS(ledger!J:J, ledger!B:B, _xlpm.party, ledger!E:E, "<>*RD*", ledger!D:D, "Silky", ledger!C:C, "<>December Closing CF") )) + _xlfn.IFNA(H91, 0)} -> 2391888.3 | X12: {=_xlfn.BYROW(B56, _xlfn.LAMBDA(_xlpm.party, SUMIFS(ledger!J:J, ledger!B:B, _xlpm.party, ledger!E:E, "<>*RD*", ledger!D:D, "Slub", ledger!C:C, "<>December Closing CF") ))+ _xlfn.IFNA(I91, 0)} -> 0 | Y12: {=_xlfn.BYROW(B56, _xlfn.LAMBDA(_xlpm.party, SUMIFS(ledger!J:J, ledger!B:B, _xlpm.party, ledger!E:E, "<>*RD*", ledger!D:D, "Satin", ledger!C:C, "<>December Closing CF") ))+ _xlfn.IFNA(J91, 0)} -> 0 | Z12: {=_xlfn.BYROW(B56, _xlfn.LAMBDA(_xlpm.party, SUMIFS(ledger!J:J, ledger!B:B, _xlpm.party, ledger!E:E, "<>*RD*", ledger!D:D, "Black-Chamki", ledger!C:C, "<>December Closing CF") ))+ _xlfn.IFNA(K91, 0)} -> 0 | AA12: {=_xlfn.BYROW(B56, _xlfn.LAMBDA(_xlpm.party, SUMIFS(ledger!J:J, ledger!B:B, _xlpm.party, ledger!E:E, "<>*RD*", ledger!D:D, "Kataan", ledger!C:C, "<>December Closing CF") ))+ _xlfn.IFNA(L91, 0)} -> 0 | AB12: {=_xlfn.BYROW(B56, _xlfn.LAMBDA(_xlpm.party, SUMIFS(ledger!J:J, ledger!B:B, _xlpm.party, ledger!E:E, "<>*RD*", ledger!D:D, "Munaar", ledger!C:C, "<>December Closing CF") ))+ _xlfn.IFNA(M91, 0)} -> 0 | AC12: =V12+W12+X12+Y12+Z12+AA12+AB12 -> 7403071.5 | AD12: =(SUMIF(Table14[Party],Q12,Table14[Credit]))+_xlfn.IFNA(O91,0) -> 7402540 | AE12: =AC12-AD12 -> 531.50695 | AF12: 10 | AG12: 13
B13: =B60 -> Badshah Fabrics | C13: =SUMIFS(ledger!G:G, ledger!B:B, B13, ledger!E:E, "<>*RD*") / 1.0936 -> 0 | E13: =(SUMIFS(ledger!G:G, ledger!B:B, B13, ledger!E:E, "<>*RD*",ledger!D:D, "Silky") / 1.0936)*12 + (SUMIFS(ledger!G:G, ledger!B:B, B13, ledger!E:E, "<>*RD*",ledger!D:D, "Chamki") / 1.0936)*10 -> 0 | I13: Badshah Fabrics | Q13: Ubaidullah | R13: {=_xlfn.BYROW(B57,_xlfn.LAMBDA(_xlpm.party,SUMIFS(ledger!G:G,ledger!B:B,_xlpm.party,ledger!E:E,"<>*RD*")))+_xlfn.IFNA(C92,0)} -> 173534 | S13: {=_xlfn.BYROW(B57, _xlfn.LAMBDA(_xlpm.party, SUMIFS(ledger!G:G, ledger!B:B, _xlpm.party, ledger!E:E, "<>*RD*") / 1.0936 ))+_xlfn.IFNA(D92,0)} -> 158681.42 | T13: {=(_xlfn.BYROW(B57,_xlfn.LAMBDA(_xlpm.party,SUMIFS(ledger!G:G,ledger!B:B,_xlpm.party,ledger!E:E,"<>*RD*",ledger!D:D,"Chamki")+SUMIFS(ledger!G:G, ledger!B:B, _xlpm.party, ledger!E:E, "<>*RD*", ledger!D:D, "Crinkle")))/1.0936)+_xlfn.IFNA(E92,0)} -> 46132.955 | U13: {=(_xlfn.BYROW(B57,_xlfn.LAMBDA(_xlpm.party,SUMIFS(ledger!G:G,ledger!B:B,_xlpm.party,ledger!E:E,"<>*RD*",ledger!D:D,"Silky")))/1.0936)+_xlfn.IFNA(F92,0)} -> 112548.46 | V13: {=(_xlfn.BYROW(B57,_xlfn.LAMBDA(_xlpm.party, (SUMIFS(ledger!J:J,ledger!B:B,_xlpm.party,ledger!E:E,"<>*RD*",ledger!D:D,"Chamki",ledger!C:C,"<>December Closing CF")+ SUMIFS(ledger!J:J,ledger!B:B,_xlpm.party,ledger!E:E,"<>*RD*",ledger!D:D,"Crinkle",ledger!C:C,"<>December Closing CF") )+_xlfn.IFNA(G92,0))))} -> 461329.55 | W13: {=_xlfn.BYROW(B57, _xlfn.LAMBDA(_xlpm.party, SUMIFS(ledger!J:J, ledger!B:B, _xlpm.party, ledger!E:E, "<>*RD*", ledger!D:D, "Silky", ledger!C:C, "<>December Closing CF") )) + _xlfn.IFNA(H92, 0)} -> 1448134.6 | X13: {=_xlfn.BYROW(B57, _xlfn.LAMBDA(_xlpm.party, SUMIFS(ledger!J:J, ledger!B:B, _xlpm.party, ledger!E:E, "<>*RD*", ledger!D:D, "Slub", ledger!C:C, "<>December Closing CF") ))+ _xlfn.IFNA(I92, 0)} -> 0 | Y13: {=_xlfn.BYROW(B57, _xlfn.LAMBDA(_xlpm.party, SUMIFS(ledger!J:J, ledger!B:B, _xlpm.party, ledger!E:E, "<>*RD*", ledger!D:D, "Satin", ledger!C:C, "<>December Closing CF") ))+ _xlfn.IFNA(J92, 0)} -> 0 | Z13: {=_xlfn.BYROW(B57, _xlfn.LAMBDA(_xlpm.party, SUMIFS(ledger!J:J, ledger!B:B, _xlpm.party, ledger!E:E, "<>*RD*", ledger!D:D, "Black-Chamki", ledger!C:C, "<>December Closing CF") ))+ _xlfn.IFNA(K92, 0)} -> 0 | AA13: {=_xlfn.BYROW(B57, _xlfn.LAMBDA(_xlpm.party, SUMIFS(ledger!J:J, ledger!B:B, _xlpm.party, ledger!E:E, "<>*RD*", ledger!D:D, "Kataan", ledger!C:C, "<>December Closing CF") ))+ _xlfn.IFNA(L92, 0)} -> 0 | AB13: {=_xlfn.BYROW(B57, _xlfn.LAMBDA(_xlpm.party, SUMIFS(ledger!J:J, ledger!B:B, _xlpm.party, ledger!E:E, "<>*RD*", ledger!D:D, "Munaar", ledger!C:C, "<>December Closing CF") ))+ _xlfn.IFNA(M92, 0)} -> 0 | AC13: =V13+W13+X13+Y13+Z13+AA13+AB13 -> 1909464.2 | AD13: =(SUMIF(Table14[Party],Q13,Table14[Credit]))+_xlfn.IFNA(O92,0) -> 1908190 | AE13: =AC13-AD13 -> 1274.1551 | AF13: 10 | AG13: 13
B14: =B61 -> Gauhar Kashif | C14: =SUMIFS(ledger!G:G, ledger!B:B, B14, ledger!E:E, "<>*RD*") / 1.0936 -> 70997.623 | E14: =(SUMIFS(ledger!G:G, ledger!B:B, B14, ledger!E:E, "<>*RD*",ledger!D:D, "Silky") / 1.0936)*12 + (SUMIFS(ledger!G:G, ledger!B:B, B14, ledger!E:E, "<>*RD*",ledger!D:D, "Chamki") / 1.0936)*10 -> 709976.23 | I14: Reject | Q14: Ashraf Zia | R14: {=_xlfn.BYROW(B58,_xlfn.LAMBDA(_xlpm.party,SUMIFS(ledger!G:G,ledger!B:B,_xlpm.party,ledger!E:E,"<>*RD*")))+_xlfn.IFNA(C93,0)} -> 23305 | S14: {=_xlfn.BYROW(B58, _xlfn.LAMBDA(_xlpm.party, SUMIFS(ledger!G:G, ledger!B:B, _xlpm.party, ledger!E:E, "<>*RD*") / 1.0936 ))+_xlfn.IFNA(D93,0)} -> 21310.351 | T14: {=(_xlfn.BYROW(B58,_xlfn.LAMBDA(_xlpm.party,SUMIFS(ledger!G:G,ledger!B:B,_xlpm.party,ledger!E:E,"<>*RD*",ledger!D:D,"Chamki")+SUMIFS(ledger!G:G, ledger!B:B, _xlpm.party, ledger!E:E, "<>*RD*", ledger!D:D, "Crinkle")))/1.0936)+_xlfn.IFNA(E93,0)} -> 21310.351 | U14: {=(_xlfn.BYROW(B58,_xlfn.LAMBDA(_xlpm.party,SUMIFS(ledger!G:G,ledger!B:B,_xlpm.party,ledger!E:E,"<>*RD*",ledger!D:D,"Silky")))/1.0936)+_xlfn.IFNA(F93,0)} -> 0 | V14: {=(_xlfn.BYROW(B58,_xlfn.LAMBDA(_xlpm.party, (SUMIFS(ledger!J:J,ledger!B:B,_xlpm.party,ledger!E:E,"<>*RD*",ledger!D:D,"Chamki",ledger!C:C,"<>December Closing CF")+ SUMIFS(ledger!J:J,ledger!B:B,_xlpm.party,ledger!E:E,"<>*RD*",ledger!D:D,"Crinkle",ledger!C:C,"<>December Closing CF") )+_xlfn.IFNA(G93,0))))} -> 255724.21 | W14: {=_xlfn.BYROW(B58, _xlfn.LAMBDA(_xlpm.party, SUMIFS(ledger!J:J, ledger!B:B, _xlpm.party, ledger!E:E, "<>*RD*", ledger!D:D, "Silky", ledger!C:C, "<>December Closing CF") )) + _xlfn.IFNA(H93, 0)} -> 0 | X14: {=_xlfn.BYROW(B58, _xlfn.LAMBDA(_xlpm.party, SUMIFS(ledger!J:J, ledger!B:B, _xlpm.party, ledger!E:E, "<>*RD*", ledger!D:D, "Slub", ledger!C:C, "<>December Closing CF") ))+ _xlfn.IFNA(I93, 0)} -> 0 | Y14: {=_xlfn.BYROW(B58, _xlfn.LAMBDA(_xlpm.party, SUMIFS(ledger!J:J, ledger!B:B, _xlpm.party, ledger!E:E, "<>*RD*", ledger!D:D, "Satin", ledger!C:C, "<>December Closing CF") ))+ _xlfn.IFNA(J93, 0)} -> 0 | Z14: {=_xlfn.BYROW(B58, _xlfn.LAMBDA(_xlpm.party, SUMIFS(ledger!J:J, ledger!B:B, _xlpm.party, ledger!E:E, "<>*RD*", ledger!D:D, "Black-Chamki", ledger!C:C, "<>December Closing CF") ))+ _xlfn.IFNA(K93, 0)} -> 0 | AA14: {=_xlfn.BYROW(B58, _xlfn.LAMBDA(_xlpm.party, SUMIFS(ledger!J:J, ledger!B:B, _xlpm.party, ledger!E:E, "<>*RD*", ledger!D:D, "Kataan", ledger!C:C, "<>December Closing CF") ))+ _xlfn.IFNA(L93, 0)} -> 0 | AB14: {=_xlfn.BYROW(B58, _xlfn.LAMBDA(_xlpm.party, SUMIFS(ledger!J:J, ledger!B:B, _xlpm.party, ledger!E:E, "<>*RD*", ledger!D:D, "Munaar", ledger!C:C, "<>December Closing CF") ))+ _xlfn.IFNA(M93, 0)} -> 0 | AC14: =V14+W14+X14+Y14+Z14+AA14+AB14 -> 255724.21 | AD14: =(SUMIF(Table14[Party],Q14,Table14[Credit]))+_xlfn.IFNA(O93,0) -> 130000 | AE14: =AC14-AD14 -> 125724.21 | AF14: 12 | AG14: 13
B15: =B62 -> Amjad 7up | C15: =SUMIFS(ledger!G:G, ledger!B:B, B15, ledger!E:E, "<>*RD*") / 1.0936 -> 0 | E15: =(SUMIFS(ledger!G:G, ledger!B:B, B15, ledger!E:E, "<>*RD*",ledger!D:D, "Silky") / 1.0936)*12 + (SUMIFS(ledger!G:G, ledger!B:B, B15, ledger!E:E, "<>*RD*",ledger!D:D, "Chamki") / 1.0936)*10 -> 0 | I15: Amjad 7up | Q15: Hafiz Qureshi | R15: {=_xlfn.BYROW(B59,_xlfn.LAMBDA(_xlpm.party,SUMIFS(ledger!G:G,ledger!B:B,_xlpm.party,ledger!E:E,"<>*RD*")))+_xlfn.IFNA(C94,0)} -> 454627 | S15: {=_xlfn.BYROW(B59, _xlfn.LAMBDA(_xlpm.party, SUMIFS(ledger!G:G, ledger!B:B, _xlpm.party, ledger!E:E, "<>*RD*") / 1.0936 ))+_xlfn.IFNA(D94,0)} -> 415715.98 | T15: {=(_xlfn.BYROW(B59,_xlfn.LAMBDA(_xlpm.party,SUMIFS(ledger!G:G,ledger!B:B,_xlpm.party,ledger!E:E,"<>*RD*",ledger!D:D,"Chamki")+SUMIFS(ledger!G:G, ledger!B:B, _xlpm.party, ledger!E:E, "<>*RD*", ledger!D:D, "Crinkle")))/1.0936)+_xlfn.IFNA(E94,0)} -> 415715.98 | U15: {=(_xlfn.BYROW(B59,_xlfn.LAMBDA(_xlpm.party,SUMIFS(ledger!G:G,ledger!B:B,_xlpm.party,ledger!E:E,"<>*RD*",ledger!D:D,"Silky")))/1.0936)+_xlfn.IFNA(F94,0)} -> 0 | V15: {=(_xlfn.BYROW(B59,_xlfn.LAMBDA(_xlpm.party, (SUMIFS(ledger!J:J,ledger!B:B,_xlpm.party,ledger!E:E,"<>*RD*",ledger!D:D,"Chamki",ledger!C:C,"<>December Closing CF")+ SUMIFS(ledger!J:J,ledger!B:B,_xlpm.party,ledger!E:E,"<>*RD*",ledger!D:D,"Crinkle",ledger!C:C,"<>December Closing CF") )+_xlfn.IFNA(G94,0))))} -> 4157159.8 | W15: {=_xlfn.BYROW(B59, _xlfn.LAMBDA(_xlpm.party, SUMIFS(ledger!J:J, ledger!B:B, _xlpm.party, ledger!E:E, "<>*RD*", ledger!D:D, "Silky", ledger!C:C, "<>December Closing CF") )) + _xlfn.IFNA(H94, 0)} -> 0 | X15: {=_xlfn.BYROW(B59, _xlfn.LAMBDA(_xlpm.party, SUMIFS(ledger!J:J, ledger!B:B, _xlpm.party, ledger!E:E, "<>*RD*", ledger!D:D, "Slub", ledger!C:C, "<>December Closing CF") ))+ _xlfn.IFNA(I94, 0)} -> 0 | Y15: {=_xlfn.BYROW(B59, _xlfn.LAMBDA(_xlpm.party, SUMIFS(ledger!J:J, ledger!B:B, _xlpm.party, ledger!E:E, "<>*RD*", ledger!D:D, "Satin", ledger!C:C, "<>December Closing CF") ))+ _xlfn.IFNA(J94, 0)} -> 0 | Z15: {=_xlfn.BYROW(B59, _xlfn.LAMBDA(_xlpm.party, SUMIFS(ledger!J:J, ledger!B:B, _xlpm.party, ledger!E:E, "<>*RD*", ledger!D:D, "Black-Chamki", ledger!C:C, "<>December Closing CF") ))+ _xlfn.IFNA(K94, 0)} -> 0 | AA15: {=_xlfn.BYROW(B59, _xlfn.LAMBDA(_xlpm.party, SUMIFS(ledger!J:J, ledger!B:B, _xlpm.party, ledger!E:E, "<>*RD*", ledger!D:D, "Kataan", ledger!C:C, "<>December Closing CF") ))+ _xlfn.IFNA(L94, 0)} -> 0 | AB15: {=_xlfn.BYROW(B59, _xlfn.LAMBDA(_xlpm.party, SUMIFS(ledger!J:J, ledger!B:B, _xlpm.party, ledger!E:E, "<>*RD*", ledger!D:D, "Munaar", ledger!C:C, "<>December Closing CF") ))+ _xlfn.IFNA(M94, 0)} -> 0 | AC15: =V15+W15+X15+Y15+Z15+AA15+AB15 -> 4157159.8 | AD15: =(SUMIF(Table14[Party],Q15,Table14[Credit]))+_xlfn.IFNA(O94,0) -> 4146179 | AE15: =AC15-AD15 -> 10980.839 | AF15: 10 | AG15: 13
B16: =B63 -> Hazrat Khan | C16: =SUMIFS(ledger!G:G, ledger!B:B, B16, ledger!E:E, "<>*RD*") / 1.0936 -> 0 | E16: =(SUMIFS(ledger!G:G, ledger!B:B, B16, ledger!E:E, "<>*RD*",ledger!D:D, "Silky") / 1.0936)*12 + (SUMIFS(ledger!G:G, ledger!B:B, B16, ledger!E:E, "<>*RD*",ledger!D:D, "Chamki") / 1.0936)*10 -> 0 | I16: Hazrat Khan | Q16: Badshah Fabrics | R16: {=_xlfn.BYROW(B60,_xlfn.LAMBDA(_xlpm.party,SUMIFS(ledger!G:G,ledger!B:B,_xlpm.party,ledger!E:E,"<>*RD*")))+_xlfn.IFNA(C95,0)} -> 681314 | S16: {=_xlfn.BYROW(B60, _xlfn.LAMBDA(_xlpm.party, SUMIFS(ledger!G:G, ledger!B:B, _xlpm.party, ledger!E:E, "<>*RD*") / 1.0936 ))+_xlfn.IFNA(D95,0)} -> 623001.1 | T16: {=(_xlfn.BYROW(B60,_xlfn.LAMBDA(_xlpm.party,SUMIFS(ledger!G:G,ledger!B:B,_xlpm.party,ledger!E:E,"<>*RD*",ledger!D:D,"Chamki")+SUMIFS(ledger!G:G, ledger!B:B, _xlpm.party, ledger!E:E, "<>*RD*", ledger!D:D, "Crinkle")))/1.0936)+_xlfn.IFNA(E95,0)} -> 481526.15 | U16: {=(_xlfn.BYROW(B60,_xlfn.LAMBDA(_xlpm.party,SUMIFS(ledger!G:G,ledger!B:B,_xlpm.party,ledger!E:E,"<>*RD*",ledger!D:D,"Silky")))/1.0936)+_xlfn.IFNA(F95,0)} -> 141474.95 | V16: {=(_xlfn.BYROW(B60,_xlfn.LAMBDA(_xlpm.party, (SUMIFS(ledger!J:J,ledger!B:B,_xlpm.party,ledger!E:E,"<>*RD*",ledger!D:D,"Chamki",ledger!C:C,"<>December Closing CF")+ SUMIFS(ledger!J:J,ledger!B:B,_xlpm.party,ledger!E:E,"<>*RD*",ledger!D:D,"Crinkle",ledger!C:C,"<>December Closing CF") )+_xlfn.IFNA(G95,0))))} -> 4861679.8 | W16: {=_xlfn.BYROW(B60, _xlfn.LAMBDA(_xlpm.party, SUMIFS(ledger!J:J, ledger!B:B, _xlpm.party, ledger!E:E, "<>*RD*", ledger!D:D, "Silky", ledger!C:C, "<>December Closing CF") )) + _xlfn.IFNA(H95, 0)} -> 1776019.6 | X16: {=_xlfn.BYROW(B60, _xlfn.LAMBDA(_xlpm.party, SUMIFS(ledger!J:J, ledger!B:B, _xlpm.party, ledger!E:E, "<>*RD*", ledger!D:D, "Slub", ledger!C:C, "<>December Closing CF") ))+ _xlfn.IFNA(I95, 0)} -> 0 | Y16: {=_xlfn.BYROW(B60, _xlfn.LAMBDA(_xlpm.party, SUMIFS(ledger!J:J, ledger!B:B, _xlpm.party, ledger!E:E, "<>*RD*", ledger!D:D, "Satin", ledger!C:C, "<>December Closing CF") ))+ _xlfn.IFNA(J95, 0)} -> 0 | Z16: {=_xlfn.BYROW(B60, _xlfn.LAMBDA(_xlpm.party, SUMIFS(ledger!J:J, ledger!B:B, _xlpm.party, ledger!E:E, "<>*RD*", ledger!D:D, "Black-Chamki", ledger!C:C, "<>December Closing CF") ))+ _xlfn.IFNA(K95, 0)} -> 0 | AA16: {=_xlfn.BYROW(B60, _xlfn.LAMBDA(_xlpm.party, SUMIFS(ledger!J:J, ledger!B:B, _xlpm.party, ledger!E:E, "<>*RD*", ledger!D:D, "Kataan", ledger!C:C, "<>December Closing CF") ))+ _xlfn.IFNA(L95, 0)} -> 0 | AB16: {=_xlfn.BYROW(B60, _xlfn.LAMBDA(_xlpm.party, SUMIFS(ledger!J:J, ledger!B:B, _xlpm.party, ledger!E:E, "<>*RD*", ledger!D:D, "Munaar", ledger!C:C, "<>December Closing CF") ))+ _xlfn.IFNA(M95, 0)} -> 0 | AC16: =V16+W16+X16+Y16+Z16+AA16+AB16 -> 6637699.3 | AD16: =(SUMIF(Table14[Party],Q16,Table14[Credit]))+_xlfn.IFNA(O95,0) -> 6545761 | AE16: =AC16-AD16 -> 91938.342 | AF16: 10 | AG16: 13
B17: =B64 -> Haseeb Shamsi | C17: =SUMIFS(ledger!G:G, ledger!B:B, B17, ledger!E:E, "<>*RD*") / 1.0936 -> 0 | E17: =(SUMIFS(ledger!G:G, ledger!B:B, B17, ledger!E:E, "<>*RD*",ledger!D:D, "Silky") / 1.0936)*12 + (SUMIFS(ledger!G:G, ledger!B:B, B17, ledger!E:E, "<>*RD*",ledger!D:D, "Chamki") / 1.0936)*10 -> 0 | I17: Haseeb Shamsi | Q17: Gauhar Kashif | R17: {=_xlfn.BYROW(B61,_xlfn.LAMBDA(_xlpm.party,SUMIFS(ledger!G:G,ledger!B:B,_xlpm.party,ledger!E:E,"<>*RD*")))+_xlfn.IFNA(C96,0)} -> 132768 | S17: {=_xlfn.BYROW(B61, _xlfn.LAMBDA(_xlpm.party, SUMIFS(ledger!G:G, ledger!B:B, _xlpm.party, ledger!E:E, "<>*RD*") / 1.0936 ))+_xlfn.IFNA(D96,0)} -> 121404.54 | T17: {=(_xlfn.BYROW(B61,_xlfn.LAMBDA(_xlpm.party,SUMIFS(ledger!G:G,ledger!B:B,_xlpm.party,ledger!E:E,"<>*RD*",ledger!D:D,"Chamki")+SUMIFS(ledger!G:G, ledger!B:B, _xlpm.party, ledger!E:E, "<>*RD*", ledger!D:D, "Crinkle")))/1.0936)+_xlfn.IFNA(E96,0)} -> 121404.54 | U17: {=(_xlfn.BYROW(B61,_xlfn.LAMBDA(_xlpm.party,SUMIFS(ledger!G:G,ledger!B:B,_xlpm.party,ledger!E:E,"<>*RD*",ledger!D:D,"Silky")))/1.0936)+_xlfn.IFNA(F96,0)} -> 0 | V17: {=(_xlfn.BYROW(B61,_xlfn.LAMBDA(_xlpm.party, (SUMIFS(ledger!J:J,ledger!B:B,_xlpm.party,ledger!E:E,"<>*RD*",ledger!D:D,"Chamki",ledger!C:C,"<>December Closing CF")+ SUMIFS(ledger!J:J,ledger!B:B,_xlpm.party,ledger!E:E,"<>*RD*",ledger!D:D,"Crinkle",ledger!C:C,"<>December Closing CF") )+_xlfn.IFNA(G96,0))))} -> 1214045.4 | W17: {=_xlfn.BYROW(B61, _xlfn.LAMBDA(_xlpm.party, SUMIFS(ledger!J:J, ledger!B:B, _xlpm.party, ledger!E:E, "<>*RD*", ledger!D:D, "Silky", ledger!C:C, "<>December Closing CF") )) + _xlfn.IFNA(H96, 0)} -> 0 | X17: {=_xlfn.BYROW(B61, _xlfn.LAMBDA(_xlpm.party, SUMIFS(ledger!J:J, ledger!B:B, _xlpm.party, ledger!E:E, "<>*RD*", ledger!D:D, "Slub", ledger!C:C, "<>December Closing CF") ))+ _xlfn.IFNA(I96, 0)} -> 0 | Y17: {=_xlfn.BYROW(B61, _xlfn.LAMBDA(_xlpm.party, SUMIFS(ledger!J:J, ledger!B:B, _xlpm.party, ledger!E:E, "<>*RD*", ledger!D:D, "Satin", ledger!C:C, "<>December Closing CF") ))+ _xlfn.IFNA(J96, 0)} -> 0 | Z17: {=_xlfn.BYROW(B61, _xlfn.LAMBDA(_xlpm.party, SUMIFS(ledger!J:J, ledger!B:B, _xlpm.party, ledger!E:E, "<>*RD*", ledger!D:D, "Black-Chamki", ledger!C:C, "<>December Closing CF") ))+ _xlfn.IFNA(K96, 0)} -> 0 | AA17: {=_xlfn.BYROW(B61, _xlfn.LAMBDA(_xlpm.party, SUMIFS(ledger!J:J, ledger!B:B, _xlpm.party, ledger!E:E, "<>*RD*", ledger!D:D, "Kataan", ledger!C:C, "<>December Closing CF") ))+ _xlfn.IFNA(L96, 0)} -> 0 | AB17: {=_xlfn.BYROW(B61, _xlfn.LAMBDA(_xlpm.party, SUMIFS(ledger!J:J, ledger!B:B, _xlpm.party, ledger!E:E, "<>*RD*", ledger!D:D, "Munaar", ledger!C:C, "<>December Closing CF") ))+ _xlfn.IFNA(M96, 0)} -> 0 | AC17: =V17+W17+X17+Y17+Z17+AA17+AB17 -> 1214045.4 | AD17: =(SUMIF(Table14[Party],Q17,Table14[Credit]))+_xlfn.IFNA(O96,0) -> 1214045 | AE17: =AC17-AD17 -> 0.35479151 | AF17: 10 | AG17: 13
B18: =B65 -> Faizan | C18: =SUMIFS(ledger!G:G, ledger!B:B, B18, ledger!E:E, "<>*RD*") / 1.0936 -> 64407.462 | E18: =(SUMIFS(ledger!G:G, ledger!B:B, B18, ledger!E:E, "<>*RD*",ledger!D:D, "Silky") / 1.0936)*12 + (SUMIFS(ledger!G:G, ledger!B:B, B18, ledger!E:E, "<>*RD*",ledger!D:D, "Chamki") / 1.0936)*10 -> 772889.54 | I18: Faizan | Q18: Amjad 7up | R18: {=_xlfn.BYROW(B62,_xlfn.LAMBDA(_xlpm.party,SUMIFS(ledger!G:G,ledger!B:B,_xlpm.party,ledger!E:E,"<>*RD*")))+_xlfn.IFNA(C97,0)} -> 52914 | S18: {=_xlfn.BYROW(B62, _xlfn.LAMBDA(_xlpm.party, SUMIFS(ledger!G:G, ledger!B:B, _xlpm.party, ledger!E:E, "<>*RD*") / 1.0936 ))+_xlfn.IFNA(D97,0)} -> 48385.15 | T18: {=(_xlfn.BYROW(B62,_xlfn.LAMBDA(_xlpm.party,SUMIFS(ledger!G:G,ledger!B:B,_xlpm.party,ledger!E:E,"<>*RD*",ledger!D:D,"Chamki")+SUMIFS(ledger!G:G, ledger!B:B, _xlpm.party, ledger!E:E, "<>*RD*", ledger!D:D, "Crinkle")))/1.0936)+_xlfn.IFNA(E97,0)} -> 48385.15 | U18: {=(_xlfn.BYROW(B62,_xlfn.LAMBDA(_xlpm.party,SUMIFS(ledger!G:G,ledger!B:B,_xlpm.party,ledger!E:E,"<>*RD*",ledger!D:D,"Silky")))/1.0936)+_xlfn.IFNA(F97,0)} -> 0 | V18: {=(_xlfn.BYROW(B62,_xlfn.LAMBDA(_xlpm.party, (SUMIFS(ledger!J:J,ledger!B:B,_xlpm.party,ledger!E:E,"<>*RD*",ledger!D:D,"Chamki",ledger!C:C,"<>December Closing CF")+ SUMIFS(ledger!J:J,ledger!B:B,_xlpm.party,ledger!E:E,"<>*RD*",ledger!D:D,"Crinkle",ledger!C:C,"<>December Closing CF") )+_xlfn.IFNA(G97,0))))} -> 483851.5 | W18: {=_xlfn.BYROW(B62, _xlfn.LAMBDA(_xlpm.party, SUMIFS(ledger!J:J, ledger!B:B, _xlpm.party, ledger!E:E, "<>*RD*", ledger!D:D, "Silky", ledger!C:C, "<>December Closing CF") )) + _xlfn.IFNA(H97, 0)} -> 0 | X18: {=_xlfn.BYROW(B62, _xlfn.LAMBDA(_xlpm.party, SUMIFS(ledger!J:J, ledger!B:B, _xlpm.party, ledger!E:E, "<>*RD*", ledger!D:D, "Slub", ledger!C:C, "<>December Closing CF") ))+ _xlfn.IFNA(I97, 0)} -> 0 | Y18: {=_xlfn.BYROW(B62, _xlfn.LAMBDA(_xlpm.party, SUMIFS(ledger!J:J, ledger!B:B, _xlpm.party, ledger!E:E, "<>*RD*", ledger!D:D, "Satin", ledger!C:C, "<>December Closing CF") ))+ _xlfn.IFNA(J97, 0)} -> 0 | Z18: {=_xlfn.BYROW(B62, _xlfn.LAMBDA(_xlpm.party, SUMIFS(ledger!J:J, ledger!B:B, _xlpm.party, ledger!E:E, "<>*RD*", ledger!D:D, "Black-Chamki", ledger!C:C, "<>December Closing CF") ))+ _xlfn.IFNA(K97, 0)} -> 0 | AA18: {=_xlfn.BYROW(B62, _xlfn.LAMBDA(_xlpm.party, SUMIFS(ledger!J:J, ledger!B:B, _xlpm.party, ledger!E:E, "<>*RD*", ledger!D:D, "Kataan", ledger!C:C, "<>December Closing CF") ))+ _xlfn.IFNA(L97, 0)} -> 0 | AB18: {=_xlfn.BYROW(B62, _xlfn.LAMBDA(_xlpm.party, SUMIFS(ledger!J:J, ledger!B:B, _xlpm.party, ledger!E:E, "<>*RD*", ledger!D:D, "Munaar", ledger!C:C, "<>December Closing CF") ))+ _xlfn.IFNA(M97, 0)} -> 0 | AC18: =V18+W18+X18+Y18+Z18+AA18+AB18 -> 483851.5 | AD18: =(SUMIF(Table14[Party],Q18,Table14[Credit]))+_xlfn.IFNA(O97,0) -> 480000 | AE18: =AC18-AD18 -> 3851.4996 | AF18: 10 | AG18: 13
I19: Shafique Ansari | Q19: Hazrat Khan | R19: {=_xlfn.BYROW(B63,_xlfn.LAMBDA(_xlpm.party,SUMIFS(ledger!G:G,ledger!B:B,_xlpm.party,ledger!E:E,"<>*RD*")))+_xlfn.IFNA(C98,0)} -> 9750 | S19: {=_xlfn.BYROW(B63, _xlfn.LAMBDA(_xlpm.party, SUMIFS(ledger!G:G, ledger!B:B, _xlpm.party, ledger!E:E, "<>*RD*") / 1.0936 ))+_xlfn.IFNA(D98,0)} -> 8915.5084 | T19: {=(_xlfn.BYROW(B63,_xlfn.LAMBDA(_xlpm.party,SUMIFS(ledger!G:G,ledger!B:B,_xlpm.party,ledger!E:E,"<>*RD*",ledger!D:D,"Chamki")+SUMIFS(ledger!G:G, ledger!B:B, _xlpm.party, ledger!E:E, "<>*RD*", ledger!D:D, "Crinkle")))/1.0936)+_xlfn.IFNA(E98,0)} -> 8915.5084 | U19: {=(_xlfn.BYROW(B63,_xlfn.LAMBDA(_xlpm.party,SUMIFS(ledger!G:G,ledger!B:B,_xlpm.party,ledger!E:E,"<>*RD*",ledger!D:D,"Silky")))/1.0936)+_xlfn.IFNA(F98,0)} -> 0 | V19: {=(_xlfn.BYROW(B63,_xlfn.LAMBDA(_xlpm.party, (SUMIFS(ledger!J:J,ledger!B:B,_xlpm.party,ledger!E:E,"<>*RD*",ledger!D:D,"Chamki",ledger!C:C,"<>December Closing CF")+ SUMIFS(ledger!J:J,ledger!B:B,_xlpm.party,ledger!E:E,"<>*RD*",ledger!D:D,"Crinkle",ledger!C:C,"<>December Closing CF") )+_xlfn.IFNA(G98,0))))} -> 89155.084 | W19: {=_xlfn.BYROW(B63, _xlfn.LAMBDA(_xlpm.party, SUMIFS(ledger!J:J, ledger!B:B, _xlpm.party, ledger!E:E, "<>*RD*", ledger!D:D, "Silky", ledger!C:C, "<>December Closing CF") )) + _xlfn.IFNA(H98, 0)} -> 0 | X19: {=_xlfn.BYROW(B63, _xlfn.LAMBDA(_xlpm.party, SUMIFS(ledger!J:J, ledger!B:B, _xlpm.party, ledger!E:E, "<>*RD*", ledger!D:D, "Slub", ledger!C:C, "<>December Closing CF") ))+ _xlfn.IFNA(I98, 0)} -> 0 | Y19: {=_xlfn.BYROW(B63, _xlfn.LAMBDA(_xlpm.party, SUMIFS(ledger!J:J, ledger!B:B, _xlpm.party, ledger!E:E, "<>*RD*", ledger!D:D, "Satin", ledger!C:C, "<>December Closing CF") ))+ _xlfn.IFNA(J98, 0)} -> 0 | Z19: {=_xlfn.BYROW(B63, _xlfn.LAMBDA(_xlpm.party, SUMIFS(ledger!J:J, ledger!B:B, _xlpm.party, ledger!E:E, "<>*RD*", ledger!D:D, "Black-Chamki", ledger!C:C, "<>December Closing CF") ))+ _xlfn.IFNA(K98, 0)} -> 0 | AA19: {=_xlfn.BYROW(B63, _xlfn.LAMBDA(_xlpm.party, SUMIFS(ledger!J:J, ledger!B:B, _xlpm.party, ledger!E:E, "<>*RD*", ledger!D:D, "Kataan", ledger!C:C, "<>December Closing CF") ))+ _xlfn.IFNA(L98, 0)} -> 0 | AB19: {=_xlfn.BYROW(B63, _xlfn.LAMBDA(_xlpm.party, SUMIFS(ledger!J:J, ledger!B:B, _xlpm.party, ledger!E:E, "<>*RD*", ledger!D:D, "Munaar", ledger!C:C, "<>December Closing CF") ))+ _xlfn.IFNA(M98, 0)} -> 0 | AC19: =V19+W19+X19+Y19+Z19+AA19+AB19 -> 89155.084 | AD19: =(SUMIF(Table14[Party],Q19,Table14[Credit]))+_xlfn.IFNA(O98,0) -> 95000 | AE19: =AC19-AD19 -> -5844.9159 | AF19: 10 | AG19: 13
I20: Amjad sohail | Q20: Haseeb Shamsi | R20: {=_xlfn.BYROW(B64,_xlfn.LAMBDA(_xlpm.party,SUMIFS(ledger!G:G,ledger!B:B,_xlpm.party,ledger!E:E,"<>*RD*")))+_xlfn.IFNA(C99,0)} -> 61975 | S20: {=_xlfn.BYROW(B64, _xlfn.LAMBDA(_xlpm.party, SUMIFS(ledger!G:G, ledger!B:B, _xlpm.party, ledger!E:E, "<>*RD*") / 1.0936 ))+_xlfn.IFNA(D99,0)} -> 56670.629 | T20: {=(_xlfn.BYROW(B64,_xlfn.LAMBDA(_xlpm.party,SUMIFS(ledger!G:G,ledger!B:B,_xlpm.party,ledger!E:E,"<>*RD*",ledger!D:D,"Chamki")+SUMIFS(ledger!G:G, ledger!B:B, _xlpm.party, ledger!E:E, "<>*RD*", ledger!D:D, "Crinkle")))/1.0936)+_xlfn.IFNA(E99,0)} -> 47437.82 | U20: {=(_xlfn.BYROW(B64,_xlfn.LAMBDA(_xlpm.party,SUMIFS(ledger!G:G,ledger!B:B,_xlpm.party,ledger!E:E,"<>*RD*",ledger!D:D,"Silky")))/1.0936)+_xlfn.IFNA(F99,0)} -> 9232.8091 | V20: {=(_xlfn.BYROW(B64,_xlfn.LAMBDA(_xlpm.party, (SUMIFS(ledger!J:J,ledger!B:B,_xlpm.party,ledger!E:E,"<>*RD*",ledger!D:D,"Chamki",ledger!C:C,"<>December Closing CF")+ SUMIFS(ledger!J:J,ledger!B:B,_xlpm.party,ledger!E:E,"<>*RD*",ledger!D:D,"Crinkle",ledger!C:C,"<>December Closing CF") )+_xlfn.IFNA(G99,0))))} -> 474378.2 | W20: {=_xlfn.BYROW(B64, _xlfn.LAMBDA(_xlpm.party, SUMIFS(ledger!J:J, ledger!B:B, _xlpm.party, ledger!E:E, "<>*RD*", ledger!D:D, "Silky", ledger!C:C, "<>December Closing CF") )) + _xlfn.IFNA(H99, 0)} -> 120026.52 | X20: {=_xlfn.BYROW(B64, _xlfn.LAMBDA(_xlpm.party, SUMIFS(ledger!J:J, ledger!B:B, _xlpm.party, ledger!E:E, "<>*RD*", ledger!D:D, "Slub", ledger!C:C, "<>December Closing CF") ))+ _xlfn.IFNA(I99, 0)} -> 0 | Y20: {=_xlfn.BYROW(B64, _xlfn.LAMBDA(_xlpm.party, SUMIFS(ledger!J:J, ledger!B:B, _xlpm.party, ledger!E:E, "<>*RD*", ledger!D:D, "Satin", ledger!C:C, "<>December Closing CF") ))+ _xlfn.IFNA(J99, 0)} -> 0 | Z20: {=_xlfn.BYROW(B64, _xlfn.LAMBDA(_xlpm.party, SUMIFS(ledger!J:J, ledger!B:B, _xlpm.party, ledger!E:E, "<>*RD*", ledger!D:D, "Black-Chamki", ledger!C:C, "<>December Closing CF") ))+ _xlfn.IFNA(K99, 0)} -> 0 | AA20: {=_xlfn.BYROW(B64, _xlfn.LAMBDA(_xlpm.party, SUMIFS(ledger!J:J, ledger!B:B, _xlpm.party, ledger!E:E, "<>*RD*", ledger!D:D, "Kataan", ledger!C:C, "<>December Closing CF") ))+ _xlfn.IFNA(L99, 0)} -> 0 | AB20: {=_xlfn.BYROW(B64, _xlfn.LAMBDA(_xlpm.party, SUMIFS(ledger!J:J, ledger!B:B, _xlpm.party, ledger!E:E, "<>*RD*", ledger!D:D, "Munaar", ledger!C:C, "<>December Closing CF") ))+ _xlfn.IFNA(M99, 0)} -> 0 | AC20: =V20+W20+X20+Y20+Z20+AA20+AB20 -> 594404.72 | AD20: =(SUMIF(Table14[Party],Q20,Table14[Credit]))+_xlfn.IFNA(O99,0) -> 594405 | AE20: =AC20-AD20 -> -0.28163862 | AF20: 10 | AG20: 13
B21: Total: | C21: =SUM(N49:N78) -> 20808860 | D21: (Real Figure) | I21: Salman Zaffar | Q21: Faizan | R21: {=_xlfn.BYROW(B65,_xlfn.LAMBDA(_xlpm.party,SUMIFS(ledger!G:G,ledger!B:B,_xlpm.party,ledger!E:E,"<>*RD*")))+_xlfn.IFNA(C100,0)} -> 509411 | S21: {=_xlfn.BYROW(B65, _xlfn.LAMBDA(_xlpm.party, SUMIFS(ledger!G:G, ledger!B:B, _xlpm.party, ledger!E:E, "<>*RD*") / 1.0936 ))+_xlfn.IFNA(D100,0)} -> 465811.08 | T21: {=(_xlfn.BYROW(B65,_xlfn.LAMBDA(_xlpm.party,SUMIFS(ledger!G:G,ledger!B:B,_xlpm.party,ledger!E:E,"<>*RD*",ledger!D:D,"Chamki")+SUMIFS(ledger!G:G, ledger!B:B, _xlpm.party, ledger!E:E, "<>*RD*", ledger!D:D, "Crinkle")))/1.0936)+_xlfn.IFNA(E100,0)} -> 0 | U21: {=(_xlfn.BYROW(B65,_xlfn.LAMBDA(_xlpm.party,SUMIFS(ledger!G:G,ledger!B:B,_xlpm.party,ledger!E:E,"<>*RD*",ledger!D:D,"Silky")))/1.0936)+_xlfn.IFNA(F100,0)} -> 462841.08 | V21: {=(_xlfn.BYROW(B65,_xlfn.LAMBDA(_xlpm.party, (SUMIFS(ledger!J:J,ledger!B:B,_xlpm.party,ledger!E:E,"<>*RD*",ledger!D:D,"Chamki",ledger!C:C,"<>December Closing CF")+ SUMIFS(ledger!J:J,ledger!B:B,_xlpm.party,ledger!E:E,"<>*RD*",ledger!D:D,"Crinkle",ledger!C:C,"<>December Closing CF") )+_xlfn.IFNA(G100,0))))} -> 30000 | W21: {=_xlfn.BYROW(B65, _xlfn.LAMBDA(_xlpm.party, SUMIFS(ledger!J:J, ledger!B:B, _xlpm.party, ledger!E:E, "<>*RD*", ledger!D:D, "Silky", ledger!C:C, "<>December Closing CF") )) + _xlfn.IFNA(H100, 0)} -> 6016934 | X21: {=_xlfn.BYROW(B65, _xlfn.LAMBDA(_xlpm.party, SUMIFS(ledger!J:J, ledger!B:B, _xlpm.party, ledger!E:E, "<>*RD*", ledger!D:D, "Slub", ledger!C:C, "<>December Closing CF") ))+ _xlfn.IFNA(I100, 0)} -> 44550.11 | Y21: {=_xlfn.BYROW(B65, _xlfn.LAMBDA(_xlpm.party, SUMIFS(ledger!J:J, ledger!B:B, _xlpm.party, ledger!E:E, "<>*RD*", ledger!D:D, "Satin", ledger!C:C, "<>December Closing CF") ))+ _xlfn.IFNA(J100, 0)} -> 0 | Z21: {=_xlfn.BYROW(B65, _xlfn.LAMBDA(_xlpm.party, SUMIFS(ledger!J:J, ledger!B:B, _xlpm.party, ledger!E:E, "<>*RD*", ledger!D:D, "Black-Chamki", ledger!C:C, "<>December Closing CF") ))+ _xlfn.IFNA(K100, 0)} -> 0 | AA21: {=_xlfn.BYROW(B65, _xlfn.LAMBDA(_xlpm.party, SUMIFS(ledger!J:J, ledger!B:B, _xlpm.party, ledger!E:E, "<>*RD*", ledger!D:D, "Kataan", ledger!C:C, "<>December Closing CF") ))+ _xlfn.IFNA(L100, 0)} -> 0 | AB21: {=_xlfn.BYROW(B65, _xlfn.LAMBDA(_xlpm.party, SUMIFS(ledger!J:J, ledger!B:B, _xlpm.party, ledger!E:E, "<>*RD*", ledger!D:D, "Munaar", ledger!C:C, "<>December Closing CF") ))+ _xlfn.IFNA(M100, 0)} -> 0 | AC21: =V21+W21+X21+Y21+Z21+AA21+AB21 -> 6091484.1 | AD21: =(SUMIF(Table14[Party],Q21,Table14[Credit]))+_xlfn.IFNA(O100,0) -> 6024187 | AE21: =AC21-AD21 -> 67297.089 | AF21: 10 | AG21: 13
I22: Shahid Qasayi | Q22: Shafique Ansari | R22: {=_xlfn.BYROW(B66,_xlfn.LAMBDA(_xlpm.party,SUMIFS(ledger!G:G,ledger!B:B,_xlpm.party,ledger!E:E,"<>*RD*")))+_xlfn.IFNA(C101,0)} -> 82290 | S22: {=_xlfn.BYROW(B66, _xlfn.LAMBDA(_xlpm.party, SUMIFS(ledger!G:G, ledger!B:B, _xlpm.party, ledger!E:E, "<>*RD*") / 1.0936 ))+_xlfn.IFNA(D101,0)} -> 75246.891 | T22: {=(_xlfn.BYROW(B66,_xlfn.LAMBDA(_xlpm.party,SUMIFS(ledger!G:G,ledger!B:B,_xlpm.party,ledger!E:E,"<>*RD*",ledger!D:D,"Chamki")+SUMIFS(ledger!G:G, ledger!B:B, _xlpm.party, ledger!E:E, "<>*RD*", ledger!D:D, "Crinkle")))/1.0936)+_xlfn.IFNA(E101,0)} -> 64300.475 | U22: {=(_xlfn.BYROW(B66,_xlfn.LAMBDA(_xlpm.party,SUMIFS(ledger!G:G,ledger!B:B,_xlpm.party,ledger!E:E,"<>*RD*",ledger!D:D,"Silky")))/1.0936)+_xlfn.IFNA(F101,0)} -> 7565.8376 | V22: {=(_xlfn.BYROW(B66,_xlfn.LAMBDA(_xlpm.party, (SUMIFS(ledger!J:J,ledger!B:B,_xlpm.party,ledger!E:E,"<>*RD*",ledger!D:D,"Chamki",ledger!C:C,"<>December Closing CF")+ SUMIFS(ledger!J:J,ledger!B:B,_xlpm.party,ledger!E:E,"<>*RD*",ledger!D:D,"Crinkle",ledger!C:C,"<>December Closing CF") )+_xlfn.IFNA(G101,0))))} -> 643004.75 | W22: {=_xlfn.BYROW(B66, _xlfn.LAMBDA(_xlpm.party, SUMIFS(ledger!J:J, ledger!B:B, _xlpm.party, ledger!E:E, "<>*RD*", ledger!D:D, "Silky", ledger!C:C, "<>December Closing CF") )) + _xlfn.IFNA(H101, 0)} -> 98355.889 | X22: {=_xlfn.BYROW(B66, _xlfn.LAMBDA(_xlpm.party, SUMIFS(ledger!J:J, ledger!B:B, _xlpm.party, ledger!E:E, "<>*RD*", ledger!D:D, "Slub", ledger!C:C, "<>December Closing CF") ))+ _xlfn.IFNA(I101, 0)} -> 0 | Y22: {=_xlfn.BYROW(B66, _xlfn.LAMBDA(_xlpm.party, SUMIFS(ledger!J:J, ledger!B:B, _xlpm.party, ledger!E:E, "<>*RD*", ledger!D:D, "Satin", ledger!C:C, "<>December Closing CF") ))+ _xlfn.IFNA(J101, 0)} -> 94656.181 | Z22: {=_xlfn.BYROW(B66, _xlfn.LAMBDA(_xlpm.party, SUMIFS(ledger!J:J, ledger!B:B, _xlpm.party, ledger!E:E, "<>*RD*", ledger!D:D, "Black-Chamki", ledger!C:C, "<>December Closing CF") ))+ _xlfn.IFNA(K101, 0)} -> 0 | AA22: {=_xlfn.BYROW(B66, _xlfn.LAMBDA(_xlpm.party, SUMIFS(ledger!J:J, ledger!B:B, _xlpm.party, ledger!E:E, "<>*RD*", ledger!D:D, "Kataan", ledger!C:C, "<>December Closing CF") ))+ _xlfn.IFNA(L101, 0)} -> 0 | AB22: {=_xlfn.BYROW(B66, _xlfn.LAMBDA(_xlpm.party, SUMIFS(ledger!J:J, ledger!B:B, _xlpm.party, ledger!E:E, "<>*RD*", ledger!D:D, "Munaar", ledger!C:C, "<>December Closing CF") ))+ _xlfn.IFNA(M101, 0)} -> 0 | AC22: =V22+W22+X22+Y22+Z22+AA22+AB22 -> 836016.83 | AD22: =(SUMIF(Table14[Party],Q22,Table14[Credit]))+_xlfn.IFNA(O101,0) -> 835660 | AE22: =AC22-AD22 -> 356.82516 | AF22: 10 | AG22: 13
B23: Total influx | C23: =SUM(N49:N81) -> 20808860 | D23: (considering 10.5) | I23: Hameed corporation | Q23: Amjad sohail | R23: {=_xlfn.BYROW(B67,_xlfn.LAMBDA(_xlpm.party,SUMIFS(ledger!G:G,ledger!B:B,_xlpm.party,ledger!E:E,"<>*RD*")))+_xlfn.IFNA(C102,0)} -> 445530 | S23: {=_xlfn.BYROW(B67, _xlfn.LAMBDA(_xlpm.party, SUMIFS(ledger!G:G, ledger!B:B, _xlpm.party, ledger!E:E, "<>*RD*") / 1.0936 ))+_xlfn.IFNA(D102,0)} -> 407397.59 | T23: {=(_xlfn.BYROW(B67,_xlfn.LAMBDA(_xlpm.party,SUMIFS(ledger!G:G,ledger!B:B,_xlpm.party,ledger!E:E,"<>*RD*",ledger!D:D,"Chamki")+SUMIFS(ledger!G:G, ledger!B:B, _xlpm.party, ledger!E:E, "<>*RD*", ledger!D:D, "Crinkle")))/1.0936)+_xlfn.IFNA(E102,0)} -> 360797.37 | U23: {=(_xlfn.BYROW(B67,_xlfn.LAMBDA(_xlpm.party,SUMIFS(ledger!G:G,ledger!B:B,_xlpm.party,ledger!E:E,"<>*RD*",ledger!D:D,"Silky")))/1.0936)+_xlfn.IFNA(F102,0)} -> 46600.219 | V23: {=(_xlfn.BYROW(B67,_xlfn.LAMBDA(_xlpm.party, (SUMIFS(ledger!J:J,ledger!B:B,_xlpm.party,ledger!E:E,"<>*RD*",ledger!D:D,"Chamki",ledger!C:C,"<>December Closing CF")+ SUMIFS(ledger!J:J,ledger!B:B,_xlpm.party,ledger!E:E,"<>*RD*",ledger!D:D,"Crinkle",ledger!C:C,"<>December Closing CF") )+_xlfn.IFNA(G102,0))))} -> 3607973.7 | W23: {=_xlfn.BYROW(B67, _xlfn.LAMBDA(_xlpm.party, SUMIFS(ledger!J:J, ledger!B:B, _xlpm.party, ledger!E:E, "<>*RD*", ledger!D:D, "Silky", ledger!C:C, "<>December Closing CF") )) + _xlfn.IFNA(H102, 0)} -> 605802.85 | X23: {=_xlfn.BYROW(B67, _xlfn.LAMBDA(_xlpm.party, SUMIFS(ledger!J:J, ledger!B:B, _xlpm.party, ledger!E:E, "<>*RD*", ledger!D:D, "Slub", ledger!C:C, "<>December Closing CF") ))+ _xlfn.IFNA(I102, 0)} -> 0 | Y23: {=_xlfn.BYROW(B67, _xlfn.LAMBDA(_xlpm.party, SUMIFS(ledger!J:J, ledger!B:B, _xlpm.party, ledger!E:E, "<>*RD*", ledger!D:D, "Satin", ledger!C:C, "<>December Closing CF") ))+ _xlfn.IFNA(J102, 0)} -> 0 | Z23: {=_xlfn.BYROW(B67, _xlfn.LAMBDA(_xlpm.party, SUMIFS(ledger!J:J, ledger!B:B, _xlpm.party, ledger!E:E, "<>*RD*", ledger!D:D, "Black-Chamki", ledger!C:C, "<>December Closing CF") ))+ _xlfn.IFNA(K102, 0)} -> 0 | AA23: {=_xlfn.BYROW(B67, _xlfn.LAMBDA(_xlpm.party, SUMIFS(ledger!J:J, ledger!B:B, _xlpm.party, ledger!E:E, "<>*RD*", ledger!D:D, "Kataan", ledger!C:C, "<>December Closing CF") ))+ _xlfn.IFNA(L102, 0)} -> 0 | AB23: {=_xlfn.BYROW(B67, _xlfn.LAMBDA(_xlpm.party, SUMIFS(ledger!J:J, ledger!B:B, _xlpm.party, ledger!E:E, "<>*RD*", ledger!D:D, "Munaar", ledger!C:C, "<>December Closing CF") ))+ _xlfn.IFNA(M102, 0)} -> 0 | AC23: =V23+W23+X23+Y23+Z23+AA23+AB23 -> 4213776.5 | AD23: =(SUMIF(Table14[Party],Q23,Table14[Credit]))+_xlfn.IFNA(O102,0) -> 4417830 | AE23: =AC23-AD23 -> -204053.48 | AF23: 10 | AG23: 13
I24: ibraheem behraam | Q24: Salman Zaffar | R24: {=_xlfn.BYROW(B68,_xlfn.LAMBDA(_xlpm.party,SUMIFS(ledger!G:G,ledger!B:B,_xlpm.party,ledger!E:E,"<>*RD*")))+_xlfn.IFNA(C103,0)} -> 344332 | S24: {=_xlfn.BYROW(B68, _xlfn.LAMBDA(_xlpm.party, SUMIFS(ledger!G:G, ledger!B:B, _xlpm.party, ledger!E:E, "<>*RD*") / 1.0936 ))+_xlfn.IFNA(D103,0)} -> 314861.01 | T24: {=(_xlfn.BYROW(B68,_xlfn.LAMBDA(_xlpm.party,SUMIFS(ledger!G:G,ledger!B:B,_xlpm.party,ledger!E:E,"<>*RD*",ledger!D:D,"Chamki")+SUMIFS(ledger!G:G, ledger!B:B, _xlpm.party, ledger!E:E, "<>*RD*", ledger!D:D, "Crinkle")))/1.0936)+_xlfn.IFNA(E103,0)} -> 72939.832 | U24: {=(_xlfn.BYROW(B68,_xlfn.LAMBDA(_xlpm.party,SUMIFS(ledger!G:G,ledger!B:B,_xlpm.party,ledger!E:E,"<>*RD*",ledger!D:D,"Silky")))/1.0936)+_xlfn.IFNA(F103,0)} -> 31409.108 | V24: {=(_xlfn.BYROW(B68,_xlfn.LAMBDA(_xlpm.party, (SUMIFS(ledger!J:J,ledger!B:B,_xlpm.party,ledger!E:E,"<>*RD*",ledger!D:D,"Chamki",ledger!C:C,"<>December Closing CF")+ SUMIFS(ledger!J:J,ledger!B:B,_xlpm.party,ledger!E:E,"<>*RD*",ledger!D:D,"Crinkle",ledger!C:C,"<>December Closing CF") )+_xlfn.IFNA(G103,0))))} -> 729398.32 | W24: {=_xlfn.BYROW(B68, _xlfn.LAMBDA(_xlpm.party, SUMIFS(ledger!J:J, ledger!B:B, _xlpm.party, ledger!E:E, "<>*RD*", ledger!D:D, "Silky", ledger!C:C, "<>December Closing CF") )) + _xlfn.IFNA(H103, 0)} -> 408318.4 | X24: {=_xlfn.BYROW(B68, _xlfn.LAMBDA(_xlpm.party, SUMIFS(ledger!J:J, ledger!B:B, _xlpm.party, ledger!E:E, "<>*RD*", ledger!D:D, "Slub", ledger!C:C, "<>December Closing CF") ))+ _xlfn.IFNA(I103, 0)} -> 0 | Y24: {=_xlfn.BYROW(B68, _xlfn.LAMBDA(_xlpm.party, SUMIFS(ledger!J:J, ledger!B:B, _xlpm.party, ledger!E:E, "<>*RD*", ledger!D:D, "Satin", ledger!C:C, "<>December Closing CF") ))+ _xlfn.IFNA(J103, 0)} -> 0 | Z24: {=_xlfn.BYROW(B68, _xlfn.LAMBDA(_xlpm.party, SUMIFS(ledger!J:J, ledger!B:B, _xlpm.party, ledger!E:E, "<>*RD*", ledger!D:D, "Black-Chamki", ledger!C:C, "<>December Closing CF") ))+ _xlfn.IFNA(K103, 0)} -> 161653.26 | AA24: {=_xlfn.BYROW(B68, _xlfn.LAMBDA(_xlpm.party, SUMIFS(ledger!J:J, ledger!B:B, _xlpm.party, ledger!E:E, "<>*RD*", ledger!D:D, "Kataan", ledger!C:C, "<>December Closing CF") ))+ _xlfn.IFNA(L103, 0)} -> 1970409.7 | AB24: {=_xlfn.BYROW(B68, _xlfn.LAMBDA(_xlpm.party, SUMIFS(ledger!J:J, ledger!B:B, _xlpm.party, ledger!E:E, "<>*RD*", ledger!D:D, "Munaar", ledger!C:C, "<>December Closing CF") ))+ _xlfn.IFNA(M103, 0)} -> 0 | AC24: =V24+W24+X24+Y24+Z24+AA24+AB24 -> 3269779.6 | AD24: =(SUMIF(Table14[Party],Q24,Table14[Credit]))+_xlfn.IFNA(O103,0) -> 3296025 | AE24: =AC24-AD24 -> -26245.373 | AF24: 10 | AG24: 13
I25: Zia-ullah karachi | Q25: Shahid Qasayi | R25: {=_xlfn.BYROW(B69,_xlfn.LAMBDA(_xlpm.party,SUMIFS(ledger!G:G,ledger!B:B,_xlpm.party,ledger!E:E,"<>*RD*")))+_xlfn.IFNA(C104,0)} -> 394284 | S25: {=_xlfn.BYROW(B69, _xlfn.LAMBDA(_xlpm.party, SUMIFS(ledger!G:G, ledger!B:B, _xlpm.party, ledger!E:E, "<>*RD*") / 1.0936 ))+_xlfn.IFNA(D104,0)} -> 360537.67 | T25: {=(_xlfn.BYROW(B69,_xlfn.LAMBDA(_xlpm.party,SUMIFS(ledger!G:G,ledger!B:B,_xlpm.party,ledger!E:E,"<>*RD*",ledger!D:D,"Chamki")+SUMIFS(ledger!G:G, ledger!B:B, _xlpm.party, ledger!E:E, "<>*RD*", ledger!D:D, "Crinkle")))/1.0936)+_xlfn.IFNA(E104,0)} -> 310998.54 | U25: {=(_xlfn.BYROW(B69,_xlfn.LAMBDA(_xlpm.party,SUMIFS(ledger!G:G,ledger!B:B,_xlpm.party,ledger!E:E,"<>*RD*",ledger!D:D,"Silky")))/1.0936)+_xlfn.IFNA(F104,0)} -> 0 | V25: {=(_xlfn.BYROW(B69,_xlfn.LAMBDA(_xlpm.party, (SUMIFS(ledger!J:J,ledger!B:B,_xlpm.party,ledger!E:E,"<>*RD*",ledger!D:D,"Chamki",ledger!C:C,"<>December Closing CF")+ SUMIFS(ledger!J:J,ledger!B:B,_xlpm.party,ledger!E:E,"<>*RD*",ledger!D:D,"Crinkle",ledger!C:C,"<>December Closing CF") )+_xlfn.IFNA(G104,0))))} -> 3109985.4 | W25: {=_xlfn.BYROW(B69, _xlfn.LAMBDA(_xlpm.party, SUMIFS(ledger!J:J, ledger!B:B, _xlpm.party, ledger!E:E, "<>*RD*", ledger!D:D, "Silky", ledger!C:C, "<>December Closing CF") )) + _xlfn.IFNA(H104, 0)} -> 0 | X25: {=_xlfn.BYROW(B69, _xlfn.LAMBDA(_xlpm.party, SUMIFS(ledger!J:J, ledger!B:B, _xlpm.party, ledger!E:E, "<>*RD*", ledger!D:D, "Slub", ledger!C:C, "<>December Closing CF") ))+ _xlfn.IFNA(I104, 0)} -> 0 | Y25: {=_xlfn.BYROW(B69, _xlfn.LAMBDA(_xlpm.party, SUMIFS(ledger!J:J, ledger!B:B, _xlpm.party, ledger!E:E, "<>*RD*", ledger!D:D, "Satin", ledger!C:C, "<>December Closing CF") ))+ _xlfn.IFNA(J104, 0)} -> 0 | Z25: {=_xlfn.BYROW(B69, _xlfn.LAMBDA(_xlpm.party, SUMIFS(ledger!J:J, ledger!B:B, _xlpm.party, ledger!E:E, "<>*RD*", ledger!D:D, "Black-Chamki", ledger!C:C, "<>December Closing CF") ))+ _xlfn.IFNA(K104, 0)} -> 23767.374 | AA25: {=_xlfn.BYROW(B69, _xlfn.LAMBDA(_xlpm.party, SUMIFS(ledger!J:J, ledger!B:B, _xlpm.party, ledger!E:E, "<>*RD*", ledger!D:D, "Kataan", ledger!C:C, "<>December Closing CF") ))+ _xlfn.IFNA(L104, 0)} -> 523143.75 | AB25: {=_xlfn.BYROW(B69, _xlfn.LAMBDA(_xlpm.party, SUMIFS(ledger!J:J, ledger!B:B, _xlpm.party, ledger!E:E, "<>*RD*", ledger!D:D, "Munaar", ledger!C:C, "<>December Closing CF") ))+ _xlfn.IFNA(M104, 0)} -> 0 | AC25: =V25+W25+X25+Y25+Z25+AA25+AB25 -> 3656896.5 | AD25: =(SUMIF(Table14[Party],Q25,Table14[Credit]))+_xlfn.IFNA(O104,0) -> 3625137 | AE25: =AC25-AD25 -> 31759.489 | AF25: 10 | AG25: 13
I26: ZA | Q26: Hameed corporation | R26: {=_xlfn.BYROW(B70,_xlfn.LAMBDA(_xlpm.party,SUMIFS(ledger!G:G,ledger!B:B,_xlpm.party,ledger!E:E,"<>*RD*")))+_xlfn.IFNA(C105,0)} -> 46404 | S26: {=_xlfn.BYROW(B70, _xlfn.LAMBDA(_xlpm.party, SUMIFS(ledger!G:G, ledger!B:B, _xlpm.party, ledger!E:E, "<>*RD*") / 1.0936 ))+_xlfn.IFNA(D105,0)} -> 42432.334 | T26: {=(_xlfn.BYROW(B70,_xlfn.LAMBDA(_xlpm.party,SUMIFS(ledger!G:G,ledger!B:B,_xlpm.party,ledger!E:E,"<>*RD*",ledger!D:D,"Chamki")+SUMIFS(ledger!G:G, ledger!B:B, _xlpm.party, ledger!E:E, "<>*RD*", ledger!D:D, "Crinkle")))/1.0936)+_xlfn.IFNA(E105,0)} -> 42432.334 | U26: {=(_xlfn.BYROW(B70,_xlfn.LAMBDA(_xlpm.party,SUMIFS(ledger!G:G,ledger!B:B,_xlpm.party,ledger!E:E,"<>*RD*",ledger!D:D,"Silky")))/1.0936)+_xlfn.IFNA(F105,0)} -> 0 | V26: {=(_xlfn.BYROW(B70,_xlfn.LAMBDA(_xlpm.party, (SUMIFS(ledger!J:J,ledger!B:B,_xlpm.party,ledger!E:E,"<>*RD*",ledger!D:D,"Chamki",ledger!C:C,"<>December Closing CF")+ SUMIFS(ledger!J:J,ledger!B:B,_xlpm.party,ledger!E:E,"<>*RD*",ledger!D:D,"Crinkle",ledger!C:C,"<>December Closing CF") )+_xlfn.IFNA(G105,0))))} -> 424323.34 | W26: {=_xlfn.BYROW(B70, _xlfn.LAMBDA(_xlpm.party, SUMIFS(ledger!J:J, ledger!B:B, _xlpm.party, ledger!E:E, "<>*RD*", ledger!D:D, "Silky", ledger!C:C, "<>December Closing CF") )) + _xlfn.IFNA(H105, 0)} -> 0 | X26: {=_xlfn.BYROW(B70, _xlfn.LAMBDA(_xlpm.party, SUMIFS(ledger!J:J, ledger!B:B, _xlpm.party, ledger!E:E, "<>*RD*", ledger!D:D, "Slub", ledger!C:C, "<>December Closing CF") ))+ _xlfn.IFNA(I105, 0)} -> 0 | Y26: {=_xlfn.BYROW(B70, _xlfn.LAMBDA(_xlpm.party, SUMIFS(ledger!J:J, ledger!B:B, _xlpm.party, ledger!E:E, "<>*RD*", ledger!D:D, "Satin", ledger!C:C, "<>December Closing CF") ))+ _xlfn.IFNA(J105, 0)} -> 0 | Z26: {=_xlfn.BYROW(B70, _xlfn.LAMBDA(_xlpm.party, SUMIFS(ledger!J:J, ledger!B:B, _xlpm.party, ledger!E:E, "<>*RD*", ledger!D:D, "Black-Chamki", ledger!C:C, "<>December Closing CF") ))+ _xlfn.IFNA(K105, 0)} -> 0 | AA26: {=_xlfn.BYROW(B70, _xlfn.LAMBDA(_xlpm.party, SUMIFS(ledger!J:J, ledger!B:B, _xlpm.party, ledger!E:E, "<>*RD*", ledger!D:D, "Kataan", ledger!C:C, "<>December Closing CF") ))+ _xlfn.IFNA(L105, 0)} -> 0 | AB26: {=_xlfn.BYROW(B70, _xlfn.LAMBDA(_xlpm.party, SUMIFS(ledger!J:J, ledger!B:B, _xlpm.party, ledger!E:E, "<>*RD*", ledger!D:D, "Munaar", ledger!C:C, "<>December Closing CF") ))+ _xlfn.IFNA(M105, 0)} -> 0 | AC26: =V26+W26+X26+Y26+Z26+AA26+AB26 -> 424323.34 | AD26: =(SUMIF(Table14[Party],Q26,Table14[Credit]))+_xlfn.IFNA(O105,0) -> 424323 | AE26: =AC26-AD26 -> 0.33577176 | AF26: 10 | AG26: 13
I27: Ahmad Javaid | Q27: ibraheem behraam | R27: {=_xlfn.BYROW(B71,_xlfn.LAMBDA(_xlpm.party,SUMIFS(ledger!G:G,ledger!B:B,_xlpm.party,ledger!E:E,"<>*RD*")))+_xlfn.IFNA(C106,0)} -> 122386 | S27: {=_xlfn.BYROW(B71, _xlfn.LAMBDA(_xlpm.party, SUMIFS(ledger!G:G, ledger!B:B, _xlpm.party, ledger!E:E, "<>*RD*") / 1.0936 ))+_xlfn.IFNA(D106,0)} -> 111911.12 | T27: {=(_xlfn.BYROW(B71,_xlfn.LAMBDA(_xlpm.party,SUMIFS(ledger!G:G,ledger!B:B,_xlpm.party,ledger!E:E,"<>*RD*",ledger!D:D,"Chamki")+SUMIFS(ledger!G:G, ledger!B:B, _xlpm.party, ledger!E:E, "<>*RD*", ledger!D:D, "Crinkle")))/1.0936)+_xlfn.IFNA(E106,0)} -> 0 | U27: {=(_xlfn.BYROW(B71,_xlfn.LAMBDA(_xlpm.party,SUMIFS(ledger!G:G,ledger!B:B,_xlpm.party,ledger!E:E,"<>*RD*",ledger!D:D,"Silky")))/1.0936)+_xlfn.IFNA(F106,0)} -> 111911.12 | V27: {=(_xlfn.BYROW(B71,_xlfn.LAMBDA(_xlpm.party, (SUMIFS(ledger!J:J,ledger!B:B,_xlpm.party,ledger!E:E,"<>*RD*",ledger!D:D,"Chamki",ledger!C:C,"<>December Closing CF")+ SUMIFS(ledger!J:J,ledger!B:B,_xlpm.party,ledger!E:E,"<>*RD*",ledger!D:D,"Crinkle",ledger!C:C,"<>December Closing CF") )+_xlfn.IFNA(G106,0))))} -> 0 | W27: {=_xlfn.BYROW(B71, _xlfn.LAMBDA(_xlpm.party, SUMIFS(ledger!J:J, ledger!B:B, _xlpm.party, ledger!E:E, "<>*RD*", ledger!D:D, "Silky", ledger!C:C, "<>December Closing CF") )) + _xlfn.IFNA(H106, 0)} -> 1454844.6 | X27: {=_xlfn.BYROW(B71, _xlfn.LAMBDA(_xlpm.party, SUMIFS(ledger!J:J, ledger!B:B, _xlpm.party, ledger!E:E, "<>*RD*", ledger!D:D, "Slub", ledger!C:C, "<>December Closing CF") ))+ _xlfn.IFNA(I106, 0)} -> 0 | Y27: {=_xlfn.BYROW(B71, _xlfn.LAMBDA(_xlpm.party, SUMIFS(ledger!J:J, ledger!B:B, _xlpm.party, ledger!E:E, "<>*RD*", ledger!D:D, "Satin", ledger!C:C, "<>December Closing CF") ))+ _xlfn.IFNA(J106, 0)} -> 0 | Z27: {=_xlfn.BYROW(B71, _xlfn.LAMBDA(_xlpm.party, SUMIFS(ledger!J:J, ledger!B:B, _xlpm.party, ledger!E:E, "<>*RD*", ledger!D:D, "Black-Chamki", ledger!C:C, "<>December Closing CF") ))+ _xlfn.IFNA(K106, 0)} -> 0 | AA27: {=_xlfn.BYROW(B71, _xlfn.LAMBDA(_xlpm.party, SUMIFS(ledger!J:J, ledger!B:B, _xlpm.party, ledger!E:E, "<>*RD*", ledger!D:D, "Kataan", ledger!C:C, "<>December Closing CF") ))+ _xlfn.IFNA(L106, 0)} -> 0 | AB27: {=_xlfn.BYROW(B71, _xlfn.LAMBDA(_xlpm.party, SUMIFS(ledger!J:J, ledger!B:B, _xlpm.party, ledger!E:E, "<>*RD*", ledger!D:D, "Munaar", ledger!C:C, "<>December Closing CF") ))+ _xlfn.IFNA(M106, 0)} -> 0 | AC27: =V27+W27+X27+Y27+Z27+AA27+AB27 -> 1454844.6 | AD27: =(SUMIF(Table14[Party],Q27,Table14[Credit]))+_xlfn.IFNA(O106,0) -> 1415500 | AE27: =AC27-AD27 -> 39344.55 | AF27: 10 | AG27: 13
Q28: Zia-ullah karachi | R28: {=_xlfn.BYROW(B72,_xlfn.LAMBDA(_xlpm.party,SUMIFS(ledger!G:G,ledger!B:B,_xlpm.party,ledger!E:E,"<>*RD*")))+_xlfn.IFNA(C107,0)} -> 13622 | S28: {=_xlfn.BYROW(B72, _xlfn.LAMBDA(_xlpm.party, SUMIFS(ledger!G:G, ledger!B:B, _xlpm.party, ledger!E:E, "<>*RD*") / 1.0936 ))+_xlfn.IFNA(D107,0)} -> 12456.108 | T28: {=(_xlfn.BYROW(B72,_xlfn.LAMBDA(_xlpm.party,SUMIFS(ledger!G:G,ledger!B:B,_xlpm.party,ledger!E:E,"<>*RD*",ledger!D:D,"Chamki")+SUMIFS(ledger!G:G, ledger!B:B, _xlpm.party, ledger!E:E, "<>*RD*", ledger!D:D, "Crinkle")))/1.0936)+_xlfn.IFNA(E107,0)} -> 12456.108 | U28: {=(_xlfn.BYROW(B72,_xlfn.LAMBDA(_xlpm.party,SUMIFS(ledger!G:G,ledger!B:B,_xlpm.party,ledger!E:E,"<>*RD*",ledger!D:D,"Silky")))/1.0936)+_xlfn.IFNA(F107,0)} -> 0 | V28: {=(_xlfn.BYROW(B72,_xlfn.LAMBDA(_xlpm.party, (SUMIFS(ledger!J:J,ledger!B:B,_xlpm.party,ledger!E:E,"<>*RD*",ledger!D:D,"Chamki",ledger!C:C,"<>December Closing CF")+ SUMIFS(ledger!J:J,ledger!B:B,_xlpm.party,ledger!E:E,"<>*RD*",ledger!D:D,"Crinkle",ledger!C:C,"<>December Closing CF") )+_xlfn.IFNA(G107,0))))} -> 124561.08 | W28: {=_xlfn.BYROW(B72, _xlfn.LAMBDA(_xlpm.party, SUMIFS(ledger!J:J, ledger!B:B, _xlpm.party, ledger!E:E, "<>*RD*", ledger!D:D, "Silky", ledger!C:C, "<>December Closing CF") )) + _xlfn.IFNA(H107, 0)} -> 0 | X28: {=_xlfn.BYROW(B72, _xlfn.LAMBDA(_xlpm.party, SUMIFS(ledger!J:J, ledger!B:B, _xlpm.party, ledger!E:E, "<>*RD*", ledger!D:D, "Slub", ledger!C:C, "<>December Closing CF") ))+ _xlfn.IFNA(I107, 0)} -> 0 | Y28: {=_xlfn.BYROW(B72, _xlfn.LAMBDA(_xlpm.party, SUMIFS(ledger!J:J, ledger!B:B, _xlpm.party, ledger!E:E, "<>*RD*", ledger!D:D, "Satin", ledger!C:C, "<>December Closing CF") ))+ _xlfn.IFNA(J107, 0)} -> 0 | Z28: {=_xlfn.BYROW(B72, _xlfn.LAMBDA(_xlpm.party, SUMIFS(ledger!J:J, ledger!B:B, _xlpm.party, ledger!E:E, "<>*RD*", ledger!D:D, "Black-Chamki", ledger!C:C, "<>December Closing CF") ))+ _xlfn.IFNA(K107, 0)} -> 0 | AA28: {=_xlfn.BYROW(B72, _xlfn.LAMBDA(_xlpm.party, SUMIFS(ledger!J:J, ledger!B:B, _xlpm.party, ledger!E:E, "<>*RD*", ledger!D:D, "Kataan", ledger!C:C, "<>December Closing CF") ))+ _xlfn.IFNA(L107, 0)} -> 0 | AB28: {=_xlfn.BYROW(B72, _xlfn.LAMBDA(_xlpm.party, SUMIFS(ledger!J:J, ledger!B:B, _xlpm.party, ledger!E:E, "<>*RD*", ledger!D:D, "Munaar", ledger!C:C, "<>December Closing CF") ))+ _xlfn.IFNA(M107, 0)} -> 0 | AC28: =V28+W28+X28+Y28+Z28+AA28+AB28 -> 124561.08 | AD28: =(SUMIF(Table14[Party],Q28,Table14[Credit]))+_xlfn.IFNA(O107,0) -> 124560 | AE28: =AC28-AD28 -> 1.0826628 | AF28: 10 | AG28: 13
Q29: ZA | R29: {=_xlfn.BYROW(B73,_xlfn.LAMBDA(_xlpm.party,SUMIFS(ledger!G:G,ledger!B:B,_xlpm.party,ledger!E:E,"<>*RD*")))+_xlfn.IFNA(C108,0)} -> 32399 | S29: {=_xlfn.BYROW(B73, _xlfn.LAMBDA(_xlpm.party, SUMIFS(ledger!G:G, ledger!B:B, _xlpm.party, ledger!E:E, "<>*RD*") / 1.0936 ))+_xlfn.IFNA(D108,0)} -> 29626.006 | T29: {=(_xlfn.BYROW(B73,_xlfn.LAMBDA(_xlpm.party,SUMIFS(ledger!G:G,ledger!B:B,_xlpm.party,ledger!E:E,"<>*RD*",ledger!D:D,"Chamki")+SUMIFS(ledger!G:G, ledger!B:B, _xlpm.party, ledger!E:E, "<>*RD*", ledger!D:D, "Crinkle")))/1.0936)+_xlfn.IFNA(E108,0)} -> 0 | U29: {=(_xlfn.BYROW(B73,_xlfn.LAMBDA(_xlpm.party,SUMIFS(ledger!G:G,ledger!B:B,_xlpm.party,ledger!E:E,"<>*RD*",ledger!D:D,"Silky")))/1.0936)+_xlfn.IFNA(F108,0)} -> 29626.006 | V29: {=(_xlfn.BYROW(B73,_xlfn.LAMBDA(_xlpm.party, (SUMIFS(ledger!J:J,ledger!B:B,_xlpm.party,ledger!E:E,"<>*RD*",ledger!D:D,"Chamki",ledger!C:C,"<>December Closing CF")+ SUMIFS(ledger!J:J,ledger!B:B,_xlpm.party,ledger!E:E,"<>*RD*",ledger!D:D,"Crinkle",ledger!C:C,"<>December Closing CF") )+_xlfn.IFNA(G108,0))))} -> 0 | W29: {=_xlfn.BYROW(B73, _xlfn.LAMBDA(_xlpm.party, SUMIFS(ledger!J:J, ledger!B:B, _xlpm.party, ledger!E:E, "<>*RD*", ledger!D:D, "Silky", ledger!C:C, "<>December Closing CF") )) + _xlfn.IFNA(H108, 0)} -> 385138.08 | X29: {=_xlfn.BYROW(B73, _xlfn.LAMBDA(_xlpm.party, SUMIFS(ledger!J:J, ledger!B:B, _xlpm.party, ledger!E:E, "<>*RD*", ledger!D:D, "Slub", ledger!C:C, "<>December Closing CF") ))+ _xlfn.IFNA(I108, 0)} -> 0 | Y29: {=_xlfn.BYROW(B73, _xlfn.LAMBDA(_xlpm.party, SUMIFS(ledger!J:J, ledger!B:B, _xlpm.party, ledger!E:E, "<>*RD*", ledger!D:D, "Satin", ledger!C:C, "<>December Closing CF") ))+ _xlfn.IFNA(J108, 0)} -> 0 | Z29: {=_xlfn.BYROW(B73, _xlfn.LAMBDA(_xlpm.party, SUMIFS(ledger!J:J, ledger!B:B, _xlpm.party, ledger!E:E, "<>*RD*", ledger!D:D, "Black-Chamki", ledger!C:C, "<>December Closing CF") ))+ _xlfn.IFNA(K108, 0)} -> 0 | AA29: {=_xlfn.BYROW(B73, _xlfn.LAMBDA(_xlpm.party, SUMIFS(ledger!J:J, ledger!B:B, _xlpm.party, ledger!E:E, "<>*RD*", ledger!D:D, "Kataan", ledger!C:C, "<>December Closing CF") ))+ _xlfn.IFNA(L108, 0)} -> 0 | AB29: {=_xlfn.BYROW(B73, _xlfn.LAMBDA(_xlpm.party, SUMIFS(ledger!J:J, ledger!B:B, _xlpm.party, ledger!E:E, "<>*RD*", ledger!D:D, "Munaar", ledger!C:C, "<>December Closing CF") ))+ _xlfn.IFNA(M108, 0)} -> 0 | AC29: =V29+W29+X29+Y29+Z29+AA29+AB29 -> 385138.08 | AD29: =(SUMIF(Table14[Party],Q29,Table14[Credit]))+_xlfn.IFNA(O108,0) -> 250000 | AE29: =AC29-AD29 -> 135138.08 | AF29: 10 | AG29: 13
Q30: Ahmad Javaid | R30: {=_xlfn.BYROW(B74,_xlfn.LAMBDA(_xlpm.party,SUMIFS(ledger!G:G,ledger!B:B,_xlpm.party,ledger!E:E,"<>*RD*")))+_xlfn.IFNA(C109,0)} -> 12745 | S30: {=_xlfn.BYROW(B74, _xlfn.LAMBDA(_xlpm.party, SUMIFS(ledger!G:G, ledger!B:B, _xlpm.party, ledger!E:E, "<>*RD*") / 1.0936 ))+_xlfn.IFNA(D109,0)} -> 11654.17 | T30: {=(_xlfn.BYROW(B74,_xlfn.LAMBDA(_xlpm.party,SUMIFS(ledger!G:G,ledger!B:B,_xlpm.party,ledger!E:E,"<>*RD*",ledger!D:D,"Chamki")+SUMIFS(ledger!G:G, ledger!B:B, _xlpm.party, ledger!E:E, "<>*RD*", ledger!D:D, "Crinkle")))/1.0936)+_xlfn.IFNA(E109,0)} -> 0 | U30: {=(_xlfn.BYROW(B74,_xlfn.LAMBDA(_xlpm.party,SUMIFS(ledger!G:G,ledger!B:B,_xlpm.party,ledger!E:E,"<>*RD*",ledger!D:D,"Silky")))/1.0936)+_xlfn.IFNA(F109,0)} -> 0 | V30: {=(_xlfn.BYROW(B74,_xlfn.LAMBDA(_xlpm.party, (SUMIFS(ledger!J:J,ledger!B:B,_xlpm.party,ledger!E:E,"<>*RD*",ledger!D:D,"Chamki",ledger!C:C,"<>December Closing CF")+ SUMIFS(ledger!J:J,ledger!B:B,_xlpm.party,ledger!E:E,"<>*RD*",ledger!D:D,"Crinkle",ledger!C:C,"<>December Closing CF") )+_xlfn.IFNA(G109,0))))} -> 0 | W30: {=_xlfn.BYROW(B74, _xlfn.LAMBDA(_xlpm.party, SUMIFS(ledger!J:J, ledger!B:B, _xlpm.party, ledger!E:E, "<>*RD*", ledger!D:D, "Silky", ledger!C:C, "<>December Closing CF") )) + _xlfn.IFNA(H109, 0)} -> 0 | X30: {=_xlfn.BYROW(B74, _xlfn.LAMBDA(_xlpm.party, SUMIFS(ledger!J:J, ledger!B:B, _xlpm.party, ledger!E:E, "<>*RD*", ledger!D:D, "Slub", ledger!C:C, "<>December Closing CF") ))+ _xlfn.IFNA(I109, 0)} -> 0 | Y30: {=_xlfn.BYROW(B74, _xlfn.LAMBDA(_xlpm.party, SUMIFS(ledger!J:J, ledger!B:B, _xlpm.party, ledger!E:E, "<>*RD*", ledger!D:D, "Satin", ledger!C:C, "<>December Closing CF") ))+ _xlfn.IFNA(J109, 0)} -> 0 | Z30: {=_xlfn.BYROW(B74, _xlfn.LAMBDA(_xlpm.party, SUMIFS(ledger!J:J, ledger!B:B, _xlpm.party, ledger!E:E, "<>*RD*", ledger!D:D, "Black-Chamki", ledger!C:C, "<>December Closing CF") ))+ _xlfn.IFNA(K109, 0)} -> 0 | AA30: {=_xlfn.BYROW(B74, _xlfn.LAMBDA(_xlpm.party, SUMIFS(ledger!J:J, ledger!B:B, _xlpm.party, ledger!E:E, "<>*RD*", ledger!D:D, "Kataan", ledger!C:C, "<>December Closing CF") ))+ _xlfn.IFNA(L109, 0)} -> 0 | AB30: {=_xlfn.BYROW(B74, _xlfn.LAMBDA(_xlpm.party, SUMIFS(ledger!J:J, ledger!B:B, _xlpm.party, ledger!E:E, "<>*RD*", ledger!D:D, "Munaar", ledger!C:C, "<>December Closing CF") ))+ _xlfn.IFNA(M109, 0)} -> 151504.21 | AC30: =V30+W30+X30+Y30+Z30+AA30+AB30 -> 151504.21 | AD30: =(SUMIF(Table14[Party],Q30,Table14[Credit]))+_xlfn.IFNA(O109,0) -> 0 | AE30: =AC30-AD30 -> 151504.21 | AF30: 10 | AG30: 13
Q31: Rehman Ali | R31: {=_xlfn.BYROW(B75,_xlfn.LAMBDA(_xlpm.party,SUMIFS(ledger!G:G,ledger!B:B,_xlpm.party,ledger!E:E,"<>*RD*")))+_xlfn.IFNA(C110,0)} -> 50131 | S31: {=_xlfn.BYROW(B75, _xlfn.LAMBDA(_xlpm.party, SUMIFS(ledger!G:G, ledger!B:B, _xlpm.party, ledger!E:E, "<>*RD*") / 1.0936 ))+_xlfn.IFNA(D110,0)} -> 45840.344 | T31: {=(_xlfn.BYROW(B75,_xlfn.LAMBDA(_xlpm.party,SUMIFS(ledger!G:G,ledger!B:B,_xlpm.party,ledger!E:E,"<>*RD*",ledger!D:D,"Chamki")+SUMIFS(ledger!G:G, ledger!B:B, _xlpm.party, ledger!E:E, "<>*RD*", ledger!D:D, "Crinkle")))/1.0936)+_xlfn.IFNA(E110,0)} -> 0 | U31: {=(_xlfn.BYROW(B75,_xlfn.LAMBDA(_xlpm.party,SUMIFS(ledger!G:G,ledger!B:B,_xlpm.party,ledger!E:E,"<>*RD*",ledger!D:D,"Silky")))/1.0936)+_xlfn.IFNA(F110,0)} -> 45840.344 | V31: {=(_xlfn.BYROW(B75,_xlfn.LAMBDA(_xlpm.party, (SUMIFS(ledger!J:J,ledger!B:B,_xlpm.party,ledger!E:E,"<>*RD*",ledger!D:D,"Chamki",ledger!C:C,"<>December Closing CF")+ SUMIFS(ledger!J:J,ledger!B:B,_xlpm.party,ledger!E:E,"<>*RD*",ledger!D:D,"Crinkle",ledger!C:C,"<>December Closing CF") )+_xlfn.IFNA(G110,0))))} -> 0 | W31: {=_xlfn.BYROW(B75, _xlfn.LAMBDA(_xlpm.party, SUMIFS(ledger!J:J, ledger!B:B, _xlpm.party, ledger!E:E, "<>*RD*", ledger!D:D, "Silky", ledger!C:C, "<>December Closing CF") )) + _xlfn.IFNA(H110, 0)} -> 595924.47 | X31: {=_xlfn.BYROW(B75, _xlfn.LAMBDA(_xlpm.party, SUMIFS(ledger!J:J, ledger!B:B, _xlpm.party, ledger!E:E, "<>*RD*", ledger!D:D, "Slub", ledger!C:C, "<>December Closing CF") ))+ _xlfn.IFNA(I110, 0)} -> 0 | Y31: {=_xlfn.BYROW(B75, _xlfn.LAMBDA(_xlpm.party, SUMIFS(ledger!J:J, ledger!B:B, _xlpm.party, ledger!E:E, "<>*RD*", ledger!D:D, "Satin", ledger!C:C, "<>December Closing CF") ))+ _xlfn.IFNA(J110, 0)} -> 0 | Z31: {=_xlfn.BYROW(B75, _xlfn.LAMBDA(_xlpm.party, SUMIFS(ledger!J:J, ledger!B:B, _xlpm.party, ledger!E:E, "<>*RD*", ledger!D:D, "Black-Chamki", ledger!C:C, "<>December Closing CF") ))+ _xlfn.IFNA(K110, 0)} -> 0 | AA31: {=_xlfn.BYROW(B75, _xlfn.LAMBDA(_xlpm.party, SUMIFS(ledger!J:J, ledger!B:B, _xlpm.party, ledger!E:E, "<>*RD*", ledger!D:D, "Kataan", ledger!C:C, "<>December Closing CF") ))+ _xlfn.IFNA(L110, 0)} -> 0 | AB31: {=_xlfn.BYROW(B75, _xlfn.LAMBDA(_xlpm.party, SUMIFS(ledger!J:J, ledger!B:B, _xlpm.party, ledger!E:E, "<>*RD*", ledger!D:D, "Munaar", ledger!C:C, "<>December Closing CF") ))+ _xlfn.IFNA(M110, 0)} -> 0 | AC31: =V31+W31+X31+Y31+Z31+AA31+AB31 -> 595924.47 | AD31: =(SUMIF(Table14[Party],Q31,Table14[Credit]))+_xlfn.IFNA(O110,0) -> 550000 | AE31: =AC31-AD31 -> 45924.47 | AF31: 10 | AG31: 13
Q32: Shani Badshah | R32: {=_xlfn.BYROW(B76,_xlfn.LAMBDA(_xlpm.party,SUMIFS(ledger!G:G,ledger!B:B,_xlpm.party,ledger!E:E,"<>*RD*")))+_xlfn.IFNA(C111,0)} -> 200033 | S32: {=_xlfn.BYROW(B76, _xlfn.LAMBDA(_xlpm.party, SUMIFS(ledger!G:G, ledger!B:B, _xlpm.party, ledger!E:E, "<>*RD*") / 1.0936 ))+_xlfn.IFNA(D111,0)} -> 182912.4 | T32: {=(_xlfn.BYROW(B76,_xlfn.LAMBDA(_xlpm.party,SUMIFS(ledger!G:G,ledger!B:B,_xlpm.party,ledger!E:E,"<>*RD*",ledger!D:D,"Chamki")+SUMIFS(ledger!G:G, ledger!B:B, _xlpm.party, ledger!E:E, "<>*RD*", ledger!D:D, "Crinkle")))/1.0936)+_xlfn.IFNA(E111,0)} -> 96185.077 | U32: {=(_xlfn.BYROW(B76,_xlfn.LAMBDA(_xlpm.party,SUMIFS(ledger!G:G,ledger!B:B,_xlpm.party,ledger!E:E,"<>*RD*",ledger!D:D,"Silky")))/1.0936)+_xlfn.IFNA(F111,0)} -> 86727.323 | V32: {=(_xlfn.BYROW(B76,_xlfn.LAMBDA(_xlpm.party, (SUMIFS(ledger!J:J,ledger!B:B,_xlpm.party,ledger!E:E,"<>*RD*",ledger!D:D,"Chamki",ledger!C:C,"<>December Closing CF")+ SUMIFS(ledger!J:J,ledger!B:B,_xlpm.party,ledger!E:E,"<>*RD*",ledger!D:D,"Crinkle",ledger!C:C,"<>December Closing CF") )+_xlfn.IFNA(G111,0))))} -> 961850.77 | W32: {=_xlfn.BYROW(B76, _xlfn.LAMBDA(_xlpm.party, SUMIFS(ledger!J:J, ledger!B:B, _xlpm.party, ledger!E:E, "<>*RD*", ledger!D:D, "Silky", ledger!C:C, "<>December Closing CF") )) + _xlfn.IFNA(H111, 0)} -> 1127455.2 | X32: {=_xlfn.BYROW(B76, _xlfn.LAMBDA(_xlpm.party, SUMIFS(ledger!J:J, ledger!B:B, _xlpm.party, ledger!E:E, "<>*RD*", ledger!D:D, "Slub", ledger!C:C, "<>December Closing CF") ))+ _xlfn.IFNA(I111, 0)} -> 0 | Y32: {=_xlfn.BYROW(B76, _xlfn.LAMBDA(_xlpm.party, SUMIFS(ledger!J:J, ledger!B:B, _xlpm.party, ledger!E:E, "<>*RD*", ledger!D:D, "Satin", ledger!C:C, "<>December Closing CF") ))+ _xlfn.IFNA(J111, 0)} -> 0 | Z32: {=_xlfn.BYROW(B76, _xlfn.LAMBDA(_xlpm.party, SUMIFS(ledger!J:J, ledger!B:B, _xlpm.party, ledger!E:E, "<>*RD*", ledger!D:D, "Black-Chamki", ledger!C:C, "<>December Closing CF") ))+ _xlfn.IFNA(K111, 0)} -> 0 | AA32: {=_xlfn.BYROW(B76, _xlfn.LAMBDA(_xlpm.party, SUMIFS(ledger!J:J, ledger!B:B, _xlpm.party, ledger!E:E, "<>*RD*", ledger!D:D, "Kataan", ledger!C:C, "<>December Closing CF") ))+ _xlfn.IFNA(L111, 0)} -> 0 | AB32: {=_xlfn.BYROW(B76, _xlfn.LAMBDA(_xlpm.party, SUMIFS(ledger!J:J, ledger!B:B, _xlpm.party, ledger!E:E, "<>*RD*", ledger!D:D, "Munaar", ledger!C:C, "<>December Closing CF") ))+ _xlfn.IFNA(M111, 0)} -> 0 | AC32: =V32+W32+X32+Y32+Z32+AA32+AB32 -> 2089306 | AD32: =(SUMIF(Table14[Party],Q32,Table14[Credit]))+_xlfn.IFNA(O111,0) -> 1300000 | AE32: =AC32-AD32 -> 789305.96 | AF32: 10 | AG32: 13
Q33: Ahmad Shafique | R33: {=_xlfn.BYROW(B77,_xlfn.LAMBDA(_xlpm.party,SUMIFS(ledger!G:G,ledger!B:B,_xlpm.party,ledger!E:E,"<>*RD*")))+_xlfn.IFNA(C112,0)} -> 53541 | S33: {=_xlfn.BYROW(B77, _xlfn.LAMBDA(_xlpm.party, SUMIFS(ledger!G:G, ledger!B:B, _xlpm.party, ledger!E:E, "<>*RD*") / 1.0936 ))+_xlfn.IFNA(D112,0)} -> 48958.486 | T33: {=(_xlfn.BYROW(B77,_xlfn.LAMBDA(_xlpm.party,SUMIFS(ledger!G:G,ledger!B:B,_xlpm.party,ledger!E:E,"<>*RD*",ledger!D:D,"Chamki")+SUMIFS(ledger!G:G, ledger!B:B, _xlpm.party, ledger!E:E, "<>*RD*", ledger!D:D, "Crinkle")))/1.0936)+_xlfn.IFNA(E112,0)} -> 0 | U33: {=(_xlfn.BYROW(B77,_xlfn.LAMBDA(_xlpm.party,SUMIFS(ledger!G:G,ledger!B:B,_xlpm.party,ledger!E:E,"<>*RD*",ledger!D:D,"Silky")))/1.0936)+_xlfn.IFNA(F112,0)} -> 48958.486 | V33: {=(_xlfn.BYROW(B77,_xlfn.LAMBDA(_xlpm.party, (SUMIFS(ledger!J:J,ledger!B:B,_xlpm.party,ledger!E:E,"<>*RD*",ledger!D:D,"Chamki",ledger!C:C,"<>December Closing CF")+ SUMIFS(ledger!J:J,ledger!B:B,_xlpm.party,ledger!E:E,"<>*RD*",ledger!D:D,"Crinkle",ledger!C:C,"<>December Closing CF") )+_xlfn.IFNA(G112,0))))} -> 0 | W33: {=_xlfn.BYROW(B77, _xlfn.LAMBDA(_xlpm.party, SUMIFS(ledger!J:J, ledger!B:B, _xlpm.party, ledger!E:E, "<>*RD*", ledger!D:D, "Silky", ledger!C:C, "<>December Closing CF") )) + _xlfn.IFNA(H112, 0)} -> 636460.31 | X33: {=_xlfn.BYROW(B77, _xlfn.LAMBDA(_xlpm.party, SUMIFS(ledger!J:J, ledger!B:B, _xlpm.party, ledger!E:E, "<>*RD*", ledger!D:D, "Slub", ledger!C:C, "<>December Closing CF") ))+ _xlfn.IFNA(I112, 0)} -> 0 | Y33: {=_xlfn.BYROW(B77, _xlfn.LAMBDA(_xlpm.party, SUMIFS(ledger!J:J, ledger!B:B, _xlpm.party, ledger!E:E, "<>*RD*", ledger!D:D, "Satin", ledger!C:C, "<>December Closing CF") ))+ _xlfn.IFNA(J112, 0)} -> 0 | Z33: {=_xlfn.BYROW(B77, _xlfn.LAMBDA(_xlpm.party, SUMIFS(ledger!J:J, ledger!B:B, _xlpm.party, ledger!E:E, "<>*RD*", ledger!D:D, "Black-Chamki", ledger!C:C, "<>December Closing CF") ))+ _xlfn.IFNA(K112, 0)} -> 0 | AA33: {=_xlfn.BYROW(B77, _xlfn.LAMBDA(_xlpm.party, SUMIFS(ledger!J:J, ledger!B:B, _xlpm.party, ledger!E:E, "<>*RD*", ledger!D:D, "Kataan", ledger!C:C, "<>December Closing CF") ))+ _xlfn.IFNA(L112, 0)} -> 0 | AB33: {=_xlfn.BYROW(B77, _xlfn.LAMBDA(_xlpm.party, SUMIFS(ledger!J:J, ledger!B:B, _xlpm.party, ledger!E:E, "<>*RD*", ledger!D:D, "Munaar", ledger!C:C, "<>December Closing CF") ))+ _xlfn.IFNA(M112, 0)} -> 0 | AC33: =V33+W33+X33+Y33+Z33+AA33+AB33 -> 636460.31 | AD33: =(SUMIF(Table14[Party],Q33,Table14[Credit]))+_xlfn.IFNA(O112,0) -> 636000 | AE33: =AC33-AD33 -> 460.31456 | AF33: 10 | AG33: 13
Q34: Hafiz Shawl | R34: {=_xlfn.BYROW(B78,_xlfn.LAMBDA(_xlpm.party,SUMIFS(ledger!G:G,ledger!B:B,_xlpm.party,ledger!E:E,"<>*RD*")))+_xlfn.IFNA(C113,0)} -> 1445 | S34: {=_xlfn.BYROW(B78, _xlfn.LAMBDA(_xlpm.party, SUMIFS(ledger!G:G, ledger!B:B, _xlpm.party, ledger!E:E, "<>*RD*") / 1.0936 ))+_xlfn.IFNA(D113,0)} -> 1321.3241 | T34: {=(_xlfn.BYROW(B78,_xlfn.LAMBDA(_xlpm.party,SUMIFS(ledger!G:G,ledger!B:B,_xlpm.party,ledger!E:E,"<>*RD*",ledger!D:D,"Chamki")+SUMIFS(ledger!G:G, ledger!B:B, _xlpm.party, ledger!E:E, "<>*RD*", ledger!D:D, "Crinkle")))/1.0936)+_xlfn.IFNA(E113,0)} -> 0 | U34: {=(_xlfn.BYROW(B78,_xlfn.LAMBDA(_xlpm.party,SUMIFS(ledger!G:G,ledger!B:B,_xlpm.party,ledger!E:E,"<>*RD*",ledger!D:D,"Silky")))/1.0936)+_xlfn.IFNA(F113,0)} -> 1321.3241 | V34: {=(_xlfn.BYROW(B78,_xlfn.LAMBDA(_xlpm.party, (SUMIFS(ledger!J:J,ledger!B:B,_xlpm.party,ledger!E:E,"<>*RD*",ledger!D:D,"Chamki",ledger!C:C,"<>December Closing CF")+ SUMIFS(ledger!J:J,ledger!B:B,_xlpm.party,ledger!E:E,"<>*RD*",ledger!D:D,"Crinkle",ledger!C:C,"<>December Closing CF") )+_xlfn.IFNA(G113,0))))} -> 0 | W34: {=_xlfn.BYROW(B78, _xlfn.LAMBDA(_xlpm.party, SUMIFS(ledger!J:J, ledger!B:B, _xlpm.party, ledger!E:E, "<>*RD*", ledger!D:D, "Silky", ledger!C:C, "<>December Closing CF") )) + _xlfn.IFNA(H113, 0)} -> 15855.889 | X34: {=_xlfn.BYROW(B78, _xlfn.LAMBDA(_xlpm.party, SUMIFS(ledger!J:J, ledger!B:B, _xlpm.party, ledger!E:E, "<>*RD*", ledger!D:D, "Slub", ledger!C:C, "<>December Closing CF") ))+ _xlfn.IFNA(I113, 0)} -> 0 | Y34: {=_xlfn.BYROW(B78, _xlfn.LAMBDA(_xlpm.party, SUMIFS(ledger!J:J, ledger!B:B, _xlpm.party, ledger!E:E, "<>*RD*", ledger!D:D, "Satin", ledger!C:C, "<>December Closing CF") ))+ _xlfn.IFNA(J113, 0)} -> 0 | Z34: {=_xlfn.BYROW(B78, _xlfn.LAMBDA(_xlpm.party, SUMIFS(ledger!J:J, ledger!B:B, _xlpm.party, ledger!E:E, "<>*RD*", ledger!D:D, "Black-Chamki", ledger!C:C, "<>December Closing CF") ))+ _xlfn.IFNA(K113, 0)} -> 0 | AA34: {=_xlfn.BYROW(B78, _xlfn.LAMBDA(_xlpm.party, SUMIFS(ledger!J:J, ledger!B:B, _xlpm.party, ledger!E:E, "<>*RD*", ledger!D:D, "Kataan", ledger!C:C, "<>December Closing CF") ))+ _xlfn.IFNA(L113, 0)} -> 0 | AB34: {=_xlfn.BYROW(B78, _xlfn.LAMBDA(_xlpm.party, SUMIFS(ledger!J:J, ledger!B:B, _xlpm.party, ledger!E:E, "<>*RD*", ledger!D:D, "Munaar", ledger!C:C, "<>December Closing CF") ))+ _xlfn.IFNA(M113, 0)} -> 0 | AC34: =V34+W34+X34+Y34+Z34+AA34+AB34 -> 15855.889 | AD34: =(SUMIF(Table14[Party],Q34,Table14[Credit]))+_xlfn.IFNA(O113,0) -> 15855 | AE34: =AC34-AD34 -> 0.88880761 | AF34: 10 | AG34: 13
R35: {=_xlfn.BYROW(B79,_xlfn.LAMBDA(_xlpm.party,SUMIFS(ledger!G:G,ledger!B:B,_xlpm.party,ledger!E:E,"<>*RD*")))+_xlfn.IFNA(C114,0)} -> 0 | S35: {=_xlfn.BYROW(B79, _xlfn.LAMBDA(_xlpm.party, SUMIFS(ledger!G:G, ledger!B:B, _xlpm.party, ledger!E:E, "<>*RD*") / 1.0936 ))+_xlfn.IFNA(D114,0)} -> 0 | T35: {=(_xlfn.BYROW(B79,_xlfn.LAMBDA(_xlpm.party,SUMIFS(ledger!G:G,ledger!B:B,_xlpm.party,ledger!E:E,"<>*RD*",ledger!D:D,"Chamki")+SUMIFS(ledger!G:G, ledger!B:B, _xlpm.party, ledger!E:E, "<>*RD*", ledger!D:D, "Crinkle")))/1.0936)+_xlfn.IFNA(E114,0)} -> 0 | U35: {=(_xlfn.BYROW(B79,_xlfn.LAMBDA(_xlpm.party,SUMIFS(ledger!G:G,ledger!B:B,_xlpm.party,ledger!E:E,"<>*RD*",ledger!D:D,"Silky")))/1.0936)+_xlfn.IFNA(F114,0)} -> 0 | V35: {=(_xlfn.BYROW(B79,_xlfn.LAMBDA(_xlpm.party, (SUMIFS(ledger!J:J,ledger!B:B,_xlpm.party,ledger!E:E,"<>*RD*",ledger!D:D,"Chamki",ledger!C:C,"<>December Closing CF")+ SUMIFS(ledger!J:J,ledger!B:B,_xlpm.party,ledger!E:E,"<>*RD*",ledger!D:D,"Crinkle",ledger!C:C,"<>December Closing CF") )+_xlfn.IFNA(G114,0))))} -> 0 | W35: {=_xlfn.BYROW(B79, _xlfn.LAMBDA(_xlpm.party, SUMIFS(ledger!J:J, ledger!B:B, _xlpm.party, ledger!E:E, "<>*RD*", ledger!D:D, "Silky", ledger!C:C, "<>December Closing CF") )) + _xlfn.IFNA(H114, 0)} -> 0 | X35: {=_xlfn.BYROW(B79, _xlfn.LAMBDA(_xlpm.party, SUMIFS(ledger!J:J, ledger!B:B, _xlpm.party, ledger!E:E, "<>*RD*", ledger!D:D, "Slub", ledger!C:C, "<>December Closing CF") ))+ _xlfn.IFNA(I114, 0)} -> 0 | Y35: {=_xlfn.BYROW(B79, _xlfn.LAMBDA(_xlpm.party, SUMIFS(ledger!J:J, ledger!B:B, _xlpm.party, ledger!E:E, "<>*RD*", ledger!D:D, "Satin", ledger!C:C, "<>December Closing CF") ))+ _xlfn.IFNA(J114, 0)} -> 0 | Z35: {=_xlfn.BYROW(B79, _xlfn.LAMBDA(_xlpm.party, SUMIFS(ledger!J:J, ledger!B:B, _xlpm.party, ledger!E:E, "<>*RD*", ledger!D:D, "Black-Chamki", ledger!C:C, "<>December Closing CF") ))+ _xlfn.IFNA(K114, 0)} -> 0 | AA35: {=_xlfn.BYROW(B79, _xlfn.LAMBDA(_xlpm.party, SUMIFS(ledger!J:J, ledger!B:B, _xlpm.party, ledger!E:E, "<>*RD*", ledger!D:D, "Kataan", ledger!C:C, "<>December Closing CF") ))+ _xlfn.IFNA(L114, 0)} -> 0 | AB35: {=_xlfn.BYROW(B79, _xlfn.LAMBDA(_xlpm.party, SUMIFS(ledger!J:J, ledger!B:B, _xlpm.party, ledger!E:E, "<>*RD*", ledger!D:D, "Munaar", ledger!C:C, "<>December Closing CF") ))+ _xlfn.IFNA(M114, 0)} -> 0 | AC35: =V35+W35+X35+Y35+Z35+AA35+AB35 -> 0 | AD35: =(SUMIF(Table14[Party],Q35,Table14[Credit]))+_xlfn.IFNA(O114,0) -> 0 | AE35: =AC35-AD35 -> 0 | AF35: 10 | AG35: 13
V36: {=(_xlfn.BYROW(B80,_xlfn.LAMBDA(_xlpm.party, (SUMIFS(ledger!J:J,ledger!B:B,_xlpm.party,ledger!E:E,"<>*RD*",ledger!D:D,"Chamki",ledger!C:C,"<>November Closing CF")+ SUMIFS(ledger!J:J,ledger!B:B,_xlpm.party,ledger!E:E,"<>*RD*",ledger!D:D,"Crinkle",ledger!C:C,"<>November Closing CF") )+_xlfn.IFNA(G115,0))))} -> 0 | W36: {=_xlfn.BYROW(B80, _xlfn.LAMBDA(_xlpm.party, SUMIFS(ledger!J:J, ledger!B:B, _xlpm.party, ledger!E:E, "<>*RD*", ledger!D:D, "Silky", ledger!C:C, "<>November Closing CF") )) + _xlfn.IFNA(H115, 0)} -> 0 | X36: {=_xlfn.BYROW(B80, _xlfn.LAMBDA(_xlpm.party, SUMIFS(ledger!J:J, ledger!B:B, _xlpm.party, ledger!E:E, "<>*RD*", ledger!D:D, "Slub", ledger!C:C, "<>November Closing CF") ))+ _xlfn.IFNA(I115, 0)} -> 0 | Y36: {=_xlfn.BYROW(B80, _xlfn.LAMBDA(_xlpm.party, SUMIFS(ledger!J:J, ledger!B:B, _xlpm.party, ledger!E:E, "<>*RD*", ledger!D:D, "Satin", ledger!C:C, "<>November Closing CF") ))+ _xlfn.IFNA(J115, 0)} -> 0 | Z36: {=_xlfn.BYROW(B80, _xlfn.LAMBDA(_xlpm.party, SUMIFS(ledger!J:J, ledger!B:B, _xlpm.party, ledger!E:E, "<>*RD*", ledger!D:D, "Black-Chamki", ledger!C:C, "<>November Closing CF") ))+ _xlfn.IFNA(K115, 0)} -> 0 | AA36: {=_xlfn.BYROW(B80, _xlfn.LAMBDA(_xlpm.party, SUMIFS(ledger!J:J, ledger!B:B, _xlpm.party, ledger!E:E, "<>*RD*", ledger!D:D, "Kataan", ledger!C:C, "<>November Closing CF") ))+ _xlfn.IFNA(L115, 0)} -> 0 | AB36: {=_xlfn.BYROW(B80, _xlfn.LAMBDA(_xlpm.party, SUMIFS(ledger!J:J, ledger!B:B, _xlpm.party, ledger!E:E, "<>*RD*", ledger!D:D, "Munaar", ledger!C:C, "<>November Closing CF") ))+ _xlfn.IFNA(M115, 0)} -> 0 | AC36: =V36+W36+X36+Y36+Z36+AA36+AB36 -> 0 | AD36: =(SUMIF(Table14[Party],Q36,Table14[Credit]))+_xlfn.IFNA(O115,0) -> 0
B47: Billing September
C48: Gaz | D48: Total Metres | E48: Total Chamki | F48: Total Super Silky | G48: Billing (Chamki/Crinkle) | H48: Billing (Super Chamki) | I48: Billing (Slub) | J48: Billing (Satin) | K48: Billing (Black-chamki) | L48: Billing (Kataan) | M48: Billing (Munaar) | N48: Adjusted Bill | O48: Amount Paid | P48: Balance | Q48: Rate (Chamki) | R48: Rate (Super Silky)
A49: Parties: | B49: {=_xlfn.UNIQUE(Table1[Party Name])} -> BSC | C49: {=_xlfn.BYROW(_xlfn.ANCHORARRAY(B49),_xlfn.LAMBDA(_xlpm.party,SUMIFS(ledger!G:G,ledger!B:B,_xlpm.party,ledger!E:E,"<>*RD*")))} -> 538194 | D49: {=_xlfn.BYROW(_xlfn.ANCHORARRAY(B49), _xlfn.LAMBDA(_xlpm.party, SUMIFS(ledger!G:G, ledger!B:B, _xlpm.party, ledger!E:E, "<>*RD*") / 1.0936 ))} -> 492130.58 | E49: {=(_xlfn.BYROW(_xlfn.ANCHORARRAY(B49),_xlfn.LAMBDA(_xlpm.party,SUMIFS(ledger!G:G,ledger!B:B,_xlpm.party,ledger!E:E,"<>*RD*",ledger!D:D,"Chamki")+SUMIFS(ledger!G:G, ledger!B:B, _xlpm.party, ledger!E:E, "<>*RD*", ledger!D:D, "Crinkle")))/1.0936)} -> 299517.19 | F49: {=(_xlfn.BYROW(_xlfn.ANCHORARRAY(B49),_xlfn.LAMBDA(_xlpm.party,SUMIFS(ledger!G:G,ledger!B:B,_xlpm.party,ledger!E:E,"<>*RD*",ledger!D:D,"Silky")))/1.0936)} -> 181098.21 | G49: {=(_xlfn.BYROW(B49,_xlfn.LAMBDA(_xlpm.party, (SUMIFS(ledger!J:J,ledger!B:B,_xlpm.party,ledger!E:E,"<>*RD*",ledger!D:D,"Chamki",ledger!C:C,"<>December Closing CF")+ SUMIFS(ledger!J:J,ledger!B:B,_xlpm.party,ledger!E:E,"<>*RD*",ledger!D:D,"Crinkle",ledger!C:C,"<>December Closing CF") ))))} -> 2995171.9 | H49: {=_xlfn.BYROW(B49, _xlfn.LAMBDA(_xlpm.party, SUMIFS(ledger!J:J, ledger!B:B, _xlpm.party, ledger!E:E, "<>*RD*", ledger!D:D, "Silky", ledger!C:C, "<>December Closing CF") ))} -> 2354276.7 | I49: {=_xlfn.BYROW(B49, _xlfn.LAMBDA(_xlpm.party, SUMIFS(ledger!J:J, ledger!B:B, _xlpm.party, ledger!E:E, "<>*RD*", ledger!D:D, "Slub", ledger!C:C, "<>December Closing CF") ))} -> 0 | J49: {=_xlfn.BYROW(B49, _xlfn.LAMBDA(_xlpm.party, SUMIFS(ledger!J:J, ledger!B:B, _xlpm.party, ledger!E:E, "<>*RD*", ledger!D:D, "Satin", ledger!C:C, "<>December Closing CF") ))} -> 0 | K49: {=_xlfn.BYROW(B49, _xlfn.LAMBDA(_xlpm.party, SUMIFS(ledger!J:J, ledger!B:B, _xlpm.party, ledger!E:E, "<>*RD*", ledger!D:D, "Black-chamki", ledger!C:C, "<>December Closing CF") ))} -> 0 | L49: {=_xlfn.BYROW(B49, _xlfn.LAMBDA(_xlpm.party, SUMIFS(ledger!J:J, ledger!B:B, _xlpm.party, ledger!E:E, "<>*RD*", ledger!D:D, "Kataan", ledger!C:C, "<>December Closing CF") ))} -> 126666.97 | M49: {=_xlfn.BYROW(B49, _xlfn.LAMBDA(_xlpm.party, SUMIFS(ledger!J:J, ledger!B:B, _xlpm.party, ledger!E:E, "<>*RD*", ledger!D:D, "Munaar", ledger!C:C, "<>December Closing CF") ))} -> 0 | N49: =SUM(G49:M49) -> 5476115.6 | O49: =(SUMIF(Table14[Party],B49,Table14[Credit])) -> 0 | P49: =N49-O49 -> 5476115.6 | Q49: 10 | R49: 12
B50: Ejaz Sahab | C50: 101070 | D50: 92419.532 | E50: 0 | F50: 92419.532 | G50: {=(_xlfn.BYROW(B50,_xlfn.LAMBDA(_xlpm.party, (SUMIFS(ledger!J:J,ledger!B:B,_xlpm.party,ledger!E:E,"<>*RD*",ledger!D:D,"Chamki",ledger!C:C,"<>December Closing CF")+ SUMIFS(ledger!J:J,ledger!B:B,_xlpm.party,ledger!E:E,"<>*RD*",ledger!D:D,"Crinkle",ledger!C:C,"<>December Closing CF") ))))} -> 0 | H50: {=_xlfn.BYROW(B50, _xlfn.LAMBDA(_xlpm.party, SUMIFS(ledger!J:J, ledger!B:B, _xlpm.party, ledger!E:E, "<>*RD*", ledger!D:D, "Silky", ledger!C:C, "<>December Closing CF") ))} -> 1201453.9 | I50: {=_xlfn.BYROW(B50, _xlfn.LAMBDA(_xlpm.party, SUMIFS(ledger!J:J, ledger!B:B, _xlpm.party, ledger!E:E, "<>*RD*", ledger!D:D, "Slub", ledger!C:C, "<>December Closing CF") ))} -> 0 | J50: {=_xlfn.BYROW(B50, _xlfn.LAMBDA(_xlpm.party, SUMIFS(ledger!J:J, ledger!B:B, _xlpm.party, ledger!E:E, "<>*RD*", ledger!D:D, "Satin", ledger!C:C, "<>December Closing CF") ))} -> 0 | K50: {=_xlfn.BYROW(B50, _xlfn.LAMBDA(_xlpm.party, SUMIFS(ledger!J:J, ledger!B:B, _xlpm.party, ledger!E:E, "<>*RD*", ledger!D:D, "Black-chamki", ledger!C:C, "<>December Closing CF") ))} -> 0 | L50: {=_xlfn.BYROW(B50, _xlfn.LAMBDA(_xlpm.party, SUMIFS(ledger!J:J, ledger!B:B, _xlpm.party, ledger!E:E, "<>*RD*", ledger!D:D, "Kataan", ledger!C:C, "<>December Closing CF") ))} -> 0 | M50: {=_xlfn.BYROW(B50, _xlfn.LAMBDA(_xlpm.party, SUMIFS(ledger!J:J, ledger!B:B, _xlpm.party, ledger!E:E, "<>*RD*", ledger!D:D, "Munaar", ledger!C:C, "<>December Closing CF") ))} -> 0 | N50: =SUM(G50:M50) -> 1201453.9 | O50: =(SUMIF(Table14[Party],B50,Table14[Credit])) -> 872000 | P50: =N50-O50 -> 329453.91 | Q50: 10 | R50: 12
B51: Arshad | C51: 71016 | D51: 64937.82 | E51: 45460.863 | F51: 19476.957 | G51: {=(_xlfn.BYROW(B51,_xlfn.LAMBDA(_xlpm.party, (SUMIFS(ledger!J:J,ledger!B:B,_xlpm.party,ledger!E:E,"<>*RD*",ledger!D:D,"Chamki",ledger!C:C,"<>December Closing CF")+ SUMIFS(ledger!J:J,ledger!B:B,_xlpm.party,ledger!E:E,"<>*RD*",ledger!D:D,"Crinkle",ledger!C:C,"<>December Closing CF") ))))} -> 454608.63 | H51: {=_xlfn.BYROW(B51, _xlfn.LAMBDA(_xlpm.party, SUMIFS(ledger!J:J, ledger!B:B, _xlpm.party, ledger!E:E, "<>*RD*", ledger!D:D, "Silky", ledger!C:C, "<>December Closing CF") ))} -> 253200.44 | I51: {=_xlfn.BYROW(B51, _xlfn.LAMBDA(_xlpm.party, SUMIFS(ledger!J:J, ledger!B:B, _xlpm.party, ledger!E:E, "<>*RD*", ledger!D:D, "Slub", ledger!C:C, "<>December Closing CF") ))} -> 0 | J51: {=_xlfn.BYROW(B51, _xlfn.LAMBDA(_xlpm.party, SUMIFS(ledger!J:J, ledger!B:B, _xlpm.party, ledger!E:E, "<>*RD*", ledger!D:D, "Satin", ledger!C:C, "<>December Closing CF") ))} -> 0 | K51: {=_xlfn.BYROW(B51, _xlfn.LAMBDA(_xlpm.party, SUMIFS(ledger!J:J, ledger!B:B, _xlpm.party, ledger!E:E, "<>*RD*", ledger!D:D, "Black-chamki", ledger!C:C, "<>December Closing CF") ))} -> 0 | L51: {=_xlfn.BYROW(B51, _xlfn.LAMBDA(_xlpm.party, SUMIFS(ledger!J:J, ledger!B:B, _xlpm.party, ledger!E:E, "<>*RD*", ledger!D:D, "Kataan", ledger!C:C, "<>December Closing CF") ))} -> 0 | M51: {=_xlfn.BYROW(B51, _xlfn.LAMBDA(_xlpm.party, SUMIFS(ledger!J:J, ledger!B:B, _xlpm.party, ledger!E:E, "<>*RD*", ledger!D:D, "Munaar", ledger!C:C, "<>December Closing CF") ))} -> 0 | N51: =SUM(G51:M51) -> 707809.07 | O51: =(SUMIF(Table14[Party],B51,Table14[Credit])) -> 657000 | P51: =N51-O51 -> 50809.071 | Q51: 10 | R51: 12
B52: Shehzad Kamoki | C52: 0 | D52: 0 | E52: 0 | F52: 0 | G52: {=(_xlfn.BYROW(B52,_xlfn.LAMBDA(_xlpm.party, (SUMIFS(ledger!J:J,ledger!B:B,_xlpm.party,ledger!E:E,"<>*RD*",ledger!D:D,"Chamki",ledger!C:C,"<>December Closing CF")+ SUMIFS(ledger!J:J,ledger!B:B,_xlpm.party,ledger!E:E,"<>*RD*",ledger!D:D,"Crinkle",ledger!C:C,"<>December Closing CF") ))))} -> 0 | H52: {=_xlfn.BYROW(B52, _xlfn.LAMBDA(_xlpm.party, SUMIFS(ledger!J:J, ledger!B:B, _xlpm.party, ledger!E:E, "<>*RD*", ledger!D:D, "Silky", ledger!C:C, "<>December Closing CF") ))} -> 0 | I52: {=_xlfn.BYROW(B52, _xlfn.LAMBDA(_xlpm.party, SUMIFS(ledger!J:J, ledger!B:B, _xlpm.party, ledger!E:E, "<>*RD*", ledger!D:D, "Slub", ledger!C:C, "<>December Closing CF") ))} -> 0 | J52: {=_xlfn.BYROW(B52, _xlfn.LAMBDA(_xlpm.party, SUMIFS(ledger!J:J, ledger!B:B, _xlpm.party, ledger!E:E, "<>*RD*", ledger!D:D, "Satin", ledger!C:C, "<>December Closing CF") ))} -> 0 | K52: {=_xlfn.BYROW(B52, _xlfn.LAMBDA(_xlpm.party, SUMIFS(ledger!J:J, ledger!B:B, _xlpm.party, ledger!E:E, "<>*RD*", ledger!D:D, "Black-chamki", ledger!C:C, "<>December Closing CF") ))} -> 0 | L52: {=_xlfn.BYROW(B52, _xlfn.LAMBDA(_xlpm.party, SUMIFS(ledger!J:J, ledger!B:B, _xlpm.party, ledger!E:E, "<>*RD*", ledger!D:D, "Kataan", ledger!C:C, "<>December Closing CF") ))} -> 0 | M52: {=_xlfn.BYROW(B52, _xlfn.LAMBDA(_xlpm.party, SUMIFS(ledger!J:J, ledger!B:B, _xlpm.party, ledger!E:E, "<>*RD*", ledger!D:D, "Munaar", ledger!C:C, "<>December Closing CF") ))} -> 0 | N52: =SUM(G52:M52) -> 0 | O52: =(SUMIF(Table14[Party],B52,Table14[Credit])) -> 0 | P52: =N52-O52 -> 0 | Q52: 10.5 | R52: 13
B53: Sufi Nawaz Sahab | C53: 0 | D53: 0 | E53: 0 | F53: 0 | G53: {=(_xlfn.BYROW(B53,_xlfn.LAMBDA(_xlpm.party, (SUMIFS(ledger!J:J,ledger!B:B,_xlpm.party,ledger!E:E,"<>*RD*",ledger!D:D,"Chamki",ledger!C:C,"<>December Closing CF")+ SUMIFS(ledger!J:J,ledger!B:B,_xlpm.party,ledger!E:E,"<>*RD*",ledger!D:D,"Crinkle",ledger!C:C,"<>December Closing CF") ))))} -> 0 | H53: {=_xlfn.BYROW(B53, _xlfn.LAMBDA(_xlpm.party, SUMIFS(ledger!J:J, ledger!B:B, _xlpm.party, ledger!E:E, "<>*RD*", ledger!D:D, "Silky", ledger!C:C, "<>December Closing CF") ))} -> 0 | I53: {=_xlfn.BYROW(B53, _xlfn.LAMBDA(_xlpm.party, SUMIFS(ledger!J:J, ledger!B:B, _xlpm.party, ledger!E:E, "<>*RD*", ledger!D:D, "Slub", ledger!C:C, "<>December Closing CF") ))} -> 0 | J53: {=_xlfn.BYROW(B53, _xlfn.LAMBDA(_xlpm.party, SUMIFS(ledger!J:J, ledger!B:B, _xlpm.party, ledger!E:E, "<>*RD*", ledger!D:D, "Satin", ledger!C:C, "<>December Closing CF") ))} -> 0 | K53: {=_xlfn.BYROW(B53, _xlfn.LAMBDA(_xlpm.party, SUMIFS(ledger!J:J, ledger!B:B, _xlpm.party, ledger!E:E, "<>*RD*", ledger!D:D, "Black-chamki", ledger!C:C, "<>December Closing CF") ))} -> 0 | L53: {=_xlfn.BYROW(B53, _xlfn.LAMBDA(_xlpm.party, SUMIFS(ledger!J:J, ledger!B:B, _xlpm.party, ledger!E:E, "<>*RD*", ledger!D:D, "Kataan", ledger!C:C, "<>December Closing CF") ))} -> 0 | M53: {=_xlfn.BYROW(B53, _xlfn.LAMBDA(_xlpm.party, SUMIFS(ledger!J:J, ledger!B:B, _xlpm.party, ledger!E:E, "<>*RD*", ledger!D:D, "Munaar", ledger!C:C, "<>December Closing CF") ))} -> 0 | N53: =SUM(G53:M53) -> 0 | O53: =(SUMIF(Table14[Party],B53,Table14[Credit])) -> 0 | P53: =N53-O53 -> 0 | Q53: 10 | R53: 12
B54: Sajad Khan | C54: 143586 | D54: 131296.63 | E54: 104438.55 | F54: 0 | G54: {=(_xlfn.BYROW(B54,_xlfn.LAMBDA(_xlpm.party, (SUMIFS(ledger!J:J,ledger!B:B,_xlpm.party,ledger!E:E,"<>*RD*",ledger!D:D,"Chamki",ledger!C:C,"<>December Closing CF")+ SUMIFS(ledger!J:J,ledger!B:B,_xlpm.party,ledger!E:E,"<>*RD*",ledger!D:D,"Crinkle",ledger!C:C,"<>December Closing CF") ))))} -> 1044385.5 | H54: {=_xlfn.BYROW(B54, _xlfn.LAMBDA(_xlpm.party, SUMIFS(ledger!J:J, ledger!B:B, _xlpm.party, ledger!E:E, "<>*RD*", ledger!D:D, "Silky", ledger!C:C, "<>December Closing CF") ))} -> 0 | I54: {=_xlfn.BYROW(B54, _xlfn.LAMBDA(_xlpm.party, SUMIFS(ledger!J:J, ledger!B:B, _xlpm.party, ledger!E:E, "<>*RD*", ledger!D:D, "Slub", ledger!C:C, "<>December Closing CF") ))} -> 0 | J54: {=_xlfn.BYROW(B54, _xlfn.LAMBDA(_xlpm.party, SUMIFS(ledger!J:J, ledger!B:B, _xlpm.party, ledger!E:E, "<>*RD*", ledger!D:D, "Satin", ledger!C:C, "<>December Closing CF") ))} -> 0 | K54: {=_xlfn.BYROW(B54, _xlfn.LAMBDA(_xlpm.party, SUMIFS(ledger!J:J, ledger!B:B, _xlpm.party, ledger!E:E, "<>*RD*", ledger!D:D, "Black-chamki", ledger!C:C, "<>December Closing CF") ))} -> 322297 | L54: {=_xlfn.BYROW(B54, _xlfn.LAMBDA(_xlpm.party, SUMIFS(ledger!J:J, ledger!B:B, _xlpm.party, ledger!E:E, "<>*RD*", ledger!D:D, "Kataan", ledger!C:C, "<>December Closing CF") ))} -> 0 | M54: {=_xlfn.BYROW(B54, _xlfn.LAMBDA(_xlpm.party, SUMIFS(ledger!J:J, ledger!B:B, _xlpm.party, ledger!E:E, "<>*RD*", ledger!D:D, "Munaar", ledger!C:C, "<>December Closing CF") ))} -> 0 | N54: =SUM(G54:M54) -> 1366682.5 | O54: =(SUMIF(Table14[Party],B54,Table14[Credit])) -> 1612000 | P54: =N54-O54 -> -245317.48 | Q54: 10 | R54: 12
B55: Raaz Fabrics | C55: 0 | D55: 0 | E55: 0 | F55: 0 | G55: {=(_xlfn.BYROW(B55,_xlfn.LAMBDA(_xlpm.party, (SUMIFS(ledger!J:J,ledger!B:B,_xlpm.party,ledger!E:E,"<>*RD*",ledger!D:D,"Chamki",ledger!C:C,"<>December Closing CF")+ SUMIFS(ledger!J:J,ledger!B:B,_xlpm.party,ledger!E:E,"<>*RD*",ledger!D:D,"Crinkle",ledger!C:C,"<>December Closing CF") ))))} -> 0 | H55: {=_xlfn.BYROW(B55, _xlfn.LAMBDA(_xlpm.party, SUMIFS(ledger!J:J, ledger!B:B, _xlpm.party, ledger!E:E, "<>*RD*", ledger!D:D, "Silky", ledger!C:C, "<>December Closing CF") ))} -> 0 | I55: {=_xlfn.BYROW(B55, _xlfn.LAMBDA(_xlpm.party, SUMIFS(ledger!J:J, ledger!B:B, _xlpm.party, ledger!E:E, "<>*RD*", ledger!D:D, "Slub", ledger!C:C, "<>December Closing CF") ))} -> 0 | J55: {=_xlfn.BYROW(B55, _xlfn.LAMBDA(_xlpm.party, SUMIFS(ledger!J:J, ledger!B:B, _xlpm.party, ledger!E:E, "<>*RD*", ledger!D:D, "Satin", ledger!C:C, "<>December Closing CF") ))} -> 0 | K55: {=_xlfn.BYROW(B55, _xlfn.LAMBDA(_xlpm.party, SUMIFS(ledger!J:J, ledger!B:B, _xlpm.party, ledger!E:E, "<>*RD*", ledger!D:D, "Black-chamki", ledger!C:C, "<>December Closing CF") ))} -> 0 | L55: {=_xlfn.BYROW(B55, _xlfn.LAMBDA(_xlpm.party, SUMIFS(ledger!J:J, ledger!B:B, _xlpm.party, ledger!E:E, "<>*RD*", ledger!D:D, "Kataan", ledger!C:C, "<>December Closing CF") ))} -> 0 | M55: {=_xlfn.BYROW(B55, _xlfn.LAMBDA(_xlpm.party, SUMIFS(ledger!J:J, ledger!B:B, _xlpm.party, ledger!E:E, "<>*RD*", ledger!D:D, "Munaar", ledger!C:C, "<>December Closing CF") ))} -> 0 | N55: =SUM(G55:M55) -> 0 | O55: =(SUMIF(Table14[Party],B55,Table14[Credit])) -> 0 | P55: =N55-O55 -> 0 | Q55: 10 | R55: 12
B56: Azam | C56: 205799 | D56: 188184.89 | E56: 100809.25 | F56: 87375.64 | G56: {=(_xlfn.BYROW(B56,_xlfn.LAMBDA(_xlpm.party, (SUMIFS(ledger!J:J,ledger!B:B,_xlpm.party,ledger!E:E,"<>*RD*",ledger!D:D,"Chamki",ledger!C:C,"<>December Closing CF")+ SUMIFS(ledger!J:J,ledger!B:B,_xlpm.party,ledger!E:E,"<>*RD*",ledger!D:D,"Crinkle",ledger!C:C,"<>December Closing CF") ))))} -> 1008092.5 | H56: {=_xlfn.BYROW(B56, _xlfn.LAMBDA(_xlpm.party, SUMIFS(ledger!J:J, ledger!B:B, _xlpm.party, ledger!E:E, "<>*RD*", ledger!D:D, "Silky", ledger!C:C, "<>December Closing CF") ))} -> 1135883.3 | I56: {=_xlfn.BYROW(B56, _xlfn.LAMBDA(_xlpm.party, SUMIFS(ledger!J:J, ledger!B:B, _xlpm.party, ledger!E:E, "<>*RD*", ledger!D:D, "Slub", ledger!C:C, "<>December Closing CF") ))} -> 0 | J56: {=_xlfn.BYROW(B56, _xlfn.LAMBDA(_xlpm.party, SUMIFS(ledger!J:J, ledger!B:B, _xlpm.party, ledger!E:E, "<>*RD*", ledger!D:D, "Satin", ledger!C:C, "<>December Closing CF") ))} -> 0 | K56: {=_xlfn.BYROW(B56, _xlfn.LAMBDA(_xlpm.party, SUMIFS(ledger!J:J, ledger!B:B, _xlpm.party, ledger!E:E, "<>*RD*", ledger!D:D, "Black-chamki", ledger!C:C, "<>December Closing CF") ))} -> 0 | L56: {=_xlfn.BYROW(B56, _xlfn.LAMBDA(_xlpm.party, SUMIFS(ledger!J:J, ledger!B:B, _xlpm.party, ledger!E:E, "<>*RD*", ledger!D:D, "Kataan", ledger!C:C, "<>December Closing CF") ))} -> 0 | M56: {=_xlfn.BYROW(B56, _xlfn.LAMBDA(_xlpm.party, SUMIFS(ledger!J:J, ledger!B:B, _xlpm.party, ledger!E:E, "<>*RD*", ledger!D:D, "Munaar", ledger!C:C, "<>December Closing CF") ))} -> 0 | N56: =SUM(G56:M56) -> 2143975.9 | O56: =(SUMIF(Table14[Party],B56,Table14[Credit])) -> 2313000 | P56: =N56-O56 -> -169024.14 | Q56: 10 | R56: 12
B57: Ubaidullah | C57: 47086 | D57: 43055.962 | E57: 0 | F57: 43055.962 | G57: {=(_xlfn.BYROW(B57,_xlfn.LAMBDA(_xlpm.party, (SUMIFS(ledger!J:J,ledger!B:B,_xlpm.party,ledger!E:E,"<>*RD*",ledger!D:D,"Chamki",ledger!C:C,"<>December Closing CF")+ SUMIFS(ledger!J:J,ledger!B:B,_xlpm.party,ledger!E:E,"<>*RD*",ledger!D:D,"Crinkle",ledger!C:C,"<>December Closing CF") ))))} -> 0 | H57: {=_xlfn.BYROW(B57, _xlfn.LAMBDA(_xlpm.party, SUMIFS(ledger!J:J, ledger!B:B, _xlpm.party, ledger!E:E, "<>*RD*", ledger!D:D, "Silky", ledger!C:C, "<>December Closing CF") ))} -> 559727.51 | I57: {=_xlfn.BYROW(B57, _xlfn.LAMBDA(_xlpm.party, SUMIFS(ledger!J:J, ledger!B:B, _xlpm.party, ledger!E:E, "<>*RD*", ledger!D:D, "Slub", ledger!C:C, "<>December Closing CF") ))} -> 0 | J57: {=_xlfn.BYROW(B57, _xlfn.LAMBDA(_xlpm.party, SUMIFS(ledger!J:J, ledger!B:B, _xlpm.party, ledger!E:E, "<>*RD*", ledger!D:D, "Satin", ledger!C:C, "<>December Closing CF") ))} -> 0 | K57: {=_xlfn.BYROW(B57, _xlfn.LAMBDA(_xlpm.party, SUMIFS(ledger!J:J, ledger!B:B, _xlpm.party, ledger!E:E, "<>*RD*", ledger!D:D, "Black-chamki", ledger!C:C, "<>December Closing CF") ))} -> 0 | L57: {=_xlfn.BYROW(B57, _xlfn.LAMBDA(_xlpm.party, SUMIFS(ledger!J:J, ledger!B:B, _xlpm.party, ledger!E:E, "<>*RD*", ledger!D:D, "Kataan", ledger!C:C, "<>December Closing CF") ))} -> 0 | M57: {=_xlfn.BYROW(B57, _xlfn.LAMBDA(_xlpm.party, SUMIFS(ledger!J:J, ledger!B:B, _xlpm.party, ledger!E:E, "<>*RD*", ledger!D:D, "Munaar", ledger!C:C, "<>December Closing CF") ))} -> 0 | N57: =SUM(G57:M57) -> 559727.51 | O57: =(SUMIF(Table14[Party],B57,Table14[Credit])) -> 518000 | P57: =N57-O57 -> 41727.505 | Q57: 10 | R57: 12 | U57: Row Labels | V57: Sum of Tiyaar | W57: Sum of Total
B58: Ashraf Zia | C58: 0 | D58: 0 | E58: 0 | F58: 0 | G58: {=(_xlfn.BYROW(B58,_xlfn.LAMBDA(_xlpm.party, (SUMIFS(ledger!J:J,ledger!B:B,_xlpm.party,ledger!E:E,"<>*RD*",ledger!D:D,"Chamki",ledger!C:C,"<>December Closing CF")+ SUMIFS(ledger!J:J,ledger!B:B,_xlpm.party,ledger!E:E,"<>*RD*",ledger!D:D,"Crinkle",ledger!C:C,"<>December Closing CF") ))))} -> 0 | H58: {=_xlfn.BYROW(B58, _xlfn.LAMBDA(_xlpm.party, SUMIFS(ledger!J:J, ledger!B:B, _xlpm.party, ledger!E:E, "<>*RD*", ledger!D:D, "Silky", ledger!C:C, "<>December Closing CF") ))} -> 0 | I58: {=_xlfn.BYROW(B58, _xlfn.LAMBDA(_xlpm.party, SUMIFS(ledger!J:J, ledger!B:B, _xlpm.party, ledger!E:E, "<>*RD*", ledger!D:D, "Slub", ledger!C:C, "<>December Closing CF") ))} -> 0 | J58: {=_xlfn.BYROW(B58, _xlfn.LAMBDA(_xlpm.party, SUMIFS(ledger!J:J, ledger!B:B, _xlpm.party, ledger!E:E, "<>*RD*", ledger!D:D, "Satin", ledger!C:C, "<>December Closing CF") ))} -> 0 | K58: {=_xlfn.BYROW(B58, _xlfn.LAMBDA(_xlpm.party, SUMIFS(ledger!J:J, ledger!B:B, _xlpm.party, ledger!E:E, "<>*RD*", ledger!D:D, "Black-chamki", ledger!C:C, "<>December Closing CF") ))} -> 0 | L58: {=_xlfn.BYROW(B58, _xlfn.LAMBDA(_xlpm.party, SUMIFS(ledger!J:J, ledger!B:B, _xlpm.party, ledger!E:E, "<>*RD*", ledger!D:D, "Kataan", ledger!C:C, "<>December Closing CF") ))} -> 0 | M58: {=_xlfn.BYROW(B58, _xlfn.LAMBDA(_xlpm.party, SUMIFS(ledger!J:J, ledger!B:B, _xlpm.party, ledger!E:E, "<>*RD*", ledger!D:D, "Munaar", ledger!C:C, "<>December Closing CF") ))} -> 0 | N58: =SUM(G58:M58) -> 0 | O58: =(SUMIF(Table14[Party],B58,Table14[Credit])) -> 0 | P58: =N58-O58 -> 0 | Q58: 12 | R58: 12 | U58: BSC | V58: 556955.93 | W58: 5381133.9
B59: Hafiz Qureshi | C59: 139703 | D59: 127745.98 | E59: 127745.98 | F59: 0 | G59: {=(_xlfn.BYROW(B59,_xlfn.LAMBDA(_xlpm.party, (SUMIFS(ledger!J:J,ledger!B:B,_xlpm.party,ledger!E:E,"<>*RD*",ledger!D:D,"Chamki",ledger!C:C,"<>December Closing CF")+ SUMIFS(ledger!J:J,ledger!B:B,_xlpm.party,ledger!E:E,"<>*RD*",ledger!D:D,"Crinkle",ledger!C:C,"<>December Closing CF") ))))} -> 1277459.8 | H59: {=_xlfn.BYROW(B59, _xlfn.LAMBDA(_xlpm.party, SUMIFS(ledger!J:J, ledger!B:B, _xlpm.party, ledger!E:E, "<>*RD*", ledger!D:D, "Silky", ledger!C:C, "<>December Closing CF") ))} -> 0 | I59: {=_xlfn.BYROW(B59, _xlfn.LAMBDA(_xlpm.party, SUMIFS(ledger!J:J, ledger!B:B, _xlpm.party, ledger!E:E, "<>*RD*", ledger!D:D, "Slub", ledger!C:C, "<>December Closing CF") ))} -> 0 | J59: {=_xlfn.BYROW(B59, _xlfn.LAMBDA(_xlpm.party, SUMIFS(ledger!J:J, ledger!B:B, _xlpm.party, ledger!E:E, "<>*RD*", ledger!D:D, "Satin", ledger!C:C, "<>December Closing CF") ))} -> 0 | K59: {=_xlfn.BYROW(B59, _xlfn.LAMBDA(_xlpm.party, SUMIFS(ledger!J:J, ledger!B:B, _xlpm.party, ledger!E:E, "<>*RD*", ledger!D:D, "Black-chamki", ledger!C:C, "<>December Closing CF") ))} -> 0 | L59: {=_xlfn.BYROW(B59, _xlfn.LAMBDA(_xlpm.party, SUMIFS(ledger!J:J, ledger!B:B, _xlpm.party, ledger!E:E, "<>*RD*", ledger!D:D, "Kataan", ledger!C:C, "<>December Closing CF") ))} -> 0 | M59: {=_xlfn.BYROW(B59, _xlfn.LAMBDA(_xlpm.party, SUMIFS(ledger!J:J, ledger!B:B, _xlpm.party, ledger!E:E, "<>*RD*", ledger!D:D, "Munaar", ledger!C:C, "<>December Closing CF") ))} -> 0 | N59: =SUM(G59:M59) -> 1277459.8 | O59: =(SUMIF(Table14[Party],B59,Table14[Credit])) -> 1276500 | P59: =N59-O59 -> 959.76591 | Q59: 10 | R59: 12 | U59: Ejaz Sahab | V59: 92419.532 | W59: 1109034.4
B60: Badshah Fabrics | C60: 0 | D60: 0 | E60: 0 | F60: 0 | G60: {=(_xlfn.BYROW(B60,_xlfn.LAMBDA(_xlpm.party, (SUMIFS(ledger!J:J,ledger!B:B,_xlpm.party,ledger!E:E,"<>*RD*",ledger!D:D,"Chamki",ledger!C:C,"<>December Closing CF")+ SUMIFS(ledger!J:J,ledger!B:B,_xlpm.party,ledger!E:E,"<>*RD*",ledger!D:D,"Crinkle",ledger!C:C,"<>December Closing CF") ))))} -> 0 | H60: {=_xlfn.BYROW(B60, _xlfn.LAMBDA(_xlpm.party, SUMIFS(ledger!J:J, ledger!B:B, _xlpm.party, ledger!E:E, "<>*RD*", ledger!D:D, "Silky", ledger!C:C, "<>December Closing CF") ))} -> 0 | I60: {=_xlfn.BYROW(B60, _xlfn.LAMBDA(_xlpm.party, SUMIFS(ledger!J:J, ledger!B:B, _xlpm.party, ledger!E:E, "<>*RD*", ledger!D:D, "Slub", ledger!C:C, "<>December Closing CF") ))} -> 0 | J60: {=_xlfn.BYROW(B60, _xlfn.LAMBDA(_xlpm.party, SUMIFS(ledger!J:J, ledger!B:B, _xlpm.party, ledger!E:E, "<>*RD*", ledger!D:D, "Satin", ledger!C:C, "<>December Closing CF") ))} -> 0 | K60: {=_xlfn.BYROW(B60, _xlfn.LAMBDA(_xlpm.party, SUMIFS(ledger!J:J, ledger!B:B, _xlpm.party, ledger!E:E, "<>*RD*", ledger!D:D, "Black-chamki", ledger!C:C, "<>December Closing CF") ))} -> 0 | L60: {=_xlfn.BYROW(B60, _xlfn.LAMBDA(_xlpm.party, SUMIFS(ledger!J:J, ledger!B:B, _xlpm.party, ledger!E:E, "<>*RD*", ledger!D:D, "Kataan", ledger!C:C, "<>December Closing CF") ))} -> 0 | M60: {=_xlfn.BYROW(B60, _xlfn.LAMBDA(_xlpm.party, SUMIFS(ledger!J:J, ledger!B:B, _xlpm.party, ledger!E:E, "<>*RD*", ledger!D:D, "Munaar", ledger!C:C, "<>December Closing CF") ))} -> 0 | N60: =SUM(G60:M60) -> 0 | O60: =(SUMIF(Table14[Party],B60,Table14[Credit])) -> 0 | P60: =N60-O60 -> 0 | Q60: 10 | R60: 12 | U60: Arshad | V60: 87661.851 | W60: 915572.42
B61: Gauhar Kashif | C61: 77643 | D61: 70997.623 | E61: 70997.623 | F61: 0 | G61: {=(_xlfn.BYROW(B61,_xlfn.LAMBDA(_xlpm.party, (SUMIFS(ledger!J:J,ledger!B:B,_xlpm.party,ledger!E:E,"<>*RD*",ledger!D:D,"Chamki",ledger!C:C,"<>December Closing CF")+ SUMIFS(ledger!J:J,ledger!B:B,_xlpm.party,ledger!E:E,"<>*RD*",ledger!D:D,"Crinkle",ledger!C:C,"<>December Closing CF") ))))} -> 709976.23 | H61: {=_xlfn.BYROW(B61, _xlfn.LAMBDA(_xlpm.party, SUMIFS(ledger!J:J, ledger!B:B, _xlpm.party, ledger!E:E, "<>*RD*", ledger!D:D, "Silky", ledger!C:C, "<>December Closing CF") ))} -> 0 | I61: {=_xlfn.BYROW(B61, _xlfn.LAMBDA(_xlpm.party, SUMIFS(ledger!J:J, ledger!B:B, _xlpm.party, ledger!E:E, "<>*RD*", ledger!D:D, "Slub", ledger!C:C, "<>December Closing CF") ))} -> 0 | J61: {=_xlfn.BYROW(B61, _xlfn.LAMBDA(_xlpm.party, SUMIFS(ledger!J:J, ledger!B:B, _xlpm.party, ledger!E:E, "<>*RD*", ledger!D:D, "Satin", ledger!C:C, "<>December Closing CF") ))} -> 0 | K61: {=_xlfn.BYROW(B61, _xlfn.LAMBDA(_xlpm.party, SUMIFS(ledger!J:J, ledger!B:B, _xlpm.party, ledger!E:E, "<>*RD*", ledger!D:D, "Black-chamki", ledger!C:C, "<>December Closing CF") ))} -> 0 | L61: {=_xlfn.BYROW(B61, _xlfn.LAMBDA(_xlpm.party, SUMIFS(ledger!J:J, ledger!B:B, _xlpm.party, ledger!E:E, "<>*RD*", ledger!D:D, "Kataan", ledger!C:C, "<>December Closing CF") ))} -> 0 | M61: {=_xlfn.BYROW(B61, _xlfn.LAMBDA(_xlpm.party, SUMIFS(ledger!J:J, ledger!B:B, _xlpm.party, ledger!E:E, "<>*RD*", ledger!D:D, "Munaar", ledger!C:C, "<>December Closing CF") ))} -> 0 | N61: =SUM(G61:M61) -> 709976.23 | O61: =(SUMIF(Table14[Party],B61,Table14[Credit])) -> 728245 | P61: =N61-O61 -> -18268.775 | Q61: 10 | R61: 12 | U61: Shehzad Kamoki | V61: 0 | W61: 0
B62: Amjad 7up | C62: 0 | D62: 0 | E62: 0 | F62: 0 | G62: {=(_xlfn.BYROW(B62,_xlfn.LAMBDA(_xlpm.party, (SUMIFS(ledger!J:J,ledger!B:B,_xlpm.party,ledger!E:E,"<>*RD*",ledger!D:D,"Chamki",ledger!C:C,"<>December Closing CF")+ SUMIFS(ledger!J:J,ledger!B:B,_xlpm.party,ledger!E:E,"<>*RD*",ledger!D:D,"Crinkle",ledger!C:C,"<>December Closing CF") ))))} -> 0 | H62: {=_xlfn.BYROW(B62, _xlfn.LAMBDA(_xlpm.party, SUMIFS(ledger!J:J, ledger!B:B, _xlpm.party, ledger!E:E, "<>*RD*", ledger!D:D, "Silky", ledger!C:C, "<>December Closing CF") ))} -> 0 | I62: {=_xlfn.BYROW(B62, _xlfn.LAMBDA(_xlpm.party, SUMIFS(ledger!J:J, ledger!B:B, _xlpm.party, ledger!E:E, "<>*RD*", ledger!D:D, "Slub", ledger!C:C, "<>December Closing CF") ))} -> 0 | J62: {=_xlfn.BYROW(B62, _xlfn.LAMBDA(_xlpm.party, SUMIFS(ledger!J:J, ledger!B:B, _xlpm.party, ledger!E:E, "<>*RD*", ledger!D:D, "Satin", ledger!C:C, "<>December Closing CF") ))} -> 0 | K62: {=_xlfn.BYROW(B62, _xlfn.LAMBDA(_xlpm.party, SUMIFS(ledger!J:J, ledger!B:B, _xlpm.party, ledger!E:E, "<>*RD*", ledger!D:D, "Black-chamki", ledger!C:C, "<>December Closing CF") ))} -> 0 | L62: {=_xlfn.BYROW(B62, _xlfn.LAMBDA(_xlpm.party, SUMIFS(ledger!J:J, ledger!B:B, _xlpm.party, ledger!E:E, "<>*RD*", ledger!D:D, "Kataan", ledger!C:C, "<>December Closing CF") ))} -> 0 | M62: {=_xlfn.BYROW(B62, _xlfn.LAMBDA(_xlpm.party, SUMIFS(ledger!J:J, ledger!B:B, _xlpm.party, ledger!E:E, "<>*RD*", ledger!D:D, "Munaar", ledger!C:C, "<>December Closing CF") ))} -> 0 | N62: =SUM(G62:M62) -> 0 | O62: =(SUMIF(Table14[Party],B62,Table14[Credit])) -> 0 | P62: =N62-O62 -> 0 | Q62: 10 | R62: 12 | U62: Sufi Nawaz Sahab | V62: 0 | W62: 0
B63: Hazrat Khan | C63: 0 | D63: 0 | E63: 0 | F63: 0 | G63: {=(_xlfn.BYROW(B63,_xlfn.LAMBDA(_xlpm.party, (SUMIFS(ledger!J:J,ledger!B:B,_xlpm.party,ledger!E:E,"<>*RD*",ledger!D:D,"Chamki",ledger!C:C,"<>December Closing CF")+ SUMIFS(ledger!J:J,ledger!B:B,_xlpm.party,ledger!E:E,"<>*RD*",ledger!D:D,"Crinkle",ledger!C:C,"<>December Closing CF") ))))} -> 0 | H63: {=_xlfn.BYROW(B63, _xlfn.LAMBDA(_xlpm.party, SUMIFS(ledger!J:J, ledger!B:B, _xlpm.party, ledger!E:E, "<>*RD*", ledger!D:D, "Silky", ledger!C:C, "<>December Closing CF") ))} -> 0 | I63: {=_xlfn.BYROW(B63, _xlfn.LAMBDA(_xlpm.party, SUMIFS(ledger!J:J, ledger!B:B, _xlpm.party, ledger!E:E, "<>*RD*", ledger!D:D, "Slub", ledger!C:C, "<>December Closing CF") ))} -> 0 | J63: {=_xlfn.BYROW(B63, _xlfn.LAMBDA(_xlpm.party, SUMIFS(ledger!J:J, ledger!B:B, _xlpm.party, ledger!E:E, "<>*RD*", ledger!D:D, "Satin", ledger!C:C, "<>December Closing CF") ))} -> 0 | K63: {=_xlfn.BYROW(B63, _xlfn.LAMBDA(_xlpm.party, SUMIFS(ledger!J:J, ledger!B:B, _xlpm.party, ledger!E:E, "<>*RD*", ledger!D:D, "Black-chamki", ledger!C:C, "<>December Closing CF") ))} -> 0 | L63: {=_xlfn.BYROW(B63, _xlfn.LAMBDA(_xlpm.party, SUMIFS(ledger!J:J, ledger!B:B, _xlpm.party, ledger!E:E, "<>*RD*", ledger!D:D, "Kataan", ledger!C:C, "<>December Closing CF") ))} -> 0 | M63: {=_xlfn.BYROW(B63, _xlfn.LAMBDA(_xlpm.party, SUMIFS(ledger!J:J, ledger!B:B, _xlpm.party, ledger!E:E, "<>*RD*", ledger!D:D, "Munaar", ledger!C:C, "<>December Closing CF") ))} -> 0 | N63: =SUM(G63:M63) -> 0 | O63: =(SUMIF(Table14[Party],B63,Table14[Credit])) -> 0 | P63: =N63-O63 -> 0 | Q63: 10 | R63: 12 | U63: Sajad Khan | V63: 131296.63 | W63: 1044385.5
B64: Haseeb Shamsi | C64: 0 | D64: 0 | E64: 0 | F64: 0 | G64: {=(_xlfn.BYROW(B64,_xlfn.LAMBDA(_xlpm.party, (SUMIFS(ledger!J:J,ledger!B:B,_xlpm.party,ledger!E:E,"<>*RD*",ledger!D:D,"Chamki",ledger!C:C,"<>December Closing CF")+ SUMIFS(ledger!J:J,ledger!B:B,_xlpm.party,ledger!E:E,"<>*RD*",ledger!D:D,"Crinkle",ledger!C:C,"<>December Closing CF") ))))} -> 0 | H64: {=_xlfn.BYROW(B64, _xlfn.LAMBDA(_xlpm.party, SUMIFS(ledger!J:J, ledger!B:B, _xlpm.party, ledger!E:E, "<>*RD*", ledger!D:D, "Silky", ledger!C:C, "<>December Closing CF") ))} -> 0 | I64: {=_xlfn.BYROW(B64, _xlfn.LAMBDA(_xlpm.party, SUMIFS(ledger!J:J, ledger!B:B, _xlpm.party, ledger!E:E, "<>*RD*", ledger!D:D, "Slub", ledger!C:C, "<>December Closing CF") ))} -> 0 | J64: {=_xlfn.BYROW(B64, _xlfn.LAMBDA(_xlpm.party, SUMIFS(ledger!J:J, ledger!B:B, _xlpm.party, ledger!E:E, "<>*RD*", ledger!D:D, "Satin", ledger!C:C, "<>December Closing CF") ))} -> 0 | K64: {=_xlfn.BYROW(B64, _xlfn.LAMBDA(_xlpm.party, SUMIFS(ledger!J:J, ledger!B:B, _xlpm.party, ledger!E:E, "<>*RD*", ledger!D:D, "Black-chamki", ledger!C:C, "<>December Closing CF") ))} -> 0 | L64: {=_xlfn.BYROW(B64, _xlfn.LAMBDA(_xlpm.party, SUMIFS(ledger!J:J, ledger!B:B, _xlpm.party, ledger!E:E, "<>*RD*", ledger!D:D, "Kataan", ledger!C:C, "<>December Closing CF") ))} -> 0 | M64: {=_xlfn.BYROW(B64, _xlfn.LAMBDA(_xlpm.party, SUMIFS(ledger!J:J, ledger!B:B, _xlpm.party, ledger!E:E, "<>*RD*", ledger!D:D, "Munaar", ledger!C:C, "<>December Closing CF") ))} -> 0 | N64: =SUM(G64:M64) -> 0 | O64: =(SUMIF(Table14[Party],B64,Table14[Credit])) -> 0 | P64: =N64-O64 -> 0 | Q64: 10 | R64: 12 | U64: Raaz Fabrics | V64: 0 | W64: 0
B65: Faizan | C65: 70436 | D65: 64407.462 | E65: 0 | F65: 64407.462 | G65: {=(_xlfn.BYROW(B65,_xlfn.LAMBDA(_xlpm.party, (SUMIFS(ledger!J:J,ledger!B:B,_xlpm.party,ledger!E:E,"<>*RD*",ledger!D:D,"Chamki",ledger!C:C,"<>December Closing CF")+ SUMIFS(ledger!J:J,ledger!B:B,_xlpm.party,ledger!E:E,"<>*RD*",ledger!D:D,"Crinkle",ledger!C:C,"<>December Closing CF") ))))} -> 30000 | H65: {=_xlfn.BYROW(B65, _xlfn.LAMBDA(_xlpm.party, SUMIFS(ledger!J:J, ledger!B:B, _xlpm.party, ledger!E:E, "<>*RD*", ledger!D:D, "Silky", ledger!C:C, "<>December Closing CF") ))} -> 837297 | I65: {=_xlfn.BYROW(B65, _xlfn.LAMBDA(_xlpm.party, SUMIFS(ledger!J:J, ledger!B:B, _xlpm.party, ledger!E:E, "<>*RD*", ledger!D:D, "Slub", ledger!C:C, "<>December Closing CF") ))} -> 0 | J65: {=_xlfn.BYROW(B65, _xlfn.LAMBDA(_xlpm.party, SUMIFS(ledger!J:J, ledger!B:B, _xlpm.party, ledger!E:E, "<>*RD*", ledger!D:D, "Satin", ledger!C:C, "<>December Closing CF") ))} -> 0 | K65: {=_xlfn.BYROW(B65, _xlfn.LAMBDA(_xlpm.party, SUMIFS(ledger!J:J, ledger!B:B, _xlpm.party, ledger!E:E, "<>*RD*", ledger!D:D, "Black-chamki", ledger!C:C, "<>December Closing CF") ))} -> 0 | L65: {=_xlfn.BYROW(B65, _xlfn.LAMBDA(_xlpm.party, SUMIFS(ledger!J:J, ledger!B:B, _xlpm.party, ledger!E:E, "<>*RD*", ledger!D:D, "Kataan", ledger!C:C, "<>December Closing CF") ))} -> 0 | M65: {=_xlfn.BYROW(B65, _xlfn.LAMBDA(_xlpm.party, SUMIFS(ledger!J:J, ledger!B:B, _xlpm.party, ledger!E:E, "<>*RD*", ledger!D:D, "Munaar", ledger!C:C, "<>December Closing CF") ))} -> 0 | N65: =SUM(G65:M65) -> 867297 | O65: =(SUMIF(Table14[Party],B65,Table14[Credit])) -> 1108616 | P65: =N65-O65 -> -241319 | Q65: 10 | R65: 13 | U65: Azam | V65: 188184.89 | W65: 2056600.2
B66: Shafique Ansari | C66: 0 | D66: 0 | E66: 0 | F66: 0 | G66: {=(_xlfn.BYROW(B66,_xlfn.LAMBDA(_xlpm.party, (SUMIFS(ledger!J:J,ledger!B:B,_xlpm.party,ledger!E:E,"<>*RD*",ledger!D:D,"Chamki",ledger!C:C,"<>December Closing CF")+ SUMIFS(ledger!J:J,ledger!B:B,_xlpm.party,ledger!E:E,"<>*RD*",ledger!D:D,"Crinkle",ledger!C:C,"<>December Closing CF") ))))} -> 0 | H66: {=_xlfn.BYROW(B66, _xlfn.LAMBDA(_xlpm.party, SUMIFS(ledger!J:J, ledger!B:B, _xlpm.party, ledger!E:E, "<>*RD*", ledger!D:D, "Silky", ledger!C:C, "<>December Closing CF") ))} -> 0 | I66: {=_xlfn.BYROW(B66, _xlfn.LAMBDA(_xlpm.party, SUMIFS(ledger!J:J, ledger!B:B, _xlpm.party, ledger!E:E, "<>*RD*", ledger!D:D, "Slub", ledger!C:C, "<>December Closing CF") ))} -> 0 | J66: {=_xlfn.BYROW(B66, _xlfn.LAMBDA(_xlpm.party, SUMIFS(ledger!J:J, ledger!B:B, _xlpm.party, ledger!E:E, "<>*RD*", ledger!D:D, "Satin", ledger!C:C, "<>December Closing CF") ))} -> 0 | K66: {=_xlfn.BYROW(B66, _xlfn.LAMBDA(_xlpm.party, SUMIFS(ledger!J:J, ledger!B:B, _xlpm.party, ledger!E:E, "<>*RD*", ledger!D:D, "Black-chamki", ledger!C:C, "<>December Closing CF") ))} -> 0 | L66: {=_xlfn.BYROW(B66, _xlfn.LAMBDA(_xlpm.party, SUMIFS(ledger!J:J, ledger!B:B, _xlpm.party, ledger!E:E, "<>*RD*", ledger!D:D, "Kataan", ledger!C:C, "<>December Closing CF") ))} -> 0 | M66: {=_xlfn.BYROW(B66, _xlfn.LAMBDA(_xlpm.party, SUMIFS(ledger!J:J, ledger!B:B, _xlpm.party, ledger!E:E, "<>*RD*", ledger!D:D, "Munaar", ledger!C:C, "<>December Closing CF") ))} -> 0 | N66: =SUM(G66:M66) -> 0 | O66: =(SUMIF(Table14[Party],B66,Table14[Credit])) -> 0 | P66: =N66-O66 -> 0 | Q66: 10 | R66: 12 | U66: Ubaidullah | V66: 43055.962 | W66: 516671.54
B67: Amjad sohail | C67: 124922 | D67: 114230.07 | E67: 111463.97 | F67: 2766.0936 | G67: {=(_xlfn.BYROW(B67,_xlfn.LAMBDA(_xlpm.party, (SUMIFS(ledger!J:J,ledger!B:B,_xlpm.party,ledger!E:E,"<>*RD*",ledger!D:D,"Chamki",ledger!C:C,"<>December Closing CF")+ SUMIFS(ledger!J:J,ledger!B:B,_xlpm.party,ledger!E:E,"<>*RD*",ledger!D:D,"Crinkle",ledger!C:C,"<>December Closing CF") ))))} -> 1114639.7 | H67: {=_xlfn.BYROW(B67, _xlfn.LAMBDA(_xlpm.party, SUMIFS(ledger!J:J, ledger!B:B, _xlpm.party, ledger!E:E, "<>*RD*", ledger!D:D, "Silky", ledger!C:C, "<>December Closing CF") ))} -> 35959.217 | I67: {=_xlfn.BYROW(B67, _xlfn.LAMBDA(_xlpm.party, SUMIFS(ledger!J:J, ledger!B:B, _xlpm.party, ledger!E:E, "<>*RD*", ledger!D:D, "Slub", ledger!C:C, "<>December Closing CF") ))} -> 0 | J67: {=_xlfn.BYROW(B67, _xlfn.LAMBDA(_xlpm.party, SUMIFS(ledger!J:J, ledger!B:B, _xlpm.party, ledger!E:E, "<>*RD*", ledger!D:D, "Satin", ledger!C:C, "<>December Closing CF") ))} -> 0 | K67: {=_xlfn.BYROW(B67, _xlfn.LAMBDA(_xlpm.party, SUMIFS(ledger!J:J, ledger!B:B, _xlpm.party, ledger!E:E, "<>*RD*", ledger!D:D, "Black-chamki", ledger!C:C, "<>December Closing CF") ))} -> 0 | L67: {=_xlfn.BYROW(B67, _xlfn.LAMBDA(_xlpm.party, SUMIFS(ledger!J:J, ledger!B:B, _xlpm.party, ledger!E:E, "<>*RD*", ledger!D:D, "Kataan", ledger!C:C, "<>December Closing CF") ))} -> 0 | M67: {=_xlfn.BYROW(B67, _xlfn.LAMBDA(_xlpm.party, SUMIFS(ledger!J:J, ledger!B:B, _xlpm.party, ledger!E:E, "<>*RD*", ledger!D:D, "Munaar", ledger!C:C, "<>December Closing CF") ))} -> 0 | N67: =SUM(G67:M67) -> 1150598.9 | O67: =(SUMIF(Table14[Party],B67,Table14[Credit])) -> 1508520 | P67: =N67-O67 -> -357921.06 | Q67: 10 | R67: 12 | U67: Ashraf Zia | V67: 0 | W67: 0
B68: Salman Zaffar | C68: 68676 | D68: 62798.098 | E68: 20323.702 | F68: 0 | G68: {=(_xlfn.BYROW(B68,_xlfn.LAMBDA(_xlpm.party, (SUMIFS(ledger!J:J,ledger!B:B,_xlpm.party,ledger!E:E,"<>*RD*",ledger!D:D,"Chamki",ledger!C:C,"<>December Closing CF")+ SUMIFS(ledger!J:J,ledger!B:B,_xlpm.party,ledger!E:E,"<>*RD*",ledger!D:D,"Crinkle",ledger!C:C,"<>December Closing CF") ))))} -> 203237.02 | H68: {=_xlfn.BYROW(B68, _xlfn.LAMBDA(_xlpm.party, SUMIFS(ledger!J:J, ledger!B:B, _xlpm.party, ledger!E:E, "<>*RD*", ledger!D:D, "Silky", ledger!C:C, "<>December Closing CF") ))} -> 0 | I68: {=_xlfn.BYROW(B68, _xlfn.LAMBDA(_xlpm.party, SUMIFS(ledger!J:J, ledger!B:B, _xlpm.party, ledger!E:E, "<>*RD*", ledger!D:D, "Slub", ledger!C:C, "<>December Closing CF") ))} -> 0 | J68: {=_xlfn.BYROW(B68, _xlfn.LAMBDA(_xlpm.party, SUMIFS(ledger!J:J, ledger!B:B, _xlpm.party, ledger!E:E, "<>*RD*", ledger!D:D, "Satin", ledger!C:C, "<>December Closing CF") ))} -> 0 | K68: {=_xlfn.BYROW(B68, _xlfn.LAMBDA(_xlpm.party, SUMIFS(ledger!J:J, ledger!B:B, _xlpm.party, ledger!E:E, "<>*RD*", ledger!D:D, "Black-chamki", ledger!C:C, "<>December Closing CF") ))} -> 0 | L68: {=_xlfn.BYROW(B68, _xlfn.LAMBDA(_xlpm.party, SUMIFS(ledger!J:J, ledger!B:B, _xlpm.party, ledger!E:E, "<>*RD*", ledger!D:D, "Kataan", ledger!C:C, "<>December Closing CF") ))} -> 424743.96 | M68: {=_xlfn.BYROW(B68, _xlfn.LAMBDA(_xlpm.party, SUMIFS(ledger!J:J, ledger!B:B, _xlpm.party, ledger!E:E, "<>*RD*", ledger!D:D, "Munaar", ledger!C:C, "<>December Closing CF") ))} -> 0 | N68: =SUM(G68:M68) -> 627980.98 | O68: =(SUMIF(Table14[Party],B68,Table14[Credit])) -> 1150000 | P68: =N68-O68 -> -522019.02 | Q68: 10 | R68: 12 | U68: Hafiz Qureshi | V68: 176970.56 | W68: 1769705.6
B69: Shahid Qasayi | C69: 78776 | D69: 72033.65 | E69: 72033.65 | F69: 0 | G69: {=(_xlfn.BYROW(B69,_xlfn.LAMBDA(_xlpm.party, (SUMIFS(ledger!J:J,ledger!B:B,_xlpm.party,ledger!E:E,"<>*RD*",ledger!D:D,"Chamki",ledger!C:C,"<>December Closing CF")+ SUMIFS(ledger!J:J,ledger!B:B,_xlpm.party,ledger!E:E,"<>*RD*",ledger!D:D,"Crinkle",ledger!C:C,"<>December Closing CF") ))))} -> 720336.5 | H69: {=_xlfn.BYROW(B69, _xlfn.LAMBDA(_xlpm.party, SUMIFS(ledger!J:J, ledger!B:B, _xlpm.party, ledger!E:E, "<>*RD*", ledger!D:D, "Silky", ledger!C:C, "<>December Closing CF") ))} -> 0 | I69: {=_xlfn.BYROW(B69, _xlfn.LAMBDA(_xlpm.party, SUMIFS(ledger!J:J, ledger!B:B, _xlpm.party, ledger!E:E, "<>*RD*", ledger!D:D, "Slub", ledger!C:C, "<>December Closing CF") ))} -> 0 | J69: {=_xlfn.BYROW(B69, _xlfn.LAMBDA(_xlpm.party, SUMIFS(ledger!J:J, ledger!B:B, _xlpm.party, ledger!E:E, "<>*RD*", ledger!D:D, "Satin", ledger!C:C, "<>December Closing CF") ))} -> 0 | K69: {=_xlfn.BYROW(B69, _xlfn.LAMBDA(_xlpm.party, SUMIFS(ledger!J:J, ledger!B:B, _xlpm.party, ledger!E:E, "<>*RD*", ledger!D:D, "Black-chamki", ledger!C:C, "<>December Closing CF") ))} -> 0 | L69: {=_xlfn.BYROW(B69, _xlfn.LAMBDA(_xlpm.party, SUMIFS(ledger!J:J, ledger!B:B, _xlpm.party, ledger!E:E, "<>*RD*", ledger!D:D, "Kataan", ledger!C:C, "<>December Closing CF") ))} -> 0 | M69: {=_xlfn.BYROW(B69, _xlfn.LAMBDA(_xlpm.party, SUMIFS(ledger!J:J, ledger!B:B, _xlpm.party, ledger!E:E, "<>*RD*", ledger!D:D, "Munaar", ledger!C:C, "<>December Closing CF") ))} -> 0 | N69: =SUM(G69:M69) -> 720336.5 | O69: =(SUMIF(Table14[Party],B69,Table14[Credit])) -> 863242 | P69: =N69-O69 -> -142905.5 | Q69: 10 | R69: 12 | U69: Badshah Fabrics | V69: 0 | W69: 0
B70: Hameed corporation | C70: 0 | D70: 0 | E70: 0 | F70: 0 | G70: {=(_xlfn.BYROW(B70,_xlfn.LAMBDA(_xlpm.party, (SUMIFS(ledger!J:J,ledger!B:B,_xlpm.party,ledger!E:E,"<>*RD*",ledger!D:D,"Chamki",ledger!C:C,"<>December Closing CF")+ SUMIFS(ledger!J:J,ledger!B:B,_xlpm.party,ledger!E:E,"<>*RD*",ledger!D:D,"Crinkle",ledger!C:C,"<>December Closing CF") ))))} -> 0 | H70: {=_xlfn.BYROW(B70, _xlfn.LAMBDA(_xlpm.party, SUMIFS(ledger!J:J, ledger!B:B, _xlpm.party, ledger!E:E, "<>*RD*", ledger!D:D, "Silky", ledger!C:C, "<>December Closing CF") ))} -> 0 | I70: {=_xlfn.BYROW(B70, _xlfn.LAMBDA(_xlpm.party, SUMIFS(ledger!J:J, ledger!B:B, _xlpm.party, ledger!E:E, "<>*RD*", ledger!D:D, "Slub", ledger!C:C, "<>December Closing CF") ))} -> 0 | J70: {=_xlfn.BYROW(B70, _xlfn.LAMBDA(_xlpm.party, SUMIFS(ledger!J:J, ledger!B:B, _xlpm.party, ledger!E:E, "<>*RD*", ledger!D:D, "Satin", ledger!C:C, "<>December Closing CF") ))} -> 0 | K70: {=_xlfn.BYROW(B70, _xlfn.LAMBDA(_xlpm.party, SUMIFS(ledger!J:J, ledger!B:B, _xlpm.party, ledger!E:E, "<>*RD*", ledger!D:D, "Black-chamki", ledger!C:C, "<>December Closing CF") ))} -> 0 | L70: {=_xlfn.BYROW(B70, _xlfn.LAMBDA(_xlpm.party, SUMIFS(ledger!J:J, ledger!B:B, _xlpm.party, ledger!E:E, "<>*RD*", ledger!D:D, "Kataan", ledger!C:C, "<>December Closing CF") ))} -> 0 | M70: {=_xlfn.BYROW(B70, _xlfn.LAMBDA(_xlpm.party, SUMIFS(ledger!J:J, ledger!B:B, _xlpm.party, ledger!E:E, "<>*RD*", ledger!D:D, "Munaar", ledger!C:C, "<>December Closing CF") ))} -> 0 | N70: =SUM(G70:M70) -> 0 | O70: =(SUMIF(Table14[Party],B70,Table14[Credit])) -> 0 | P70: =N70-O70 -> 0 | U70: Amjad 7up | V70: 0 | W70: 0
B71: ibraheem behraam | C71: 55681 | D71: 50915.326 | E71: 0 | F71: 50915.326 | G71: {=(_xlfn.BYROW(B71,_xlfn.LAMBDA(_xlpm.party, (SUMIFS(ledger!J:J,ledger!B:B,_xlpm.party,ledger!E:E,"<>*RD*",ledger!D:D,"Chamki",ledger!C:C,"<>December Closing CF")+ SUMIFS(ledger!J:J,ledger!B:B,_xlpm.party,ledger!E:E,"<>*RD*",ledger!D:D,"Crinkle",ledger!C:C,"<>December Closing CF") ))))} -> 0 | H71: {=_xlfn.BYROW(B71, _xlfn.LAMBDA(_xlpm.party, SUMIFS(ledger!J:J, ledger!B:B, _xlpm.party, ledger!E:E, "<>*RD*", ledger!D:D, "Silky", ledger!C:C, "<>December Closing CF") ))} -> 661899.23 | I71: {=_xlfn.BYROW(B71, _xlfn.LAMBDA(_xlpm.party, SUMIFS(ledger!J:J, ledger!B:B, _xlpm.party, ledger!E:E, "<>*RD*", ledger!D:D, "Slub", ledger!C:C, "<>December Closing CF") ))} -> 0 | J71: {=_xlfn.BYROW(B71, _xlfn.LAMBDA(_xlpm.party, SUMIFS(ledger!J:J, ledger!B:B, _xlpm.party, ledger!E:E, "<>*RD*", ledger!D:D, "Satin", ledger!C:C, "<>December Closing CF") ))} -> 0 | K71: {=_xlfn.BYROW(B71, _xlfn.LAMBDA(_xlpm.party, SUMIFS(ledger!J:J, ledger!B:B, _xlpm.party, ledger!E:E, "<>*RD*", ledger!D:D, "Black-chamki", ledger!C:C, "<>December Closing CF") ))} -> 0 | L71: {=_xlfn.BYROW(B71, _xlfn.LAMBDA(_xlpm.party, SUMIFS(ledger!J:J, ledger!B:B, _xlpm.party, ledger!E:E, "<>*RD*", ledger!D:D, "Kataan", ledger!C:C, "<>December Closing CF") ))} -> 0 | M71: {=_xlfn.BYROW(B71, _xlfn.LAMBDA(_xlpm.party, SUMIFS(ledger!J:J, ledger!B:B, _xlpm.party, ledger!E:E, "<>*RD*", ledger!D:D, "Munaar", ledger!C:C, "<>December Closing CF") ))} -> 0 | N71: =SUM(G71:M71) -> 661899.23 | O71: =(SUMIF(Table14[Party],B71,Table14[Credit])) -> 625000 | P71: =N71-O71 -> 36899.232 | U71: Hazrat Khan | V71: 0 | W71: 0
B72: Zia-ullah karachi | C72: 0 | D72: 0 | E72: 0 | F72: 0 | G72: {=(_xlfn.BYROW(B72,_xlfn.LAMBDA(_xlpm.party, (SUMIFS(ledger!J:J,ledger!B:B,_xlpm.party,ledger!E:E,"<>*RD*",ledger!D:D,"Chamki",ledger!C:C,"<>December Closing CF")+ SUMIFS(ledger!J:J,ledger!B:B,_xlpm.party,ledger!E:E,"<>*RD*",ledger!D:D,"Crinkle",ledger!C:C,"<>December Closing CF") ))))} -> 0 | H72: {=_xlfn.BYROW(B72, _xlfn.LAMBDA(_xlpm.party, SUMIFS(ledger!J:J, ledger!B:B, _xlpm.party, ledger!E:E, "<>*RD*", ledger!D:D, "Silky", ledger!C:C, "<>December Closing CF") ))} -> 0 | I72: {=_xlfn.BYROW(B72, _xlfn.LAMBDA(_xlpm.party, SUMIFS(ledger!J:J, ledger!B:B, _xlpm.party, ledger!E:E, "<>*RD*", ledger!D:D, "Slub", ledger!C:C, "<>December Closing CF") ))} -> 0 | J72: {=_xlfn.BYROW(B72, _xlfn.LAMBDA(_xlpm.party, SUMIFS(ledger!J:J, ledger!B:B, _xlpm.party, ledger!E:E, "<>*RD*", ledger!D:D, "Satin", ledger!C:C, "<>December Closing CF") ))} -> 0 | K72: {=_xlfn.BYROW(B72, _xlfn.LAMBDA(_xlpm.party, SUMIFS(ledger!J:J, ledger!B:B, _xlpm.party, ledger!E:E, "<>*RD*", ledger!D:D, "Black-chamki", ledger!C:C, "<>December Closing CF") ))} -> 0 | L72: {=_xlfn.BYROW(B72, _xlfn.LAMBDA(_xlpm.party, SUMIFS(ledger!J:J, ledger!B:B, _xlpm.party, ledger!E:E, "<>*RD*", ledger!D:D, "Kataan", ledger!C:C, "<>December Closing CF") ))} -> 0 | M72: {=_xlfn.BYROW(B72, _xlfn.LAMBDA(_xlpm.party, SUMIFS(ledger!J:J, ledger!B:B, _xlpm.party, ledger!E:E, "<>*RD*", ledger!D:D, "Munaar", ledger!C:C, "<>December Closing CF") ))} -> 0 | N72: =SUM(G72:M72) -> 0 | O72: =(SUMIF(Table14[Party],B72,Table14[Credit])) -> 0 | P72: =N72-O72 -> 0 | U72: Haseeb Shamsi | V72: 0 | W72: 0
B73: ZA | C73: 0 | D73: 0 | E73: 0 | F73: 0 | G73: {=(_xlfn.BYROW(B73,_xlfn.LAMBDA(_xlpm.party, (SUMIFS(ledger!J:J,ledger!B:B,_xlpm.party,ledger!E:E,"<>*RD*",ledger!D:D,"Chamki",ledger!C:C,"<>December Closing CF")+ SUMIFS(ledger!J:J,ledger!B:B,_xlpm.party,ledger!E:E,"<>*RD*",ledger!D:D,"Crinkle",ledger!C:C,"<>December Closing CF") ))))} -> 0 | H73: {=_xlfn.BYROW(B73, _xlfn.LAMBDA(_xlpm.party, SUMIFS(ledger!J:J, ledger!B:B, _xlpm.party, ledger!E:E, "<>*RD*", ledger!D:D, "Silky", ledger!C:C, "<>December Closing CF") ))} -> 0 | I73: {=_xlfn.BYROW(B73, _xlfn.LAMBDA(_xlpm.party, SUMIFS(ledger!J:J, ledger!B:B, _xlpm.party, ledger!E:E, "<>*RD*", ledger!D:D, "Slub", ledger!C:C, "<>December Closing CF") ))} -> 0 | J73: {=_xlfn.BYROW(B73, _xlfn.LAMBDA(_xlpm.party, SUMIFS(ledger!J:J, ledger!B:B, _xlpm.party, ledger!E:E, "<>*RD*", ledger!D:D, "Satin", ledger!C:C, "<>December Closing CF") ))} -> 0 | K73: {=_xlfn.BYROW(B73, _xlfn.LAMBDA(_xlpm.party, SUMIFS(ledger!J:J, ledger!B:B, _xlpm.party, ledger!E:E, "<>*RD*", ledger!D:D, "Black-chamki", ledger!C:C, "<>December Closing CF") ))} -> 0 | L73: {=_xlfn.BYROW(B73, _xlfn.LAMBDA(_xlpm.party, SUMIFS(ledger!J:J, ledger!B:B, _xlpm.party, ledger!E:E, "<>*RD*", ledger!D:D, "Kataan", ledger!C:C, "<>December Closing CF") ))} -> 0 | M73: {=_xlfn.BYROW(B73, _xlfn.LAMBDA(_xlpm.party, SUMIFS(ledger!J:J, ledger!B:B, _xlpm.party, ledger!E:E, "<>*RD*", ledger!D:D, "Munaar", ledger!C:C, "<>December Closing CF") ))} -> 0 | N73: =SUM(G73:M73) -> 0 | O73: =(SUMIF(Table14[Party],B73,Table14[Credit])) -> 0 | P73: =N73-O73 -> 0 | U73: Faizan | V73: 115375.82 | W73: 1384509.9
B74: Ahmad Javaid | C74: 0 | D74: 0 | E74: 0 | F74: 0 | G74: {=(_xlfn.BYROW(B74,_xlfn.LAMBDA(_xlpm.party, (SUMIFS(ledger!J:J,ledger!B:B,_xlpm.party,ledger!E:E,"<>*RD*",ledger!D:D,"Chamki",ledger!C:C,"<>December Closing CF")+ SUMIFS(ledger!J:J,ledger!B:B,_xlpm.party,ledger!E:E,"<>*RD*",ledger!D:D,"Crinkle",ledger!C:C,"<>December Closing CF") ))))} -> 0 | H74: {=_xlfn.BYROW(B74, _xlfn.LAMBDA(_xlpm.party, SUMIFS(ledger!J:J, ledger!B:B, _xlpm.party, ledger!E:E, "<>*RD*", ledger!D:D, "Silky", ledger!C:C, "<>December Closing CF") ))} -> 0 | I74: {=_xlfn.BYROW(B74, _xlfn.LAMBDA(_xlpm.party, SUMIFS(ledger!J:J, ledger!B:B, _xlpm.party, ledger!E:E, "<>*RD*", ledger!D:D, "Slub", ledger!C:C, "<>December Closing CF") ))} -> 0 | J74: {=_xlfn.BYROW(B74, _xlfn.LAMBDA(_xlpm.party, SUMIFS(ledger!J:J, ledger!B:B, _xlpm.party, ledger!E:E, "<>*RD*", ledger!D:D, "Satin", ledger!C:C, "<>December Closing CF") ))} -> 0 | K74: {=_xlfn.BYROW(B74, _xlfn.LAMBDA(_xlpm.party, SUMIFS(ledger!J:J, ledger!B:B, _xlpm.party, ledger!E:E, "<>*RD*", ledger!D:D, "Black-chamki", ledger!C:C, "<>December Closing CF") ))} -> 0 | L74: {=_xlfn.BYROW(B74, _xlfn.LAMBDA(_xlpm.party, SUMIFS(ledger!J:J, ledger!B:B, _xlpm.party, ledger!E:E, "<>*RD*", ledger!D:D, "Kataan", ledger!C:C, "<>December Closing CF") ))} -> 0 | M74: {=_xlfn.BYROW(B74, _xlfn.LAMBDA(_xlpm.party, SUMIFS(ledger!J:J, ledger!B:B, _xlpm.party, ledger!E:E, "<>*RD*", ledger!D:D, "Munaar", ledger!C:C, "<>December Closing CF") ))} -> 0 | N74: =SUM(G74:M74) -> 0 | O74: =(SUMIF(Table14[Party],B74,Table14[Credit])) -> 0 | P74: =N74-O74 -> 0 | U74: Gauhar Kashif | V74: 70997.623 | W74: 709976.23
B75: Rehman Ali | C75: 50131 | D75: 45840.344 | E75: 0 | F75: 45840.344 | G75: {=(_xlfn.BYROW(B75,_xlfn.LAMBDA(_xlpm.party, (SUMIFS(ledger!J:J,ledger!B:B,_xlpm.party,ledger!E:E,"<>*RD*",ledger!D:D,"Chamki",ledger!C:C,"<>December Closing CF")+ SUMIFS(ledger!J:J,ledger!B:B,_xlpm.party,ledger!E:E,"<>*RD*",ledger!D:D,"Crinkle",ledger!C:C,"<>December Closing CF") ))))} -> 0 | H75: {=_xlfn.BYROW(B75, _xlfn.LAMBDA(_xlpm.party, SUMIFS(ledger!J:J, ledger!B:B, _xlpm.party, ledger!E:E, "<>*RD*", ledger!D:D, "Silky", ledger!C:C, "<>December Closing CF") ))} -> 595924.47 | I75: {=_xlfn.BYROW(B75, _xlfn.LAMBDA(_xlpm.party, SUMIFS(ledger!J:J, ledger!B:B, _xlpm.party, ledger!E:E, "<>*RD*", ledger!D:D, "Slub", ledger!C:C, "<>December Closing CF") ))} -> 0 | J75: {=_xlfn.BYROW(B75, _xlfn.LAMBDA(_xlpm.party, SUMIFS(ledger!J:J, ledger!B:B, _xlpm.party, ledger!E:E, "<>*RD*", ledger!D:D, "Satin", ledger!C:C, "<>December Closing CF") ))} -> 0 | K75: {=_xlfn.BYROW(B75, _xlfn.LAMBDA(_xlpm.party, SUMIFS(ledger!J:J, ledger!B:B, _xlpm.party, ledger!E:E, "<>*RD*", ledger!D:D, "Black-chamki", ledger!C:C, "<>December Closing CF") ))} -> 0 | L75: {=_xlfn.BYROW(B75, _xlfn.LAMBDA(_xlpm.party, SUMIFS(ledger!J:J, ledger!B:B, _xlpm.party, ledger!E:E, "<>*RD*", ledger!D:D, "Kataan", ledger!C:C, "<>December Closing CF") ))} -> 0 | M75: {=_xlfn.BYROW(B75, _xlfn.LAMBDA(_xlpm.party, SUMIFS(ledger!J:J, ledger!B:B, _xlpm.party, ledger!E:E, "<>*RD*", ledger!D:D, "Munaar", ledger!C:C, "<>December Closing CF") ))} -> 0 | N75: =SUM(G75:M75) -> 595924.47 | O75: =(SUMIF(Table14[Party],B75,Table14[Credit])) -> 550000 | P75: =N75-O75 -> 45924.47 | U75: Grand Total | V75: 1462918.8 | W75: 14887590
B76: Shani Badshah | C76: 200033 | D76: 182912.4 | E76: 96185.077 | F76: 86727.323 | G76: {=(_xlfn.BYROW(B76,_xlfn.LAMBDA(_xlpm.party, (SUMIFS(ledger!J:J,ledger!B:B,_xlpm.party,ledger!E:E,"<>*RD*",ledger!D:D,"Chamki",ledger!C:C,"<>November Closing CF")+ SUMIFS(ledger!J:J,ledger!B:B,_xlpm.party,ledger!E:E,"<>*RD*",ledger!D:D,"Crinkle",ledger!C:C,"<>November Closing CF") ))))} -> 961850.77 | H76: {=_xlfn.BYROW(B76, _xlfn.LAMBDA(_xlpm.party, SUMIFS(ledger!J:J, ledger!B:B, _xlpm.party, ledger!E:E, "<>*RD*", ledger!D:D, "Silky", ledger!C:C, "<>November Closing CF") ))} -> 1127455.2 | I76: {=_xlfn.BYROW(B76, _xlfn.LAMBDA(_xlpm.party, SUMIFS(ledger!J:J, ledger!B:B, _xlpm.party, ledger!E:E, "<>*RD*", ledger!D:D, "Slub", ledger!C:C, "<>November Closing CF") ))} -> 0 | J76: {=_xlfn.BYROW(B76, _xlfn.LAMBDA(_xlpm.party, SUMIFS(ledger!J:J, ledger!B:B, _xlpm.party, ledger!E:E, "<>*RD*", ledger!D:D, "Satin", ledger!C:C, "<>November Closing CF") ))} -> 0 | K76: {=_xlfn.BYROW(B76, _xlfn.LAMBDA(_xlpm.party, SUMIFS(ledger!J:J, ledger!B:B, _xlpm.party, ledger!E:E, "<>*RD*", ledger!D:D, "Black-chamki", ledger!C:C, "<>November Closing CF") ))} -> 0 | L76: {=_xlfn.BYROW(B76, _xlfn.LAMBDA(_xlpm.party, SUMIFS(ledger!J:J, ledger!B:B, _xlpm.party, ledger!E:E, "<>*RD*", ledger!D:D, "Kataan", ledger!C:C, "<>November Closing CF") ))} -> 0 | M76: {=_xlfn.BYROW(B76, _xlfn.LAMBDA(_xlpm.party, SUMIFS(ledger!J:J, ledger!B:B, _xlpm.party, ledger!E:E, "<>*RD*", ledger!D:D, "Munaar", ledger!C:C, "<>November Closing CF") ))} -> 0 | N76: =SUM(G76:M76) -> 2089306 | O76: =SUMIF(Table14[Party], B76, Table14[Credit]) -> 1300000 | P76: =N76-O76 -> 789305.96
B77: Ahmad Shafique | C77: 53541 | D77: 48958.486 | E77: 0 | F77: 48958.486 | G77: {=(_xlfn.BYROW(B77,_xlfn.LAMBDA(_xlpm.party, (SUMIFS(ledger!J:J,ledger!B:B,_xlpm.party,ledger!E:E,"<>*RD*",ledger!D:D,"Chamki",ledger!C:C,"<>November Closing CF")+ SUMIFS(ledger!J:J,ledger!B:B,_xlpm.party,ledger!E:E,"<>*RD*",ledger!D:D,"Crinkle",ledger!C:C,"<>November Closing CF") ))))} -> 0 | H77: {=_xlfn.BYROW(B77, _xlfn.LAMBDA(_xlpm.party, SUMIFS(ledger!J:J, ledger!B:B, _xlpm.party, ledger!E:E, "<>*RD*", ledger!D:D, "Silky", ledger!C:C, "<>November Closing CF") ))} -> 636460.31 | I77: {=_xlfn.BYROW(B77, _xlfn.LAMBDA(_xlpm.party, SUMIFS(ledger!J:J, ledger!B:B, _xlpm.party, ledger!E:E, "<>*RD*", ledger!D:D, "Slub", ledger!C:C, "<>November Closing CF") ))} -> 0 | J77: {=_xlfn.BYROW(B77, _xlfn.LAMBDA(_xlpm.party, SUMIFS(ledger!J:J, ledger!B:B, _xlpm.party, ledger!E:E, "<>*RD*", ledger!D:D, "Satin", ledger!C:C, "<>November Closing CF") ))} -> 0 | K77: {=_xlfn.BYROW(B77, _xlfn.LAMBDA(_xlpm.party, SUMIFS(ledger!J:J, ledger!B:B, _xlpm.party, ledger!E:E, "<>*RD*", ledger!D:D, "Black-chamki", ledger!C:C, "<>November Closing CF") ))} -> 0 | L77: {=_xlfn.BYROW(B77, _xlfn.LAMBDA(_xlpm.party, SUMIFS(ledger!J:J, ledger!B:B, _xlpm.party, ledger!E:E, "<>*RD*", ledger!D:D, "Kataan", ledger!C:C, "<>November Closing CF") ))} -> 0 | M77: {=_xlfn.BYROW(B77, _xlfn.LAMBDA(_xlpm.party, SUMIFS(ledger!J:J, ledger!B:B, _xlpm.party, ledger!E:E, "<>*RD*", ledger!D:D, "Munaar", ledger!C:C, "<>November Closing CF") ))} -> 0 | N77: =SUM(G77:M77) -> 636460.31 | O77: =SUMIF(Table14[Party], B77, Table14[Credit]) -> 636000 | P77: =N77-O77 -> 460.31456
B78: Hafiz Shawl | C78: 1445 | D78: 1321.3241 | E78: 0 | F78: 1321.3241 | G78: {=(_xlfn.BYROW(B78,_xlfn.LAMBDA(_xlpm.party, (SUMIFS(ledger!J:J,ledger!B:B,_xlpm.party,ledger!E:E,"<>*RD*",ledger!D:D,"Chamki",ledger!C:C,"<>November Closing CF")+ SUMIFS(ledger!J:J,ledger!B:B,_xlpm.party,ledger!E:E,"<>*RD*",ledger!D:D,"Crinkle",ledger!C:C,"<>November Closing CF") ))))} -> 0 | H78: {=_xlfn.BYROW(B78, _xlfn.LAMBDA(_xlpm.party, SUMIFS(ledger!J:J, ledger!B:B, _xlpm.party, ledger!E:E, "<>*RD*", ledger!D:D, "Silky", ledger!C:C, "<>November Closing CF") ))} -> 15855.889 | I78: {=_xlfn.BYROW(B78, _xlfn.LAMBDA(_xlpm.party, SUMIFS(ledger!J:J, ledger!B:B, _xlpm.party, ledger!E:E, "<>*RD*", ledger!D:D, "Slub", ledger!C:C, "<>November Closing CF") ))} -> 0 | J78: {=_xlfn.BYROW(B78, _xlfn.LAMBDA(_xlpm.party, SUMIFS(ledger!J:J, ledger!B:B, _xlpm.party, ledger!E:E, "<>*RD*", ledger!D:D, "Satin", ledger!C:C, "<>November Closing CF") ))} -> 0 | K78: {=_xlfn.BYROW(B78, _xlfn.LAMBDA(_xlpm.party, SUMIFS(ledger!J:J, ledger!B:B, _xlpm.party, ledger!E:E, "<>*RD*", ledger!D:D, "Black-chamki", ledger!C:C, "<>November Closing CF") ))} -> 0 | L78: {=_xlfn.BYROW(B78, _xlfn.LAMBDA(_xlpm.party, SUMIFS(ledger!J:J, ledger!B:B, _xlpm.party, ledger!E:E, "<>*RD*", ledger!D:D, "Kataan", ledger!C:C, "<>November Closing CF") ))} -> 0 | M78: {=_xlfn.BYROW(B78, _xlfn.LAMBDA(_xlpm.party, SUMIFS(ledger!J:J, ledger!B:B, _xlpm.party, ledger!E:E, "<>*RD*", ledger!D:D, "Munaar", ledger!C:C, "<>November Closing CF") ))} -> 0 | N78: =SUM(G78:M78) -> 15855.889 | O78: =SUMIF(Table14[Party], B78, Table14[Credit]) -> 15855 | P78: =N78-O78 -> 0.88880761
G79: {=(_xlfn.BYROW(B79,_xlfn.LAMBDA(_xlpm.party, (SUMIFS(ledger!J:J,ledger!B:B,_xlpm.party,ledger!E:E,"<>*RD*",ledger!D:D,"Chamki",ledger!C:C,"<>November Closing CF")+ SUMIFS(ledger!J:J,ledger!B:B,_xlpm.party,ledger!E:E,"<>*RD*",ledger!D:D,"Crinkle",ledger!C:C,"<>November Closing CF") ))))} -> 0 | H79: {=_xlfn.BYROW(B79, _xlfn.LAMBDA(_xlpm.party, SUMIFS(ledger!J:J, ledger!B:B, _xlpm.party, ledger!E:E, "<>*RD*", ledger!D:D, "Silky", ledger!C:C, "<>November Closing CF") ))} -> 0 | I79: {=_xlfn.BYROW(B79, _xlfn.LAMBDA(_xlpm.party, SUMIFS(ledger!J:J, ledger!B:B, _xlpm.party, ledger!E:E, "<>*RD*", ledger!D:D, "Slub", ledger!C:C, "<>November Closing CF") ))} -> 0 | J79: {=_xlfn.BYROW(B79, _xlfn.LAMBDA(_xlpm.party, SUMIFS(ledger!J:J, ledger!B:B, _xlpm.party, ledger!E:E, "<>*RD*", ledger!D:D, "Satin", ledger!C:C, "<>November Closing CF") ))} -> 0 | K79: {=_xlfn.BYROW(B79, _xlfn.LAMBDA(_xlpm.party, SUMIFS(ledger!J:J, ledger!B:B, _xlpm.party, ledger!E:E, "<>*RD*", ledger!D:D, "Black-chamki", ledger!C:C, "<>November Closing CF") ))} -> 0 | L79: {=_xlfn.BYROW(B79, _xlfn.LAMBDA(_xlpm.party, SUMIFS(ledger!J:J, ledger!B:B, _xlpm.party, ledger!E:E, "<>*RD*", ledger!D:D, "Kataan", ledger!C:C, "<>November Closing CF") ))} -> 0 | M79: {=_xlfn.BYROW(B79, _xlfn.LAMBDA(_xlpm.party, SUMIFS(ledger!J:J, ledger!B:B, _xlpm.party, ledger!E:E, "<>*RD*", ledger!D:D, "Munaar", ledger!C:C, "<>November Closing CF") ))} -> 0 | N79: =SUM(G79:M79) -> 0
B81: Billing (Previous)
B83: Parties: | C83: Gaz | D83: Total Metres | E83: Total Chamki | F83: Total Super Silky | G83: Billing (Chamki/Crinkle) | H83: Billing (Super Chamki) | I83: billing (Slub) | J83: Billing (Satin) | K83: Billing (Black-Chamki) | L83: Billing (kataan | M83: Billing (Munaar) | N83: Adjusted Bill | O83: Amount Paid | P83: Balance | Q83: Rate (Chamki) | R83: Rate (Super Silky)
B84: {=_xlfn.UNIQUE(Table1[Party Name])} -> BSC | C84: =_xlfn.XLOOKUP($B49,[1]Billing!$Q$5:$Q$40,[1]Billing!$R$5:$R$40) -> 3114572.9 | D84: =_xlfn.XLOOKUP($B49,[1]Billing!$Q$5:$Q$40,[1]Billing!$S$5:$S$40) -> 2848000.1 | E84: =_xlfn.XLOOKUP($B49,[1]Billing!$Q$5:$Q$40,[1]Billing!$T$5:$T$40) -> 2468066.8 | F84: =_xlfn.XLOOKUP($B49,[1]Billing!$Q$5:$Q$40,[1]Billing!$U$5:$U$40) -> 379933.25 | G84: =_xlfn.XLOOKUP($B49,[1]Billing!$Q$5:$Q$40,[1]Billing!$V$5:$V$40) -> 24680668 | H84: =_xlfn.XLOOKUP($B49,[1]Billing!$Q$5:$Q$40,[1]Billing!$W$5:$W$40) -> 4850776.3 | I84: =_xlfn.XLOOKUP($B49,[1]Billing!$Q$5:$Q$40,[1]Billing!$X$5:$X$40) -> 0 | J84: =_xlfn.XLOOKUP($B49,[1]Billing!$Q$5:$Q$40,[1]Billing!$Y$5:$Y$40) -> 0 | K84: =_xlfn.XLOOKUP($B49,[1]Billing!$Q$5:$Q$40,[1]Billing!$Z$5:$Z$40) -> 0 | L84: =_xlfn.XLOOKUP($B49,[1]Billing!$Q$5:$Q$40,[1]Billing!$AA$5:$AA$40) -> 0 | M84: =_xlfn.XLOOKUP($B49,[1]Billing!$Q$5:$Q$40,[1]Billing!$AB$5:$AB$40) -> 0 | N84: =G84+H84+I84+J84+K84+L84+M84 -> 29531445 | O84: =_xlfn.XLOOKUP($B49,[1]Billing!$Q$5:$Q$40,[1]Billing!$AD$5:$AD$40) -> 19750734 | P84: =N84-O84 -> 9780710.6 | Q84: 10 | R84: 13
B85: Ejaz Sahab | C85: =_xlfn.XLOOKUP($B50,[1]Billing!$Q$5:$Q$40,[1]Billing!$R$5:$R$40) -> 479409 | D85: =_xlfn.XLOOKUP($B50,[1]Billing!$Q$5:$Q$40,[1]Billing!$S$5:$S$40) -> 438376.92 | E85: =_xlfn.XLOOKUP($B50,[1]Billing!$Q$5:$Q$40,[1]Billing!$T$5:$T$40) -> 148145.57 | F85: =_xlfn.XLOOKUP($B50,[1]Billing!$Q$5:$Q$40,[1]Billing!$U$5:$U$40) -> 290231.35 | G85: =_xlfn.XLOOKUP($B50,[1]Billing!$Q$5:$Q$40,[1]Billing!$V$5:$V$40) -> 1481455.7 | H85: =_xlfn.XLOOKUP($B50,[1]Billing!$Q$5:$Q$40,[1]Billing!$W$5:$W$40) -> 3713863.4 | I85: =_xlfn.XLOOKUP($B50,[1]Billing!$Q$5:$Q$40,[1]Billing!$X$5:$X$40) -> 0 | J85: =_xlfn.XLOOKUP($B50,[1]Billing!$Q$5:$Q$40,[1]Billing!$Y$5:$Y$40) -> 0 | K85: =_xlfn.XLOOKUP($B50,[1]Billing!$Q$5:$Q$40,[1]Billing!$Z$5:$Z$40) -> 0 | L85: =_xlfn.XLOOKUP($B50,[1]Billing!$Q$5:$Q$40,[1]Billing!$AA$5:$AA$40) -> 0 | M85: =_xlfn.XLOOKUP($B50,[1]Billing!$Q$5:$Q$40,[1]Billing!$AB$5:$AB$40) -> 0 | N85: =G85+H85+I85+J85+K85+L85+M85 -> 5195319.1 | O85: =_xlfn.XLOOKUP($B50,[1]Billing!$Q$5:$Q$40,[1]Billing!$AD$5:$AD$40) -> 5195319 | P85: =N85-O85 -> 0.12948062 | Q85: 10 | R85: 13
B86: Arshad | C86: =_xlfn.XLOOKUP($B51,[1]Billing!$Q$5:$Q$40,[1]Billing!$R$5:$R$40) -> 823577 | D86: =_xlfn.XLOOKUP($B51,[1]Billing!$Q$5:$Q$40,[1]Billing!$S$5:$S$40) -> 753087.97 | E86: =_xlfn.XLOOKUP($B51,[1]Billing!$Q$5:$Q$40,[1]Billing!$T$5:$T$40) -> 626388.08 | F86: =_xlfn.XLOOKUP($B51,[1]Billing!$Q$5:$Q$40,[1]Billing!$U$5:$U$40) -> 126699.89 | G86: =_xlfn.XLOOKUP($B51,[1]Billing!$Q$5:$Q$40,[1]Billing!$V$5:$V$40) -> 6263880.8 | H86: =_xlfn.XLOOKUP($B51,[1]Billing!$Q$5:$Q$40,[1]Billing!$W$5:$W$40) -> 1632304.3 | I86: =_xlfn.XLOOKUP($B51,[1]Billing!$Q$5:$Q$40,[1]Billing!$X$5:$X$40) -> 0 | J86: =_xlfn.XLOOKUP($B51,[1]Billing!$Q$5:$Q$40,[1]Billing!$Y$5:$Y$40) -> 0 | K86: =_xlfn.XLOOKUP($B51,[1]Billing!$Q$5:$Q$40,[1]Billing!$Z$5:$Z$40) -> 0 | L86: =_xlfn.XLOOKUP($B51,[1]Billing!$Q$5:$Q$40,[1]Billing!$AA$5:$AA$40) -> 0 | M86: =_xlfn.XLOOKUP($B51,[1]Billing!$Q$5:$Q$40,[1]Billing!$AB$5:$AB$40) -> 0 | N86: =G86+H86+I86+J86+K86+L86+M86 -> 7896185.1 | O86: =_xlfn.XLOOKUP($B51,[1]Billing!$Q$5:$Q$40,[1]Billing!$AD$5:$AD$40) -> 7835501 | P86: =N86-O86 -> 60684.077 | Q86: 10 | R86: 13
B87: Shehzad Kamoki | C87: =_xlfn.XLOOKUP($B52,[1]Billing!$Q$5:$Q$40,[1]Billing!$R$5:$R$40) -> 143457 | D87: =_xlfn.XLOOKUP($B52,[1]Billing!$Q$5:$Q$40,[1]Billing!$S$5:$S$40) -> 131178.68 | E87: =_xlfn.XLOOKUP($B52,[1]Billing!$Q$5:$Q$40,[1]Billing!$T$5:$T$40) -> 131178.68 | F87: =_xlfn.XLOOKUP($B52,[1]Billing!$Q$5:$Q$40,[1]Billing!$U$5:$U$40) -> 0 | G87: =_xlfn.XLOOKUP($B52,[1]Billing!$Q$5:$Q$40,[1]Billing!$V$5:$V$40) -> 1354242 | H87: =_xlfn.XLOOKUP($B52,[1]Billing!$Q$5:$Q$40,[1]Billing!$W$5:$W$40) -> 0 | I87: =_xlfn.XLOOKUP($B52,[1]Billing!$Q$5:$Q$40,[1]Billing!$X$5:$X$40) -> 0 | J87: =_xlfn.XLOOKUP($B52,[1]Billing!$Q$5:$Q$40,[1]Billing!$Y$5:$Y$40) -> 0 | K87: =_xlfn.XLOOKUP($B52,[1]Billing!$Q$5:$Q$40,[1]Billing!$Z$5:$Z$40) -> 0 | L87: =_xlfn.XLOOKUP($B52,[1]Billing!$Q$5:$Q$40,[1]Billing!$AA$5:$AA$40) -> 0 | M87: =_xlfn.XLOOKUP($B52,[1]Billing!$Q$5:$Q$40,[1]Billing!$AB$5:$AB$40) -> 0 | N87: =G87+H87+I87+J87+K87+L87+M87 -> 1354242 | O87: =_xlfn.XLOOKUP($B52,[1]Billing!$Q$5:$Q$40,[1]Billing!$AD$5:$AD$40) -> 1353710 | P87: =N87-O87 -> 531.99729 | Q87: 10.5 | R87: 13
B88: Sufi Nawaz Sahab | C88: =_xlfn.XLOOKUP($B53,[1]Billing!$Q$5:$Q$40,[1]Billing!$R$5:$R$40) -> 1212967 | D88: =_xlfn.XLOOKUP($B53,[1]Billing!$Q$5:$Q$40,[1]Billing!$S$5:$S$40) -> 1109150.5 | E88: =_xlfn.XLOOKUP($B53,[1]Billing!$Q$5:$Q$40,[1]Billing!$T$5:$T$40) -> 599330.65 | F88: =_xlfn.XLOOKUP($B53,[1]Billing!$Q$5:$Q$40,[1]Billing!$U$5:$U$40) -> 485823.88 | G88: =_xlfn.XLOOKUP($B53,[1]Billing!$Q$5:$Q$40,[1]Billing!$V$5:$V$40) -> 5408917.9 | H88: =_xlfn.XLOOKUP($B53,[1]Billing!$Q$5:$Q$40,[1]Billing!$W$5:$W$40) -> 5829886.6 | I88: =_xlfn.XLOOKUP($B53,[1]Billing!$Q$5:$Q$40,[1]Billing!$X$5:$X$40) -> 0 | J88: =_xlfn.XLOOKUP($B53,[1]Billing!$Q$5:$Q$40,[1]Billing!$Y$5:$Y$40) -> 239959.77 | K88: =_xlfn.XLOOKUP($B53,[1]Billing!$Q$5:$Q$40,[1]Billing!$Z$5:$Z$40) -> 0 | L88: =_xlfn.XLOOKUP($B53,[1]Billing!$Q$5:$Q$40,[1]Billing!$AA$5:$AA$40) -> 0 | M88: =_xlfn.XLOOKUP($B53,[1]Billing!$Q$5:$Q$40,[1]Billing!$AB$5:$AB$40) -> 0 | N88: =G88+H88+I88+J88+K88+L88+M88 -> 11478764 | O88: =_xlfn.XLOOKUP($B53,[1]Billing!$Q$5:$Q$40,[1]Billing!$AD$5:$AD$40) -> 11478764 | P88: =N88-O88 -> 0.23847842 | Q88: 10 | R88: 13
B89: Sajad Khan | C89: =_xlfn.XLOOKUP($B54,[1]Billing!$Q$5:$Q$40,[1]Billing!$R$5:$R$40) -> 922283 | D89: =_xlfn.XLOOKUP($B54,[1]Billing!$Q$5:$Q$40,[1]Billing!$S$5:$S$40) -> 843345.83 | E89: =_xlfn.XLOOKUP($B54,[1]Billing!$Q$5:$Q$40,[1]Billing!$T$5:$T$40) -> 837856.62 | F89: =_xlfn.XLOOKUP($B54,[1]Billing!$Q$5:$Q$40,[1]Billing!$U$5:$U$40) -> 0 | G89: =_xlfn.XLOOKUP($B54,[1]Billing!$Q$5:$Q$40,[1]Billing!$V$5:$V$40) -> 8378566.2 | H89: =_xlfn.XLOOKUP($B54,[1]Billing!$Q$5:$Q$40,[1]Billing!$W$5:$W$40) -> 0 | I89: =_xlfn.XLOOKUP($B54,[1]Billing!$Q$5:$Q$40,[1]Billing!$X$5:$X$40) -> 71359.729 | J89: =_xlfn.XLOOKUP($B54,[1]Billing!$Q$5:$Q$40,[1]Billing!$Y$5:$Y$40) -> 0 | K89: =_xlfn.XLOOKUP($B54,[1]Billing!$Q$5:$Q$40,[1]Billing!$Z$5:$Z$40) -> 0 | L89: =_xlfn.XLOOKUP($B54,[1]Billing!$Q$5:$Q$40,[1]Billing!$AA$5:$AA$40) -> 0 | M89: =_xlfn.XLOOKUP($B54,[1]Billing!$Q$5:$Q$40,[1]Billing!$AB$5:$AB$40) -> 0 | N89: =G89+H89+I89+J89+K89+L89+M89 -> 8449925.9 | O89: =_xlfn.XLOOKUP($B54,[1]Billing!$Q$5:$Q$40,[1]Billing!$AD$5:$AD$40) -> 7997871 | P89: =N89-O89 -> 452054.93 | Q89: 10 | R89: 13
B90: Raaz Fabrics | C90: =_xlfn.XLOOKUP($B55,[1]Billing!$Q$5:$Q$40,[1]Billing!$R$5:$R$40) -> 177861 | D90: =_xlfn.XLOOKUP($B55,[1]Billing!$Q$5:$Q$40,[1]Billing!$S$5:$S$40) -> 162638.08 | E90: =_xlfn.XLOOKUP($B55,[1]Billing!$Q$5:$Q$40,[1]Billing!$T$5:$T$40) -> 162638.08 | F90: =_xlfn.XLOOKUP($B55,[1]Billing!$Q$5:$Q$40,[1]Billing!$U$5:$U$40) -> 0 | G90: =_xlfn.XLOOKUP($B55,[1]Billing!$Q$5:$Q$40,[1]Billing!$V$5:$V$40) -> 1626380.8 | H90: =_xlfn.XLOOKUP($B55,[1]Billing!$Q$5:$Q$40,[1]Billing!$W$5:$W$40) -> 0 | I90: =_xlfn.XLOOKUP($B55,[1]Billing!$Q$5:$Q$40,[1]Billing!$X$5:$X$40) -> 0 | J90: =_xlfn.XLOOKUP($B55,[1]Billing!$Q$5:$Q$40,[1]Billing!$Y$5:$Y$40) -> 0 | K90: =_xlfn.XLOOKUP($B55,[1]Billing!$Q$5:$Q$40,[1]Billing!$Z$5:$Z$40) -> 0 | L90: =_xlfn.XLOOKUP($B55,[1]Billing!$Q$5:$Q$40,[1]Billing!$AA$5:$AA$40) -> 0 | M90: =_xlfn.XLOOKUP($B55,[1]Billing!$Q$5:$Q$40,[1]Billing!$AB$5:$AB$40) -> 0 | N90: =G90+H90+I90+J90+K90+L90+M90 -> 1626380.8 | O90: =_xlfn.XLOOKUP($B55,[1]Billing!$Q$5:$Q$40,[1]Billing!$AD$5:$AD$40) -> 1526321 | P90: =N90-O90 -> 100059.76 | Q90: 10 | R90: 13
B91: Azam | C91: =_xlfn.XLOOKUP($B56,[1]Billing!$Q$5:$Q$40,[1]Billing!$R$5:$R$40) -> 543437 | D91: =_xlfn.XLOOKUP($B56,[1]Billing!$Q$5:$Q$40,[1]Billing!$S$5:$S$40) -> 496924.84 | E91: =_xlfn.XLOOKUP($B56,[1]Billing!$Q$5:$Q$40,[1]Billing!$T$5:$T$40) -> 400309.07 | F91: =_xlfn.XLOOKUP($B56,[1]Billing!$Q$5:$Q$40,[1]Billing!$U$5:$U$40) -> 96615.764 | G91: =_xlfn.XLOOKUP($B56,[1]Billing!$Q$5:$Q$40,[1]Billing!$V$5:$V$40) -> 4003090.7 | H91: =_xlfn.XLOOKUP($B56,[1]Billing!$Q$5:$Q$40,[1]Billing!$W$5:$W$40) -> 1256004.9 | I91: =_xlfn.XLOOKUP($B56,[1]Billing!$Q$5:$Q$40,[1]Billing!$X$5:$X$40) -> 0 | J91: =_xlfn.XLOOKUP($B56,[1]Billing!$Q$5:$Q$40,[1]Billing!$Y$5:$Y$40) -> 0 | K91: =_xlfn.XLOOKUP($B56,[1]Billing!$Q$5:$Q$40,[1]Billing!$Z$5:$Z$40) -> 0 | L91: =_xlfn.XLOOKUP($B56,[1]Billing!$Q$5:$Q$40,[1]Billing!$AA$5:$AA$40) -> 0 | M91: =_xlfn.XLOOKUP($B56,[1]Billing!$Q$5:$Q$40,[1]Billing!$AB$5:$AB$40) -> 0 | N91: =G91+H91+I91+J91+K91+L91+M91 -> 5259095.6 | O91: =_xlfn.XLOOKUP($B56,[1]Billing!$Q$5:$Q$40,[1]Billing!$AD$5:$AD$40) -> 5089540 | P91: =N91-O91 -> 169555.65 | Q91: 10 | R91: 13
B92: Ubaidullah | C92: =_xlfn.XLOOKUP($B57,[1]Billing!$Q$5:$Q$40,[1]Billing!$R$5:$R$40) -> 126448 | D92: =_xlfn.XLOOKUP($B57,[1]Billing!$Q$5:$Q$40,[1]Billing!$S$5:$S$40) -> 115625.46 | E92: =_xlfn.XLOOKUP($B57,[1]Billing!$Q$5:$Q$40,[1]Billing!$T$5:$T$40) -> 46132.955 | F92: =_xlfn.XLOOKUP($B57,[1]Billing!$Q$5:$Q$40,[1]Billing!$U$5:$U$40) -> 69492.502 | G92: =_xlfn.XLOOKUP($B57,[1]Billing!$Q$5:$Q$40,[1]Billing!$V$5:$V$40) -> 461329.55 | H92: =_xlfn.XLOOKUP($B57,[1]Billing!$Q$5:$Q$40,[1]Billing!$W$5:$W$40) -> 888407.1 | I92: =_xlfn.XLOOKUP($B57,[1]Billing!$Q$5:$Q$40,[1]Billing!$X$5:$X$40) -> 0 | J92: =_xlfn.XLOOKUP($B57,[1]Billing!$Q$5:$Q$40,[1]Billing!$Y$5:$Y$40) -> 0 | K92: =_xlfn.XLOOKUP($B57,[1]Billing!$Q$5:$Q$40,[1]Billing!$Z$5:$Z$40) -> 0 | L92: =_xlfn.XLOOKUP($B57,[1]Billing!$Q$5:$Q$40,[1]Billing!$AA$5:$AA$40) -> 0 | M92: =_xlfn.XLOOKUP($B57,[1]Billing!$Q$5:$Q$40,[1]Billing!$AB$5:$AB$40) -> 0 | N92: =G92+H92+I92+J92+K92+L92+M92 -> 1349736.6 | O92: =_xlfn.XLOOKUP($B57,[1]Billing!$Q$5:$Q$40,[1]Billing!$AD$5:$AD$40) -> 1390190 | P92: =N92-O92 -> -40453.35 | Q92: 10 | R92: 13
B93: Ashraf Zia | C93: =_xlfn.XLOOKUP($B58,[1]Billing!$Q$5:$Q$40,[1]Billing!$R$5:$R$40) -> 23305 | D93: =_xlfn.XLOOKUP($B58,[1]Billing!$Q$5:$Q$40,[1]Billing!$S$5:$S$40) -> 21310.351 | E93: =_xlfn.XLOOKUP($B58,[1]Billing!$Q$5:$Q$40,[1]Billing!$T$5:$T$40) -> 21310.351 | F93: =_xlfn.XLOOKUP($B58,[1]Billing!$Q$5:$Q$40,[1]Billing!$U$5:$U$40) -> 0 | G93: =_xlfn.XLOOKUP($B58,[1]Billing!$Q$5:$Q$40,[1]Billing!$V$5:$V$40) -> 255724.21 | H93: =_xlfn.XLOOKUP($B58,[1]Billing!$Q$5:$Q$40,[1]Billing!$W$5:$W$40) -> 0 | I93: =_xlfn.XLOOKUP($B58,[1]Billing!$Q$5:$Q$40,[1]Billing!$X$5:$X$40) -> 0 | J93: =_xlfn.XLOOKUP($B58,[1]Billing!$Q$5:$Q$40,[1]Billing!$Y$5:$Y$40) -> 0 | K93: =_xlfn.XLOOKUP($B58,[1]Billing!$Q$5:$Q$40,[1]Billing!$Z$5:$Z$40) -> 0 | L93: =_xlfn.XLOOKUP($B58,[1]Billing!$Q$5:$Q$40,[1]Billing!$AA$5:$AA$40) -> 0 | M93: =_xlfn.XLOOKUP($B58,[1]Billing!$Q$5:$Q$40,[1]Billing!$AB$5:$AB$40) -> 0 | N93: =G93+H93+I93+J93+K93+L93+M93 -> 255724.21 | O93: =_xlfn.XLOOKUP($B58,[1]Billing!$Q$5:$Q$40,[1]Billing!$AD$5:$AD$40) -> 130000 | P93: =N93-O93 -> 125724.21 | Q93: 12 | R93: 13
B94: Hafiz Qureshi | C94: =_xlfn.XLOOKUP($B59,[1]Billing!$Q$5:$Q$40,[1]Billing!$R$5:$R$40) -> 314924 | D94: =_xlfn.XLOOKUP($B59,[1]Billing!$Q$5:$Q$40,[1]Billing!$S$5:$S$40) -> 287970.01 | E94: =_xlfn.XLOOKUP($B59,[1]Billing!$Q$5:$Q$40,[1]Billing!$T$5:$T$40) -> 287970.01 | F94: =_xlfn.XLOOKUP($B59,[1]Billing!$Q$5:$Q$40,[1]Billing!$U$5:$U$40) -> 0 | G94: =_xlfn.XLOOKUP($B59,[1]Billing!$Q$5:$Q$40,[1]Billing!$V$5:$V$40) -> 2879700.1 | H94: =_xlfn.XLOOKUP($B59,[1]Billing!$Q$5:$Q$40,[1]Billing!$W$5:$W$40) -> 0 | I94: =_xlfn.XLOOKUP($B59,[1]Billing!$Q$5:$Q$40,[1]Billing!$X$5:$X$40) -> 0 | J94: =_xlfn.XLOOKUP($B59,[1]Billing!$Q$5:$Q$40,[1]Billing!$Y$5:$Y$40) -> 0 | K94: =_xlfn.XLOOKUP($B59,[1]Billing!$Q$5:$Q$40,[1]Billing!$Z$5:$Z$40) -> 0 | L94: =_xlfn.XLOOKUP($B59,[1]Billing!$Q$5:$Q$40,[1]Billing!$AA$5:$AA$40) -> 0 | M94: =_xlfn.XLOOKUP($B59,[1]Billing!$Q$5:$Q$40,[1]Billing!$AB$5:$AB$40) -> 0 | N94: =G94+H94+I94+J94+K94+L94+M94 -> 2879700.1 | O94: =_xlfn.XLOOKUP($B59,[1]Billing!$Q$5:$Q$40,[1]Billing!$AD$5:$AD$40) -> 2869679 | P94: =N94-O94 -> 10021.073 | Q94: 10 | R94: 13
B95: Badshah Fabrics | C95: =_xlfn.XLOOKUP($B60,[1]Billing!$Q$5:$Q$40,[1]Billing!$R$5:$R$40) -> 681314 | D95: =_xlfn.XLOOKUP($B60,[1]Billing!$Q$5:$Q$40,[1]Billing!$S$5:$S$40) -> 623001.1 | E95: =_xlfn.XLOOKUP($B60,[1]Billing!$Q$5:$Q$40,[1]Billing!$T$5:$T$40) -> 481526.15 | F95: =_xlfn.XLOOKUP($B60,[1]Billing!$Q$5:$Q$40,[1]Billing!$U$5:$U$40) -> 141474.95 | G95: =_xlfn.XLOOKUP($B60,[1]Billing!$Q$5:$Q$40,[1]Billing!$V$5:$V$40) -> 4861679.8 | H95: =_xlfn.XLOOKUP($B60,[1]Billing!$Q$5:$Q$40,[1]Billing!$W$5:$W$40) -> 1776019.6 | I95: =_xlfn.XLOOKUP($B60,[1]Billing!$Q$5:$Q$40,[1]Billing!$X$5:$X$40) -> 0 | J95: =_xlfn.XLOOKUP($B60,[1]Billing!$Q$5:$Q$40,[1]Billing!$Y$5:$Y$40) -> 0 | K95: =_xlfn.XLOOKUP($B60,[1]Billing!$Q$5:$Q$40,[1]Billing!$Z$5:$Z$40) -> 0 | L95: =_xlfn.XLOOKUP($B60,[1]Billing!$Q$5:$Q$40,[1]Billing!$AA$5:$AA$40) -> 0 | M95: =_xlfn.XLOOKUP($B60,[1]Billing!$Q$5:$Q$40,[1]Billing!$AB$5:$AB$40) -> 0 | N95: =G95+H95+I95+J95+K95+L95+M95 -> 6637699.3 | O95: =_xlfn.XLOOKUP($B60,[1]Billing!$Q$5:$Q$40,[1]Billing!$AD$5:$AD$40) -> 6545761 | P95: =N95-O95 -> 91938.342 | Q95: 10 | R95: 13
B96: Gauhar Kashif | C96: =_xlfn.XLOOKUP($B61,[1]Billing!$Q$5:$Q$40,[1]Billing!$R$5:$R$40) -> 55125 | D96: =_xlfn.XLOOKUP($B61,[1]Billing!$Q$5:$Q$40,[1]Billing!$S$5:$S$40) -> 50406.913 | E96: =_xlfn.XLOOKUP($B61,[1]Billing!$Q$5:$Q$40,[1]Billing!$T$5:$T$40) -> 50406.913 | F96: =_xlfn.XLOOKUP($B61,[1]Billing!$Q$5:$Q$40,[1]Billing!$U$5:$U$40) -> 0 | G96: =_xlfn.XLOOKUP($B61,[1]Billing!$Q$5:$Q$40,[1]Billing!$V$5:$V$40) -> 504069.13 | H96: =_xlfn.XLOOKUP($B61,[1]Billing!$Q$5:$Q$40,[1]Billing!$W$5:$W$40) -> 0 | I96: =_xlfn.XLOOKUP($B61,[1]Billing!$Q$5:$Q$40,[1]Billing!$X$5:$X$40) -> 0 | J96: =_xlfn.XLOOKUP($B61,[1]Billing!$Q$5:$Q$40,[1]Billing!$Y$5:$Y$40) -> 0 | K96: =_xlfn.XLOOKUP($B61,[1]Billing!$Q$5:$Q$40,[1]Billing!$Z$5:$Z$40) -> 0 | L96: =_xlfn.XLOOKUP($B61,[1]Billing!$Q$5:$Q$40,[1]Billing!$AA$5:$AA$40) -> 0 | M96: =_xlfn.XLOOKUP($B61,[1]Billing!$Q$5:$Q$40,[1]Billing!$AB$5:$AB$40) -> 0 | N96: =G96+H96+I96+J96+K96+L96+M96 -> 504069.13 | O96: =_xlfn.XLOOKUP($B61,[1]Billing!$Q$5:$Q$40,[1]Billing!$AD$5:$AD$40) -> 485800 | P96: =N96-O96 -> 18269.129 | Q96: 10 | R96: 13
... B103: Salman Zaffar | C103: =_xlfn.XLOOKUP($B68,[1]Billing!$Q$5:$Q$40,[1]Billing!$R$5:$R$40) -> 275656 | D103: =_xlfn.XLOOKUP($B68,[1]Billing!$Q$5:$Q$40,[1]Billing!$S$5:$S$40) -> 252062.91 | E103: =_xlfn.XLOOKUP($B68,[1]Billing!$Q$5:$Q$40,[1]Billing!$T$5:$T$40) -> 52616.13 | F103: =_xlfn.XLOOKUP($B68,[1]Billing!$Q$5:$Q$40,[1]Billing!$U$5:$U$40) -> 31409.108 | G103: =_xlfn.XLOOKUP($B68,[1]Billing!$Q$5:$Q$40,[1]Billing!$V$5:$V$40) -> 526161.3 | H103: =_xlfn.XLOOKUP($B68,[1]Billing!$Q$5:$Q$40,[1]Billing!$W$5:$W$40) -> 408318.4 | I103: =_xlfn.XLOOKUP($B68,[1]Billing!$Q$5:$Q$40,[1]Billing!$X$5:$X$40) -> 0 | J103: =_xlfn.XLOOKUP($B68,[1]Billing!$Q$5:$Q$40,[1]Billing!$Y$5:$Y$40) -> 0 | K103: =_xlfn.XLOOKUP($B68,[1]Billing!$Q$5:$Q$40,[1]Billing!$Z$5:$Z$40) -> 161653.26 | L103: =_xlfn.XLOOKUP($B68,[1]Billing!$Q$5:$Q$40,[1]Billing!$AA$5:$AA$40) -> 1545665.7 | M103: =_xlfn.XLOOKUP($B68,[1]Billing!$Q$5:$Q$40,[1]Billing!$AB$5:$AB$40) -> 0 | N103: =G103+H103+I103+J103+K103+L103+M103 -> 2641798.6 | O103: =_xlfn.XLOOKUP($B68,[1]Billing!$Q$5:$Q$40,[1]Billing!$AD$5:$AD$40) -> 2146025 | P103: =N103-O103 -> 495773.65 | Q103: 10 | R103: 13
B104: Shahid Qasayi | C104: =_xlfn.XLOOKUP($B69,[1]Billing!$Q$5:$Q$40,[1]Billing!$R$5:$R$40) -> 315508 | D104: =_xlfn.XLOOKUP($B69,[1]Billing!$Q$5:$Q$40,[1]Billing!$S$5:$S$40) -> 288504.02 | E104: =_xlfn.XLOOKUP($B69,[1]Billing!$Q$5:$Q$40,[1]Billing!$T$5:$T$40) -> 238964.89 | F104: =_xlfn.XLOOKUP($B69,[1]Billing!$Q$5:$Q$40,[1]Billing!$U$5:$U$40) -> 0 | G104: =_xlfn.XLOOKUP($B69,[1]Billing!$Q$5:$Q$40,[1]Billing!$V$5:$V$40) -> 2389648.9 | H104: =_xlfn.XLOOKUP($B69,[1]Billing!$Q$5:$Q$40,[1]Billing!$W$5:$W$40) -> 0 | I104: =_xlfn.XLOOKUP($B69,[1]Billing!$Q$5:$Q$40,[1]Billing!$X$5:$X$40) -> 0 | J104: =_xlfn.XLOOKUP($B69,[1]Billing!$Q$5:$Q$40,[1]Billing!$Y$5:$Y$40) -> 0 | K104: =_xlfn.XLOOKUP($B69,[1]Billing!$Q$5:$Q$40,[1]Billing!$Z$5:$Z$40) -> 23767.374 | L104: =_xlfn.XLOOKUP($B69,[1]Billing!$Q$5:$Q$40,[1]Billing!$AA$5:$AA$40) -> 523143.75 | M104: =_xlfn.XLOOKUP($B69,[1]Billing!$Q$5:$Q$40,[1]Billing!$AB$5:$AB$40) -> 0 | N104: =G104+H104+I104+J104+K104+L104+M104 -> 2936560 | O104: =_xlfn.XLOOKUP($B69,[1]Billing!$Q$5:$Q$40,[1]Billing!$AD$5:$AD$40) -> 2761895 | P104: =N104-O104 -> 174664.99
B105: Hameed corporation | C105: =_xlfn.XLOOKUP($B70,[1]Billing!$Q$5:$Q$40,[1]Billing!$R$5:$R$40) -> 46404 | D105: =_xlfn.XLOOKUP($B70,[1]Billing!$Q$5:$Q$40,[1]Billing!$S$5:$S$40) -> 42432.334 | E105: =_xlfn.XLOOKUP($B70,[1]Billing!$Q$5:$Q$40,[1]Billing!$T$5:$T$40) -> 42432.334 | F105: =_xlfn.XLOOKUP($B70,[1]Billing!$Q$5:$Q$40,[1]Billing!$U$5:$U$40) -> 0 | G105: =_xlfn.XLOOKUP($B70,[1]Billing!$Q$5:$Q$40,[1]Billing!$V$5:$V$40) -> 424323.34 | H105: =_xlfn.XLOOKUP($B70,[1]Billing!$Q$5:$Q$40,[1]Billing!$W$5:$W$40) -> 0 | I105: =_xlfn.XLOOKUP($B70,[1]Billing!$Q$5:$Q$40,[1]Billing!$X$5:$X$40) -> 0 | J105: =_xlfn.XLOOKUP($B70,[1]Billing!$Q$5:$Q$40,[1]Billing!$Y$5:$Y$40) -> 0 | K105: =_xlfn.XLOOKUP($B70,[1]Billing!$Q$5:$Q$40,[1]Billing!$Z$5:$Z$40) -> 0 | L105: =_xlfn.XLOOKUP($B70,[1]Billing!$Q$5:$Q$40,[1]Billing!$AA$5:$AA$40) -> 0 | M105: =_xlfn.XLOOKUP($B70,[1]Billing!$Q$5:$Q$40,[1]Billing!$AB$5:$AB$40) -> 0 | N105: =G105+H105+I105+J105+K105+L105+M105 -> 424323.34 | O105: =_xlfn.XLOOKUP($B70,[1]Billing!$Q$5:$Q$40,[1]Billing!$AD$5:$AD$40) -> 424323 | P105: =N105-O105 -> 0.33577176
B106: ibraheem behraam | C106: =_xlfn.XLOOKUP($B71,[1]Billing!$Q$5:$Q$40,[1]Billing!$R$5:$R$40) -> 66705 | D106: =_xlfn.XLOOKUP($B71,[1]Billing!$Q$5:$Q$40,[1]Billing!$S$5:$S$40) -> 60995.794 | E106: =_xlfn.XLOOKUP($B71,[1]Billing!$Q$5:$Q$40,[1]Billing!$T$5:$T$40) -> 0 | F106: =_xlfn.XLOOKUP($B71,[1]Billing!$Q$5:$Q$40,[1]Billing!$U$5:$U$40) -> 60995.794 | G106: =_xlfn.XLOOKUP($B71,[1]Billing!$Q$5:$Q$40,[1]Billing!$V$5:$V$40) -> 0 | H106: =_xlfn.XLOOKUP($B71,[1]Billing!$Q$5:$Q$40,[1]Billing!$W$5:$W$40) -> 792945.32 | I106: =_xlfn.XLOOKUP($B71,[1]Billing!$Q$5:$Q$40,[1]Billing!$X$5:$X$40) -> 0 | J106: =_xlfn.XLOOKUP($B71,[1]Billing!$Q$5:$Q$40,[1]Billing!$Y$5:$Y$40) -> 0 | K106: =_xlfn.XLOOKUP($B71,[1]Billing!$Q$5:$Q$40,[1]Billing!$Z$5:$Z$40) -> 0 | L106: =_xlfn.XLOOKUP($B71,[1]Billing!$Q$5:$Q$40,[1]Billing!$AA$5:$AA$40) -> 0 | M106: =_xlfn.XLOOKUP($B71,[1]Billing!$Q$5:$Q$40,[1]Billing!$AB$5:$AB$40) -> 0 | N106: =G106+H106+I106+J106+K106+L106+M106 -> 792945.32 | O106: =_xlfn.XLOOKUP($B71,[1]Billing!$Q$5:$Q$40,[1]Billing!$AD$5:$AD$40) -> 790500 | P106: =N106-O106 -> 2445.3182
B107: Zia-ullah karachi | C107: =_xlfn.XLOOKUP($B72,[1]Billing!$Q$5:$Q$40,[1]Billing!$R$5:$R$40) -> 13622 | D107: =_xlfn.XLOOKUP($B72,[1]Billing!$Q$5:$Q$40,[1]Billing!$S$5:$S$40) -> 12456.108 | E107: =_xlfn.XLOOKUP($B72,[1]Billing!$Q$5:$Q$40,[1]Billing!$T$5:$T$40) -> 12456.108 | F107: =_xlfn.XLOOKUP($B72,[1]Billing!$Q$5:$Q$40,[1]Billing!$U$5:$U$40) -> 0 | G107: =_xlfn.XLOOKUP($B72,[1]Billing!$Q$5:$Q$40,[1]Billing!$V$5:$V$40) -> 124561.08 | H107: =_xlfn.XLOOKUP($B72,[1]Billing!$Q$5:$Q$40,[1]Billing!$W$5:$W$40) -> 0 | I107: =_xlfn.XLOOKUP($B72,[1]Billing!$Q$5:$Q$40,[1]Billing!$X$5:$X$40) -> 0 | J107: =_xlfn.XLOOKUP($B72,[1]Billing!$Q$5:$Q$40,[1]Billing!$Y$5:$Y$40) -> 0 | K107: =_xlfn.XLOOKUP($B72,[1]Billing!$Q$5:$Q$40,[1]Billing!$Z$5:$Z$40) -> 0 | L107: =_xlfn.XLOOKUP($B72,[1]Billing!$Q$5:$Q$40,[1]Billing!$AA$5:$AA$40) -> 0 | M107: =_xlfn.XLOOKUP($B72,[1]Billing!$Q$5:$Q$40,[1]Billing!$AB$5:$AB$40) -> 0 | N107: =G107+H107+I107+J107+K107+L107+M107 -> 124561.08 | O107: =_xlfn.XLOOKUP($B72,[1]Billing!$Q$5:$Q$40,[1]Billing!$AD$5:$AD$40) -> 124560 | P107: =N107-O107 -> 1.0826628
B108: ZA | C108: =_xlfn.XLOOKUP($B73,[1]Billing!$Q$5:$Q$40,[1]Billing!$R$5:$R$40) -> 32399 | D108: =_xlfn.XLOOKUP($B73,[1]Billing!$Q$5:$Q$40,[1]Billing!$S$5:$S$40) -> 29626.006 | E108: =_xlfn.XLOOKUP($B73,[1]Billing!$Q$5:$Q$40,[1]Billing!$T$5:$T$40) -> 0 | F108: =_xlfn.XLOOKUP($B73,[1]Billing!$Q$5:$Q$40,[1]Billing!$U$5:$U$40) -> 29626.006 | G108: =_xlfn.XLOOKUP($B73,[1]Billing!$Q$5:$Q$40,[1]Billing!$V$5:$V$40) -> 0 | H108: =_xlfn.XLOOKUP($B73,[1]Billing!$Q$5:$Q$40,[1]Billing!$W$5:$W$40) -> 385138.08 | I108: =_xlfn.XLOOKUP($B73,[1]Billing!$Q$5:$Q$40,[1]Billing!$X$5:$X$40) -> 0 | J108: =_xlfn.XLOOKUP($B73,[1]Billing!$Q$5:$Q$40,[1]Billing!$Y$5:$Y$40) -> 0 | K108: =_xlfn.XLOOKUP($B73,[1]Billing!$Q$5:$Q$40,[1]Billing!$Z$5:$Z$40) -> 0 | L108: =_xlfn.XLOOKUP($B73,[1]Billing!$Q$5:$Q$40,[1]Billing!$AA$5:$AA$40) -> 0 | M108: =_xlfn.XLOOKUP($B73,[1]Billing!$Q$5:$Q$40,[1]Billing!$AB$5:$AB$40) -> 0 | N108: =G108+H108+I108+J108+K108+L108+M108 -> 385138.08 | O108: =_xlfn.XLOOKUP($B73,[1]Billing!$Q$5:$Q$40,[1]Billing!$AD$5:$AD$40) -> 250000 | P108: =N108-O108 -> 135138.08
B109: Ahmad Javaid | C109: =_xlfn.XLOOKUP($B74,[1]Billing!$Q$5:$Q$40,[1]Billing!$R$5:$R$40) -> 12745 | D109: =_xlfn.XLOOKUP($B74,[1]Billing!$Q$5:$Q$40,[1]Billing!$S$5:$S$40) -> 11654.17 | E109: =_xlfn.XLOOKUP($B74,[1]Billing!$Q$5:$Q$40,[1]Billing!$T$5:$T$40) -> 0 | F109: =_xlfn.XLOOKUP($B74,[1]Billing!$Q$5:$Q$40,[1]Billing!$U$5:$U$40) -> 0 | G109: =_xlfn.XLOOKUP($B74,[1]Billing!$Q$5:$Q$40,[1]Billing!$V$5:$V$40) -> 0 | H109: =_xlfn.XLOOKUP($B74,[1]Billing!$Q$5:$Q$40,[1]Billing!$W$5:$W$40) -> 0 | I109: =_xlfn.XLOOKUP($B74,[1]Billing!$Q$5:$Q$40,[1]Billing!$X$5:$X$40) -> 0 | J109: =_xlfn.XLOOKUP($B74,[1]Billing!$Q$5:$Q$40,[1]Billing!$Y$5:$Y$40) -> 0 | K109: =_xlfn.XLOOKUP($B74,[1]Billing!$Q$5:$Q$40,[1]Billing!$Z$5:$Z$40) -> 0 | L109: =_xlfn.XLOOKUP($B74,[1]Billing!$Q$5:$Q$40,[1]Billing!$AA$5:$AA$40) -> 0 | M109: =_xlfn.XLOOKUP($B74,[1]Billing!$Q$5:$Q$40,[1]Billing!$AB$5:$AB$40) -> 151504.21 | N109: =G109+H109+I109+J109+K109+L109+M109 -> 151504.21 | O109: =_xlfn.XLOOKUP($B74,[1]Billing!$Q$5:$Q$40,[1]Billing!$AD$5:$AD$40) -> 0 | P109: =N109-O109 -> 151504.21
B110: Rehman Ali | C110: =_xlfn.XLOOKUP($B75,[1]Billing!$Q$5:$Q$40,[1]Billing!$R$5:$R$40) -> #N/A | D110: =_xlfn.XLOOKUP($B75,[1]Billing!$Q$5:$Q$40,[1]Billing!$S$5:$S$40) -> #N/A | E110: =_xlfn.XLOOKUP($B75,[1]Billing!$Q$5:$Q$40,[1]Billing!$T$5:$T$40) -> #N/A | F110: =_xlfn.XLOOKUP($B75,[1]Billing!$Q$5:$Q$40,[1]Billing!$U$5:$U$40) -> #N/A | G110: =_xlfn.XLOOKUP($B75,[1]Billing!$Q$5:$Q$40,[1]Billing!$V$5:$V$40) -> #N/A | H110: =_xlfn.XLOOKUP($B75,[1]Billing!$Q$5:$Q$40,[1]Billing!$W$5:$W$40) -> #N/A | I110: =_xlfn.XLOOKUP($B75,[1]Billing!$Q$5:$Q$40,[1]Billing!$X$5:$X$40) -> #N/A | J110: =_xlfn.XLOOKUP($B75,[1]Billing!$Q$5:$Q$40,[1]Billing!$Y$5:$Y$40) -> #N/A | K110: =_xlfn.XLOOKUP($B75,[1]Billing!$Q$5:$Q$40,[1]Billing!$Z$5:$Z$40) -> #N/A | L110: =_xlfn.XLOOKUP($B75,[1]Billing!$Q$5:$Q$40,[1]Billing!$AA$5:$AA$40) -> #N/A | M110: =_xlfn.XLOOKUP($B75,[1]Billing!$Q$5:$Q$40,[1]Billing!$AB$5:$AB$40) -> #N/A | N110: =G110+H110+I110+J110+K110+L110+M110 -> #N/A | O110: =_xlfn.XLOOKUP($B75,[1]Billing!$Q$5:$Q$40,[1]Billing!$AD$5:$AD$40) -> #N/A | P110: =N110-O110 -> #N/A
B111: Shani Badshah | C111: =_xlfn.XLOOKUP($B76,[1]Billing!$Q$5:$Q$40,[1]Billing!$R$5:$R$40) -> #N/A | D111: =_xlfn.XLOOKUP($B76,[1]Billing!$Q$5:$Q$40,[1]Billing!$S$5:$S$40) -> #N/A | E111: =_xlfn.XLOOKUP($B76,[1]Billing!$Q$5:$Q$40,[1]Billing!$T$5:$T$40) -> #N/A | F111: =_xlfn.XLOOKUP($B76,[1]Billing!$Q$5:$Q$40,[1]Billing!$U$5:$U$40) -> #N/A | G111: =_xlfn.XLOOKUP($B76,[1]Billing!$Q$5:$Q$40,[1]Billing!$V$5:$V$40) -> #N/A | H111: =_xlfn.XLOOKUP($B76,[1]Billing!$Q$5:$Q$40,[1]Billing!$W$5:$W$40) -> #N/A | I111: =_xlfn.XLOOKUP($B76,[1]Billing!$Q$5:$Q$40,[1]Billing!$X$5:$X$40) -> #N/A | J111: =_xlfn.XLOOKUP($B76,[1]Billing!$Q$5:$Q$40,[1]Billing!$Y$5:$Y$40) -> #N/A | K111: =_xlfn.XLOOKUP($B76,[1]Billing!$Q$5:$Q$40,[1]Billing!$Z$5:$Z$40) -> #N/A | L111: =_xlfn.XLOOKUP($B76,[1]Billing!$Q$5:$Q$40,[1]Billing!$AA$5:$AA$40) -> #N/A | M111: =_xlfn.XLOOKUP($B76,[1]Billing!$Q$5:$Q$40,[1]Billing!$AB$5:$AB$40) -> #N/A | N111: =G111+H111+I111+J111+K111+L111+M111 -> #N/A | O111: =_xlfn.XLOOKUP($B76,[1]Billing!$Q$5:$Q$40,[1]Billing!$AD$5:$AD$40) -> #N/A | P111: =N111-O111 -> #N/A
B112: Ahmad Shafique | C112: =_xlfn.XLOOKUP($B77,[1]Billing!$Q$5:$Q$40,[1]Billing!$R$5:$R$40) -> #N/A | D112: =_xlfn.XLOOKUP($B77,[1]Billing!$Q$5:$Q$40,[1]Billing!$S$5:$S$40) -> #N/A | E112: =_xlfn.XLOOKUP($B77,[1]Billing!$Q$5:$Q$40,[1]Billing!$T$5:$T$40) -> #N/A | F112: =_xlfn.XLOOKUP($B77,[1]Billing!$Q$5:$Q$40,[1]Billing!$U$5:$U$40) -> #N/A | G112: =_xlfn.XLOOKUP($B77,[1]Billing!$Q$5:$Q$40,[1]Billing!$V$5:$V$40) -> #N/A | H112: =_xlfn.XLOOKUP($B77,[1]Billing!$Q$5:$Q$40,[1]Billing!$W$5:$W$40) -> #N/A | I112: =_xlfn.XLOOKUP($B77,[1]Billing!$Q$5:$Q$40,[1]Billing!$X$5:$X$40) -> #N/A | J112: =_xlfn.XLOOKUP($B77,[1]Billing!$Q$5:$Q$40,[1]Billing!$Y$5:$Y$40) -> #N/A | K112: =_xlfn.XLOOKUP($B77,[1]Billing!$Q$5:$Q$40,[1]Billing!$Z$5:$Z$40) -> #N/A | L112: =_xlfn.XLOOKUP($B77,[1]Billing!$Q$5:$Q$40,[1]Billing!$AA$5:$AA$40) -> #N/A | M112: =_xlfn.XLOOKUP($B77,[1]Billing!$Q$5:$Q$40,[1]Billing!$AB$5:$AB$40) -> #N/A | N112: =G112+H112+I112+J112+K112+L112+M112 -> #N/A | O112: =_xlfn.XLOOKUP($B77,[1]Billing!$Q$5:$Q$40,[1]Billing!$AD$5:$AD$40) -> #N/A | P112: =N112-O112 -> #N/A
B113: Hafiz Shawl | C113: =_xlfn.XLOOKUP($B78,[1]Billing!$Q$5:$Q$40,[1]Billing!$R$5:$R$40) -> #N/A | D113: =_xlfn.XLOOKUP($B78,[1]Billing!$Q$5:$Q$40,[1]Billing!$S$5:$S$40) -> #N/A | E113: =_xlfn.XLOOKUP($B78,[1]Billing!$Q$5:$Q$40,[1]Billing!$T$5:$T$40) -> #N/A | F113: =_xlfn.XLOOKUP($B78,[1]Billing!$Q$5:$Q$40,[1]Billing!$U$5:$U$40) -> #N/A | G113: =_xlfn.XLOOKUP($B78,[1]Billing!$Q$5:$Q$40,[1]Billing!$V$5:$V$40) -> #N/A | H113: =_xlfn.XLOOKUP($B78,[1]Billing!$Q$5:$Q$40,[1]Billing!$W$5:$W$40) -> #N/A | I113: =_xlfn.XLOOKUP($B78,[1]Billing!$Q$5:$Q$40,[1]Billing!$X$5:$X$40) -> #N/A | J113: =_xlfn.XLOOKUP($B78,[1]Billing!$Q$5:$Q$40,[1]Billing!$Y$5:$Y$40) -> #N/A | K113: =_xlfn.XLOOKUP($B78,[1]Billing!$Q$5:$Q$40,[1]Billing!$Z$5:$Z$40) -> #N/A | L113: =_xlfn.XLOOKUP($B78,[1]Billing!$Q$5:$Q$40,[1]Billing!$AA$5:$AA$40) -> #N/A | M113: =_xlfn.XLOOKUP($B78,[1]Billing!$Q$5:$Q$40,[1]Billing!$AB$5:$AB$40) -> #N/A | N113: =G113+H113+I113+J113+K113+L113+M113 -> #N/A | O113: =_xlfn.XLOOKUP($B78,[1]Billing!$Q$5:$Q$40,[1]Billing!$AD$5:$AD$40) -> #N/A | P113: =N113-O113 -> #N/A
C114: =_xlfn.XLOOKUP($B79,[1]Billing!$Q$5:$Q$40,[1]Billing!$R$5:$R$40) -> 0 | D114: =_xlfn.XLOOKUP($B79,[1]Billing!$Q$5:$Q$40,[1]Billing!$S$5:$S$40) -> 0 | E114: =_xlfn.XLOOKUP($B79,[1]Billing!$Q$5:$Q$40,[1]Billing!$T$5:$T$40) -> 0 | F114: =_xlfn.XLOOKUP($B79,[1]Billing!$Q$5:$Q$40,[1]Billing!$U$5:$U$40) -> 0 | G114: =_xlfn.XLOOKUP($B79,[1]Billing!$Q$5:$Q$40,[1]Billing!$V$5:$V$40) -> 0 | H114: =_xlfn.XLOOKUP($B79,[1]Billing!$Q$5:$Q$40,[1]Billing!$W$5:$W$40) -> 0 | I114: =_xlfn.XLOOKUP($B79,[1]Billing!$Q$5:$Q$40,[1]Billing!$X$5:$X$40) -> 0 | J114: =_xlfn.XLOOKUP($B79,[1]Billing!$Q$5:$Q$40,[1]Billing!$Y$5:$Y$40) -> 0 | K114: =_xlfn.XLOOKUP($B79,[1]Billing!$Q$5:$Q$40,[1]Billing!$Z$5:$Z$40) -> 0 | L114: =_xlfn.XLOOKUP($B79,[1]Billing!$Q$5:$Q$40,[1]Billing!$AA$5:$AA$40) -> 0 | M114: =_xlfn.XLOOKUP($B79,[1]Billing!$Q$5:$Q$40,[1]Billing!$AB$5:$AB$40) -> 0 | N114: =G114+H114+I114+J114+K114+L114+M114 -> 0 | O114: =_xlfn.XLOOKUP($B79,[1]Billing!$Q$5:$Q$40,[1]Billing!$AD$5:$AD$40) -> 0 | P114: =N114-O114 -> 0
C115: =_xlfn.XLOOKUP($B80,[1]Billing!$Q$5:$Q$40,[1]Billing!$R$5:$R$40) -> 0 | D115: =_xlfn.XLOOKUP($B80,[1]Billing!$Q$5:$Q$40,[1]Billing!$S$5:$S$40) -> 0 | E115: =_xlfn.XLOOKUP($B80,[1]Billing!$Q$5:$Q$40,[1]Billing!$T$5:$T$40) -> 0 | F115: =_xlfn.XLOOKUP($B80,[1]Billing!$Q$5:$Q$40,[1]Billing!$U$5:$U$40) -> 0 | G115: =_xlfn.XLOOKUP($B80,[1]Billing!$Q$5:$Q$40,[1]Billing!$V$5:$V$40) -> 0 | H115: =_xlfn.XLOOKUP($B80,[1]Billing!$Q$5:$Q$40,[1]Billing!$W$5:$W$40) -> 0 | I115: =_xlfn.XLOOKUP($B80,[1]Billing!$Q$5:$Q$40,[1]Billing!$X$5:$X$40) -> 0 | J115: =_xlfn.XLOOKUP($B80,[1]Billing!$Q$5:$Q$40,[1]Billing!$Y$5:$Y$40) -> 0 | K115: =_xlfn.XLOOKUP($B80,[1]Billing!$Q$5:$Q$40,[1]Billing!$Z$5:$Z$40) -> 0 | L115: =_xlfn.XLOOKUP($B80,[1]Billing!$Q$5:$Q$40,[1]Billing!$AA$5:$AA$40) -> 0 | M115: =_xlfn.XLOOKUP($B80,[1]Billing!$Q$5:$Q$40,[1]Billing!$AB$5:$AB$40) -> 0 | N115: =G115+H115+I115+J115+K115+L115+M115 -> 0 | O115: =_xlfn.XLOOKUP($B80,[1]Billing!$Q$5:$Q$40,[1]Billing!$AD$5:$AD$40) -> 0 | P115: =N115-O115 -> 0

Sheet Bill Print
I4: Party Names: | J4: {=_xlfn.UNIQUE(Table1[Party Name])} -> BSC
J5: Ejaz Sahab
B6: Faizan | J6: Arshad
B7: Description | C7: Rate | D7: gazana | E7: sum | J7: Shehzad Kamoki
B8: Total Gazana/gaz | D8: {=_xlfn.XLOOKUP($B$6,_xlfn.ANCHORARRAY( Billing!Q5), INDEX(Billing!R5:R25, _xlfn.SEQUENCE(ROWS(_xlfn.ANCHORARRAY(Billing!$Q$5)))), "Not Found")} -> 509411 | J8: Sufi Nawaz Sahab
J9: Sajad Khan
B10: Gazana/meters | D10: {=_xlfn.XLOOKUP($B$6,_xlfn.ANCHORARRAY( Billing!$Q$5), INDEX(Billing!S5:S25, _xlfn.SEQUENCE(ROWS(_xlfn.ANCHORARRAY(Billing!$Q$5)))), "Not Found")} -> 465811.08 | J10: Raaz Fabrics
J11: Azam
B12: Total Chamki-crinkle/meters | C12: {=_xlfn.XLOOKUP($B$6,_xlfn.ANCHORARRAY( Billing!$B$49), OFFSET(Billing!Q49, 0, 0, ROWS(_xlfn.ANCHORARRAY(Billing!$B$49))), "Not Found")} -> 10 | D12: {=_xlfn.XLOOKUP($B$6,_xlfn.ANCHORARRAY( Billing!$Q$5), INDEX(Billing!T5:T25, _xlfn.SEQUENCE(ROWS(_xlfn.ANCHORARRAY(Billing!$Q$5)))), "Not Found")} -> 0 | E12: =Table21[[#This Row],[gazana]]*Table21[[#This Row],[Rate]] -> 0 | J12: Ubaidullah
J13: Ashraf Zia
B14: Total Super Silky/meters | C14: 13 | D14: {=_xlfn.XLOOKUP($B$6,_xlfn.ANCHORARRAY( Billing!$Q$5), INDEX(Billing!U5:U25, _xlfn.SEQUENCE(ROWS(_xlfn.ANCHORARRAY(Billing!$Q$5)))), "Not Found")} -> 462841.08 | E14: =Table21[[#This Row],[gazana]]*Table21[[#This Row],[Rate]] -> 6016934 | J14: Hafiz Qureshi
J15: Badshah Fabrics
B16: Total Billing | E16: =E12+E14 -> 6016934 | J16: Gauhar Kashif
J17: Amjad 7up
B18: Total Paid | E18: {=_xlfn.XLOOKUP($B$6,_xlfn.ANCHORARRAY( Billing!Q5), OFFSET(Billing!AD5, 0, 0, ROWS(_xlfn.ANCHORARRAY(Billing!Q5))), "Not Found")} -> 6024187 | J18: Hazrat Khan
J19: Haseeb Shamsi
B20: Total Balance | E20: {=_xlfn.XLOOKUP($B$6,_xlfn.ANCHORARRAY( Billing!Q5), OFFSET(Billing!AE5, 0, 0, ROWS(_xlfn.ANCHORARRAY(Billing!Q5))), "Not Found")} -> 67297.089 | J20: Faizan
J21: Shafique Ansari
J22: Amjad sohail
J23: Salman Zaffar
J24: Shahid Qasayi
J25: Hameed corporation
J26: ibraheem behraam
J27: Zia-ullah karachi
J28: ZA
J29: Ahmad Javaid
J30: Rehman Ali
J31: Shani Badshah
J32: Ahmad Shafique
J33: Hafiz Shawl

Sheet Expenses
B1: Expenses
B3: Type | C3: Amount | D3: Description | E3: cost per meter
B4: Wood | C4: =Wood!K6+(2000*810)-(1000*800) -> 7632370 | E4: =Table12[[#This Row],[Amount]]/Table1[[#Totals],[tiyar/meters]] -> 4.1162911
B5: Dyes/Chemical | C5: =SUM(Table8[Price])+(291000)-301660 -> 1899865 | E5: =Table12[[#This Row],[Amount]]/Table1[[#Totals],[tiyar/meters]] -> 1.0246355
B6: Finish | C6: =SUM(Table2[Price])+38750 -> 777350 | E6: =Table12[[#This Row],[Amount]]/Table1[[#Totals],[tiyar/meters]] -> 0.41924053
B7: Misc | C7: =SUMIFS(Table14[Debit], Table14[Party],Table12[[#This Row],[Type]]) -> 234395 | E7: =Table12[[#This Row],[Amount]]/Table1[[#Totals],[tiyar/meters]] -> 0.12641395
B8: Electricity | C8: =Electricity!E3 -> 2222081 | E8: =Table12[[#This Row],[Amount]]/Table1[[#Totals],[tiyar/meters]] -> 1.1984131
B9: Salary | C9: =SUMIFS(Table14[Debit], Table14[Party],Table12[[#This Row],[Type]])+SUMIFS(Table14[Debit], Table14[Party],"Advance Salary") -> 3699533 | E9: =Table12[[#This Row],[Amount]]/Table1[[#Totals],[tiyar/meters]] -> 1.9952328
B10: Running Acc | C10: =Table5[[#Totals],[Amount]] -> 142730 | E10: =Table12[[#This Row],[Amount]]/Table1[[#Totals],[tiyar/meters]] -> 0.076977168
B11: Transport | C11: =Table13[[#Totals],[Debit]] -> 151730 | E11: =Table12[[#This Row],[Amount]]/Table1[[#Totals],[tiyar/meters]] -> 0.081831049
B12: Parts | C12: =Table15[[#Totals],[Amount]] -> 307771 | E12: =Table12[[#This Row],[Amount]]/Table1[[#Totals],[tiyar/meters]] -> 0.16598711
E13: =Table12[[#This Row],[Amount]]/Table1[[#Totals],[tiyar/meters]] -> 0
C14: =SUM(Table12[Amount]) -> 17067825 | E14: =SUM(Table12[cost per meter]) -> 9.2050223
B17: Stock (for next 15th)
B18: Stock | C18: quantity | D18: Column3
B19: Wood | C19: =388+236+100+288 -> 1012 | D19: mann
B20: Starch | C20: 100 | D20: Kg
B21: Pva | C21: 75 | D21: Kg
B22: Dyes | C22: Nil

Sheet Profit
B2: Column1 | C2: Column2
B3: Billing | C3: =Billing!C23 + SUMIFS(Table14[Credit], Table14[Party], "Transport") -> 20808860
B4: Expenses | C4: =Table12[[#Totals],[Amount]] -> 17067825
B5: Profit | C5: =C3-C4 -> 3741034.7
B10: Column1 | C10: Column2
B11: Billing | C11: =C3 -> 20808860
B12: Credit | C12: =SUM(Table14[Credit]) -> 31270241
B13: balance | C13: =(C11-C12) -> -10461381
B15: Expenses | C15: =C4 -> 17067825
B16: Debit | C16: =SUM(Table14[Debit]) -> 25988515
B17: Exp Balance | C17: =C15-C16 -> -8920690.2
B19: Cash in hand | C19: =Table18[[#Totals],[amount]] -> 5281726
B21: Difference | C21: =(C13-C17)+C19 -> 3741034.7 | E21: My share: | F21: =C5*0.05 -> 187051.74

Sheet Transport
B2: Date | C2: Type | D2: Debit | E2: Credit | F2: Diff
B3: 46040 | D3: =SUMIFS(Table14[Debit], Table14[Date], Table13[[#This Row],[Date]], Table14[Party], "Transport") -> 0 | E3: =SUMIFS(Table14[Credit], Table14[Date], Table13[[#This Row],[Date]], Table14[Party], "Transport") -> 0
B4: 46041 | D4: =SUMIFS(Table14[Debit], Table14[Date], Table13[[#This Row],[Date]], Table14[Party], "Transport") -> 0 | E4: =SUMIFS(Table14[Credit], Table14[Date], Table13[[#This Row],[Date]], Table14[Party], "Transport") -> 0
B5: 46042 | D5: =SUMIFS(Table14[Debit], Table14[Date], Table13[[#This Row],[Date]], Table14[Party], "Transport") -> 0 | E5: =SUMIFS(Table14[Credit], Table14[Date], Table13[[#This Row],[Date]], Table14[Party], "Transport") -> 0
B6: 46043 | D6: =SUMIFS(Table14[Debit], Table14[Date], Table13[[#This Row],[Date]], Table14[Party], "Transport") -> 3000 | E6: =SUMIFS(Table14[Credit], Table14[Date], Table13[[#This Row],[Date]], Table14[Party], "Transport") -> 0
B7: 46044 | D7: =SUMIFS(Table14[Debit], Table14[Date], Table13[[#This Row],[Date]], Table14[Party], "Transport") -> 11600 | E7: =SUMIFS(Table14[Credit], Table14[Date], Table13[[#This Row],[Date]], Table14[Party], "Transport") -> 0
B8: 46045 | D8: =SUMIFS(Table14[Debit], Table14[Date], Table13[[#This Row],[Date]], Table14[Party], "Transport") -> 5000 | E8: =SUMIFS(Table14[Credit], Table14[Date], Table13[[#This Row],[Date]], Table14[Party], "Transport") -> 0
B9: 46046 | D9: =SUMIFS(Table14[Debit], Table14[Date], Table13[[#This Row],[Date]], Table14[Party], "Transport") -> 5000 | E9: =SUMIFS(Table14[Credit], Table14[Date], Table13[[#This Row],[Date]], Table14[Party], "Transport") -> 0
B10: 46047 | D10: =SUMIFS(Table14[Debit], Table14[Date], Table13[[#This Row],[Date]], Table14[Party], "Transport") -> 3700 | E10: =SUMIFS(Table14[Credit], Table14[Date], Table13[[#This Row],[Date]], Table14[Party], "Transport") -> 0
B11: 46048 | D11: =SUMIFS(Table14[Debit], Table14[Date], Table13[[#This Row],[Date]], Table14[Party], "Transport") -> 3300 | E11: =SUMIFS(Table14[Credit], Table14[Date], Table13[[#This Row],[Date]], Table14[Party], "Transport") -> 0
B12: 46049 | D12: =SUMIFS(Table14[Debit], Table14[Date], Table13[[#This Row],[Date]], Table14[Party], "Transport") -> 500 | E12: =SUMIFS(Table14[Credit], Table14[Date], Table13[[#This Row],[Date]], Table14[Party], "Transport") -> 0
B13: 46050 | D13: =SUMIFS(Table14[Debit], Table14[Date], Table13[[#This Row],[Date]], Table14[Party], "Transport") -> 0 | E13: =SUMIFS(Table14[Credit], Table14[Date], Table13[[#This Row],[Date]], Table14[Party], "Transport") -> 0
B14: 46051 | D14: =SUMIFS(Table14[Debit], Table14[Date], Table13[[#This Row],[Date]], Table14[Party], "Transport") -> 11400 | E14: =SUMIFS(Table14[Credit], Table14[Date], Table13[[#This Row],[Date]], Table14[Party], "Transport") -> 0
... B43: 46046 | D43: =SUMIFS(Table14[Debit], Table14[Date], Table13[[#This Row],[Date]], Table14[Party], "Transport") -> 5000 | E43: =SUMIFS(Table14[Credit], Table14[Date], Table13[[#This Row],[Date]], Table14[Party], "Transport") -> 0
D44: =SUBTOTAL(109,Table13[Debit]) -> 151730 | E44: =SUBTOTAL(109,Table13[Credit]) -> 0 | F44: =Table13[[#Totals],[Debit]]-Table13[[#Totals],[Credit]] -> 151730

Sheet ledger
A1: Date | B1: Party Name | C1: Bill Number | D1: Quality | E1: Shipment Number | F1: Kora/metre | G1: Tiyaar/gaz | H1: shortage % | I1: tiyar/meters | J1: billing | K1: Total Billing
A2: 46042 | B2: BSC | C2: December Closing CF | D2: Chamki | H2: =_xlfn.XLOOKUP(Table1[[#This Row],[Shipment Number]], 'pivot '!A:A,'pivot '!G:G, "NF") -> #DIV/0! | I2: =_xlfn.XLOOKUP(Table1[[#This Row],[Party Name]], [1]Billing!$Q$5:$Q$40, [1]Billing!$T$5:$T$40) -> 2468066.8 | J2: =_xlfn.XLOOKUP(Table1[[#This Row],[Party Name]], [1]Billing!$Q$5:$Q$40, [1]Billing!$V$5:$V$40) -> 24680668 | M2: {=_xlfn.UNIQUE(Table1[Party Name])} -> BSC
A3: 46042 | B3: Ejaz Sahab | C3: December Closing CF | D3: Chamki | H3: =_xlfn.XLOOKUP(Table1[[#This Row],[Shipment Number]], 'pivot '!A:A,'pivot '!G:G, "NF") -> #DIV/0! | I3: =_xlfn.XLOOKUP(Table1[[#This Row],[Party Name]], [1]Billing!$Q$5:$Q$40, [1]Billing!$T$5:$T$40) -> 148145.57 | J3: =_xlfn.XLOOKUP(Table1[[#This Row],[Party Name]], [1]Billing!$Q$5:$Q$40, [1]Billing!$V$5:$V$40) -> 1481455.7 | M3: Ejaz Sahab
A4: 46042 | B4: Arshad | C4: December Closing CF | D4: Chamki | H4: =_xlfn.XLOOKUP(Table1[[#This Row],[Shipment Number]], 'pivot '!A:A,'pivot '!G:G, "NF") -> #DIV/0! | I4: =_xlfn.XLOOKUP(Table1[[#This Row],[Party Name]], [1]Billing!$Q$5:$Q$40, [1]Billing!$T$5:$T$40) -> 626388.08 | J4: =_xlfn.XLOOKUP(Table1[[#This Row],[Party Name]], [1]Billing!$Q$5:$Q$40, [1]Billing!$V$5:$V$40) -> 6263880.8 | M4: Arshad
A5: 46042 | B5: Shehzad Kamoki | C5: December Closing CF | D5: Chamki | H5: =_xlfn.XLOOKUP(Table1[[#This Row],[Shipment Number]], 'pivot '!A:A,'pivot '!G:G, "NF") -> #DIV/0! | I5: =_xlfn.XLOOKUP(Table1[[#This Row],[Party Name]], [1]Billing!$Q$5:$Q$40, [1]Billing!$T$5:$T$40) -> 131178.68 | J5: =_xlfn.XLOOKUP(Table1[[#This Row],[Party Name]], [1]Billing!$Q$5:$Q$40, [1]Billing!$V$5:$V$40) -> 1354242 | M5: Shehzad Kamoki
A6: 46042 | B6: Sufi Nawaz Sahab | C6: December Closing CF | D6: Chamki | H6: =_xlfn.XLOOKUP(Table1[[#This Row],[Shipment Number]], 'pivot '!A:A,'pivot '!G:G, "NF") -> #DIV/0! | I6: =_xlfn.XLOOKUP(Table1[[#This Row],[Party Name]], [1]Billing!$Q$5:$Q$40, [1]Billing!$T$5:$T$40) -> 599330.65 | J6: =_xlfn.XLOOKUP(Table1[[#This Row],[Party Name]], [1]Billing!$Q$5:$Q$40, [1]Billing!$V$5:$V$40) -> 5408917.9 | M6: Sufi Nawaz Sahab
A7: 46042 | B7: Sajad Khan | C7: December Closing CF | D7: Chamki | H7: =_xlfn.XLOOKUP(Table1[[#This Row],[Shipment Number]], 'pivot '!A:A,'pivot '!G:G, "NF") -> #DIV/0! | I7: =_xlfn.XLOOKUP(Table1[[#This Row],[Party Name]], [1]Billing!$Q$5:$Q$40, [1]Billing!$T$5:$T$40) -> 837856.62 | J7: =_xlfn.XLOOKUP(Table1[[#This Row],[Party Name]], [1]Billing!$Q$5:$Q$40, [1]Billing!$V$5:$V$40) -> 8378566.2 | M7: Sajad Khan
A8: 46042 | B8: Raaz Fabrics | C8: December Closing CF | D8: Chamki | H8: =_xlfn.XLOOKUP(Table1[[#This Row],[Shipment Number]], 'pivot '!A:A,'pivot '!G:G, "NF") -> #DIV/0! | I8: =_xlfn.XLOOKUP(Table1[[#This Row],[Party Name]], [1]Billing!$Q$5:$Q$40, [1]Billing!$T$5:$T$40) -> 162638.08 | J8: =_xlfn.XLOOKUP(Table1[[#This Row],[Party Name]], [1]Billing!$Q$5:$Q$40, [1]Billing!$V$5:$V$40) -> 1626380.8 | M8: Raaz Fabrics
A9: 46042 | B9: Azam | C9: December Closing CF | D9: Chamki | H9: =_xlfn.XLOOKUP(Table1[[#This Row],[Shipment Number]], 'pivot '!A:A,'pivot '!G:G, "NF") -> #DIV/0! | I9: =_xlfn.XLOOKUP(Table1[[#This Row],[Party Name]], [1]Billing!$Q$5:$Q$40, [1]Billing!$T$5:$T$40) -> 400309.07 | J9: =_xlfn.XLOOKUP(Table1[[#This Row],[Party Name]], [1]Billing!$Q$5:$Q$40, [1]Billing!$V$5:$V$40) -> 4003090.7 | M9: Azam
A10: 46042 | B10: Ubaidullah | C10: December Closing CF | D10: Chamki | H10: =_xlfn.XLOOKUP(Table1[[#This Row],[Shipment Number]], 'pivot '!A:A,'pivot '!G:G, "NF") -> #DIV/0! | I10: =_xlfn.XLOOKUP(Table1[[#This Row],[Party Name]], [1]Billing!$Q$5:$Q$40, [1]Billing!$T$5:$T$40) -> 46132.955 | J10: =_xlfn.XLOOKUP(Table1[[#This Row],[Party Name]], [1]Billing!$Q$5:$Q$40, [1]Billing!$V$5:$V$40) -> 461329.55 | M10: Ubaidullah
A11: 46042 | B11: Ashraf Zia | C11: December Closing CF | D11: Chamki | H11: =_xlfn.XLOOKUP(Table1[[#This Row],[Shipment Number]], 'pivot '!A:A,'pivot '!G:G, "NF") -> #DIV/0! | I11: =_xlfn.XLOOKUP(Table1[[#This Row],[Party Name]], [1]Billing!$Q$5:$Q$40, [1]Billing!$T$5:$T$40) -> 21310.351 | J11: =_xlfn.XLOOKUP(Table1[[#This Row],[Party Name]], [1]Billing!$Q$5:$Q$40, [1]Billing!$V$5:$V$40) -> 255724.21 | M11: Ashraf Zia
A12: 46042 | B12: Hafiz Qureshi | C12: December Closing CF | D12: Chamki | H12: =_xlfn.XLOOKUP(Table1[[#This Row],[Shipment Number]], 'pivot '!A:A,'pivot '!G:G, "NF") -> #DIV/0! | I12: =_xlfn.XLOOKUP(Table1[[#This Row],[Party Name]], [1]Billing!$Q$5:$Q$40, [1]Billing!$T$5:$T$40) -> 287970.01 | J12: =_xlfn.XLOOKUP(Table1[[#This Row],[Party Name]], [1]Billing!$Q$5:$Q$40, [1]Billing!$V$5:$V$40) -> 2879700.1 | M12: Hafiz Qureshi
A13: 46042 | B13: Badshah Fabrics | C13: December Closing CF | D13: Chamki | H13: =_xlfn.XLOOKUP(Table1[[#This Row],[Shipment Number]], 'pivot '!A:A,'pivot '!G:G, "NF") -> #DIV/0! | I13: =_xlfn.XLOOKUP(Table1[[#This Row],[Party Name]], [1]Billing!$Q$5:$Q$40, [1]Billing!$T$5:$T$40) -> 481526.15 | J13: =_xlfn.XLOOKUP(Table1[[#This Row],[Party Name]], [1]Billing!$Q$5:$Q$40, [1]Billing!$V$5:$V$40) -> 4861679.8 | M13: Badshah Fabrics
A14: 46042 | B14: Gauhar Kashif | C14: December Closing CF | D14: Chamki | H14: =_xlfn.XLOOKUP(Table1[[#This Row],[Shipment Number]], 'pivot '!A:A,'pivot '!G:G, "NF") -> #DIV/0! | I14: =_xlfn.XLOOKUP(Table1[[#This Row],[Party Name]], [1]Billing!$Q$5:$Q$40, [1]Billing!$T$5:$T$40) -> 50406.913 | J14: =_xlfn.XLOOKUP(Table1[[#This Row],[Party Name]], [1]Billing!$Q$5:$Q$40, [1]Billing!$V$5:$V$40) -> 504069.13 | M14: Gauhar Kashif
... A27: 46042 | B27: Ahmad Javaid | C27: December Closing CF | D27: Chamki | H27: =_xlfn.XLOOKUP(Table1[[#This Row],[Shipment Number]], 'pivot '!A:A,'pivot '!G:G, "NF") -> #DIV/0! | I27: =_xlfn.XLOOKUP(Table1[[#This Row],[Party Name]], [1]Billing!$Q$5:$Q$40, [1]Billing!$T$5:$T$40) -> 0 | J27: =_xlfn.XLOOKUP(Table1[[#This Row],[Party Name]], [1]Billing!$Q$5:$Q$40, [1]Billing!$V$5:$V$40) -> 0 | M27: Ahmad Javaid
A28: 46042 | B28: BSC | C28: December Closing CF | D28: Silky | H28: =_xlfn.XLOOKUP(Table1[[#This Row],[Shipment Number]], 'pivot '!A:A,'pivot '!G:G, "NF") -> #DIV/0! | I28: =_xlfn.XLOOKUP(Table1[[#This Row],[Party Name]], [1]Billing!$Q$5:$Q$40, [1]Billing!$U$5:$U$40) -> 379933.25 | J28: =_xlfn.XLOOKUP(Table1[[#This Row],[Party Name]], [1]Billing!$Q$5:$Q$40, [1]Billing!$W$5:$W$40) -> 4850776.3 | M28: Rehman Ali
A29: 46042 | B29: Ejaz Sahab | C29: December Closing CF | D29: Silky | H29: =_xlfn.XLOOKUP(Table1[[#This Row],[Shipment Number]], 'pivot '!A:A,'pivot '!G:G, "NF") -> #DIV/0! | I29: =_xlfn.XLOOKUP(Table1[[#This Row],[Party Name]], [1]Billing!$Q$5:$Q$40, [1]Billing!$U$5:$U$40) -> 290231.35 | J29: =_xlfn.XLOOKUP(Table1[[#This Row],[Party Name]], [1]Billing!$Q$5:$Q$40, [1]Billing!$W$5:$W$40) -> 3713863.4 | M29: Shani Badshah
A30: 46042 | B30: Arshad | C30: December Closing CF | D30: Silky | H30: =_xlfn.XLOOKUP(Table1[[#This Row],[Shipment Number]], 'pivot '!A:A,'pivot '!G:G, "NF") -> #DIV/0! | I30: =_xlfn.XLOOKUP(Table1[[#This Row],[Party Name]], [1]Billing!$Q$5:$Q$40, [1]Billing!$U$5:$U$40) -> 126699.89 | J30: =_xlfn.XLOOKUP(Table1[[#This Row],[Party Name]], [1]Billing!$Q$5:$Q$40, [1]Billing!$W$5:$W$40) -> 1632304.3 | M30: Ahmad Shafique
A31: 46042 | B31: Shehzad Kamoki | C31: December Closing CF | D31: Silky | H31: =_xlfn.XLOOKUP(Table1[[#This Row],[Shipment Number]], 'pivot '!A:A,'pivot '!G:G, "NF") -> #DIV/0! | I31: =_xlfn.XLOOKUP(Table1[[#This Row],[Party Name]], [1]Billing!$Q$5:$Q$40, [1]Billing!$U$5:$U$40) -> 0 | J31: =_xlfn.XLOOKUP(Table1[[#This Row],[Party Name]], [1]Billing!$Q$5:$Q$40, [1]Billing!$W$5:$W$40) -> 0 | M31: Hafiz Shawl
A32: 46042 | B32: Sufi Nawaz Sahab | C32: December Closing CF | D32: Silky | H32: =_xlfn.XLOOKUP(Table1[[#This Row],[Shipment Number]], 'pivot '!A:A,'pivot '!G:G, "NF") -> #DIV/0! | I32: =_xlfn.XLOOKUP(Table1[[#This Row],[Party Name]], [1]Billing!$Q$5:$Q$40, [1]Billing!$U$5:$U$40) -> 485823.88 | J32: =_xlfn.XLOOKUP(Table1[[#This Row],[Party Name]], [1]Billing!$Q$5:$Q$40, [1]Billing!$W$5:$W$40) -> 5829886.6
A33: 46042 | B33: Sajad Khan | C33: December Closing CF | D33: Silky | H33: =_xlfn.XLOOKUP(Table1[[#This Row],[Shipment Number]], 'pivot '!A:A,'pivot '!G:G, "NF") -> #DIV/0! | I33: =_xlfn.XLOOKUP(Table1[[#This Row],[Party Name]], [1]Billing!$Q$5:$Q$40, [1]Billing!$U$5:$U$40) -> 0 | J33: =_xlfn.XLOOKUP(Table1[[#This Row],[Party Name]], [1]Billing!$Q$5:$Q$40, [1]Billing!$W$5:$W$40) -> 0
A34: 46042 | B34: Raaz Fabrics | C34: December Closing CF | D34: Silky | H34: =_xlfn.XLOOKUP(Table1[[#This Row],[Shipment Number]], 'pivot '!A:A,'pivot '!G:G, "NF") -> #DIV/0! | I34: =_xlfn.XLOOKUP(Table1[[#This Row],[Party Name]], [1]Billing!$Q$5:$Q$40, [1]Billing!$U$5:$U$40) -> 0 | J34: =_xlfn.XLOOKUP(Table1[[#This Row],[Party Name]], [1]Billing!$Q$5:$Q$40, [1]Billing!$W$5:$W$40) -> 0
A35: 46042 | B35: Azam | C35: December Closing CF | D35: Silky | H35: =_xlfn.XLOOKUP(Table1[[#This Row],[Shipment Number]], 'pivot '!A:A,'pivot '!G:G, "NF") -> #DIV/0! | I35: =_xlfn.XLOOKUP(Table1[[#This Row],[Party Name]], [1]Billing!$Q$5:$Q$40, [1]Billing!$U$5:$U$40) -> 96615.764 | J35: =_xlfn.XLOOKUP(Table1[[#This Row],[Party Name]], [1]Billing!$Q$5:$Q$40, [1]Billing!$W$5:$W$40) -> 1256004.9
A36: 46042 | B36: Ubaidullah | C36: December Closing CF | D36: Silky | H36: =_xlfn.XLOOKUP(Table1[[#This Row],[Shipment Number]], 'pivot '!A:A,'pivot '!G:G, "NF") -> #DIV/0! | I36: =_xlfn.XLOOKUP(Table1[[#This Row],[Party Name]], [1]Billing!$Q$5:$Q$40, [1]Billing!$U$5:$U$40) -> 69492.502 | J36: =_xlfn.XLOOKUP(Table1[[#This Row],[Party Name]], [1]Billing!$Q$5:$Q$40, [1]Billing!$W$5:$W$40) -> 888407.1
A37: 46042 | B37: Ashraf Zia | C37: December Closing CF | D37: Silky | H37: =_xlfn.XLOOKUP(Table1[[#This Row],[Shipment Number]], 'pivot '!A:A,'pivot '!G:G, "NF") -> #DIV/0! | I37: =_xlfn.XLOOKUP(Table1[[#This Row],[Party Name]], [1]Billing!$Q$5:$Q$40, [1]Billing!$U$5:$U$40) -> 0 | J37: =_xlfn.XLOOKUP(Table1[[#This Row],[Party Name]], [1]Billing!$Q$5:$Q$40, [1]Billing!$W$5:$W$40) -> 0
A38: 46042 | B38: Hafiz Qureshi | C38: December Closing CF | D38: Silky | H38: =_xlfn.XLOOKUP(Table1[[#This Row],[Shipment Number]], 'pivot '!A:A,'pivot '!G:G, "NF") -> #DIV/0! | I38: =_xlfn.XLOOKUP(Table1[[#This Row],[Party Name]], [1]Billing!$Q$5:$Q$40, [1]Billing!$U$5:$U$40) -> 0 | J38: =_xlfn.XLOOKUP(Table1[[#This Row],[Party Name]], [1]Billing!$Q$5:$Q$40, [1]Billing!$W$5:$W$40) -> 0
A39: 46042 | B39: Badshah Fabrics | C39: December Closing CF | D39: Silky | H39: =_xlfn.XLOOKUP(Table1[[#This Row],[Shipment Number]], 'pivot '!A:A,'pivot '!G:G, "NF") -> #DIV/0! | I39: =_xlfn.XLOOKUP(Table1[[#This Row],[Party Name]], [1]Billing!$Q$5:$Q$40, [1]Billing!$U$5:$U$40) -> 141474.95 | J39: =_xlfn.XLOOKUP(Table1[[#This Row],[Party Name]], [1]Billing!$Q$5:$Q$40, [1]Billing!$W$5:$W$40) -> 1776019.6
A40: 46042 | B40: Gauhar Kashif | C40: December Closing CF | D40: Silky | H40: =_xlfn.XLOOKUP(Table1[[#This Row],[Shipment Number]], 'pivot '!A:A,'pivot '!G:G, "NF") -> #DIV/0! | I40: =_xlfn.XLOOKUP(Table1[[#This Row],[Party Name]], [1]Billing!$Q$5:$Q$40, [1]Billing!$U$5:$U$40) -> 0 | J40: =_xlfn.XLOOKUP(Table1[[#This Row],[Party Name]], [1]Billing!$Q$5:$Q$40, [1]Billing!$W$5:$W$40) -> 0
A41: 46042 | B41: Amjad 7up | C41: December Closing CF | D41: Silky | H41: =_xlfn.XLOOKUP(Table1[[#This Row],[Shipment Number]], 'pivot '!A:A,'pivot '!G:G, "NF") -> #DIV/0! | I41: =_xlfn.XLOOKUP(Table1[[#This Row],[Party Name]], [1]Billing!$Q$5:$Q$40, [1]Billing!$U$5:$U$40) -> 0 | J41: =_xlfn.XLOOKUP(Table1[[#This Row],[Party Name]], [1]Billing!$Q$5:$Q$40, [1]Billing!$W$5:$W$40) -> 0
A42: 46042 | B42: Hazrat Khan | C42: December Closing CF | D42: Silky | H42: =_xlfn.XLOOKUP(Table1[[#This Row],[Shipment Number]], 'pivot '!A:A,'pivot '!G:G, "NF") -> #DIV/0! | I42: =_xlfn.XLOOKUP(Table1[[#This Row],[Party Name]], [1]Billing!$Q$5:$Q$40, [1]Billing!$U$5:$U$40) -> 0 | J42: =_xlfn.XLOOKUP(Table1[[#This Row],[Party Name]], [1]Billing!$Q$5:$Q$40, [1]Billing!$W$5:$W$40) -> 0
A43: 46042 | B43: Haseeb Shamsi | C43: December Closing CF | D43: Silky | H43: =_xlfn.XLOOKUP(Table1[[#This Row],[Shipment Number]], 'pivot '!A:A,'pivot '!G:G, "NF") -> #DIV/0! | I43: =_xlfn.XLOOKUP(Table1[[#This Row],[Party Name]], [1]Billing!$Q$5:$Q$40, [1]Billing!$U$5:$U$40) -> 9232.8091 | J43: =_xlfn.XLOOKUP(Table1[[#This Row],[Party Name]], [1]Billing!$Q$5:$Q$40, [1]Billing!$W$5:$W$40) -> 120026.52
... A53: 46042 | B53: Ahmad Javaid | C53: December Closing CF | D53: Silky | H53: =_xlfn.XLOOKUP(Table1[[#This Row],[Shipment Number]], 'pivot '!A:A,'pivot '!G:G, "NF") -> #DIV/0! | I53: =_xlfn.XLOOKUP(Table1[[#This Row],[Party Name]], [1]Billing!$Q$5:$Q$40, [1]Billing!$U$5:$U$40) -> 0 | J53: =_xlfn.XLOOKUP(Table1[[#This Row],[Party Name]], [1]Billing!$Q$5:$Q$40, [1]Billing!$W$5:$W$40) -> 0
A54: 46042 | B54: Sajad Khan | C54: December Closing CF | D54: Slub | H54: =_xlfn.XLOOKUP(Table1[[#This Row],[Shipment Number]], 'pivot '!A:A,'pivot '!G:G, "NF") -> #DIV/0! | J54: =_xlfn.XLOOKUP(Table1[[#This Row],[Party Name]], [1]Billing!$Q$5:$Q$40, [1]Billing!$X$5:$X$40) -> 71359.729
A55: 46042 | B55: Faizan | C55: December Closing CF | D55: Slub | H55: =_xlfn.XLOOKUP(Table1[[#This Row],[Shipment Number]], 'pivot '!A:A,'pivot '!G:G, "NF") -> #DIV/0! | J55: =_xlfn.XLOOKUP(Table1[[#This Row],[Party Name]], [1]Billing!$Q$5:$Q$40, [1]Billing!$X$5:$X$40) -> 44550.11
A56: 46042 | B56: Shafique Ansari | C56: December Closing CF | D56: Satin | H56: =_xlfn.XLOOKUP(Table1[[#This Row],[Shipment Number]], 'pivot '!A:A,'pivot '!G:G, "NF") -> #DIV/0! | J56: =_xlfn.XLOOKUP(Table1[[#This Row],[Party Name]], [1]Billing!$Q$5:$Q$40, [1]Billing!$Y$5:$Y$40) -> 94656.181
A57: 46042 | B57: Sufi Nawaz Sahab | C57: December Closing CF | D57: Satin | H57: =_xlfn.XLOOKUP(Table1[[#This Row],[Shipment Number]], 'pivot '!A:A,'pivot '!G:G, "NF") -> #DIV/0! | J57: =_xlfn.XLOOKUP(Table1[[#This Row],[Party Name]], [1]Billing!$Q$5:$Q$40, [1]Billing!$Y$5:$Y$40) -> 239959.77
A58: 46042 | B58: Salman Zaffar | C58: December Closing CF | D58: Black-Chamki | H58: =_xlfn.XLOOKUP(Table1[[#This Row],[Shipment Number]], 'pivot '!A:A,'pivot '!G:G, "NF") -> #DIV/0! | J58: =_xlfn.XLOOKUP(Table1[[#This Row],[Party Name]], [1]Billing!$Q$5:$Q$40, [1]Billing!$Z$5:$Z$40) -> 161653.26
A59: 46042 | B59: Salman Zaffar | C59: December Closing CF | D59: Kataan | H59: =_xlfn.XLOOKUP(Table1[[#This Row],[Shipment Number]], 'pivot '!A:A,'pivot '!G:G, "NF") -> #DIV/0! | J59: =_xlfn.XLOOKUP(Table1[[#This Row],[Party Name]], [1]Billing!$Q$5:$Q$40, [1]Billing!$AA$5:$AA$40) -> 1545665.7
A60: 46042 | B60: Shahid Qasayi | C60: December Closing CF | D60: Kataan | H60: =_xlfn.XLOOKUP(Table1[[#This Row],[Shipment Number]], 'pivot '!A:A,'pivot '!G:G, "NF") -> #DIV/0! | J60: =_xlfn.XLOOKUP(Table1[[#This Row],[Party Name]], [1]Billing!$Q$5:$Q$40, [1]Billing!$AA$5:$AA$40) -> 523143.75
A61: 46042 | B61: Shahid Qasayi | C61: December Closing CF | D61: Black-Chamki | H61: =_xlfn.XLOOKUP(Table1[[#This Row],[Shipment Number]], 'pivot '!A:A,'pivot '!G:G, "NF") -> #DIV/0! | J61: =_xlfn.XLOOKUP(Table1[[#This Row],[Party Name]], [1]Billing!$Q$5:$Q$40, [1]Billing!$Z$5:$Z$40) -> 23767.374
A62: 46042 | B62: Ahmad Javaid | C62: December Closing CF | D62: Munaar | H62: =_xlfn.XLOOKUP(Table1[[#This Row],[Shipment Number]], 'pivot '!A:A,'pivot '!G:G, "NF") -> #DIV/0! | J62: =_xlfn.XLOOKUP(Table1[[#This Row],[Party Name]], [1]Billing!$Q$5:$Q$40, [1]Billing!$AB$5:$AB$40) -> 151504.21
A63: 46043 | B63: Azam | C63: 1375 | D63: Silky | E63: 2024 | F63: 16895 | G63: 18197 | H63: =_xlfn.XLOOKUP(Table1[[#This Row],[Shipment Number]], 'pivot '!A:A,'pivot '!G:G, "NF") -> 1.5120501 | I63: =Table1[[#This Row],[Tiyaar/gaz]]/1.0936 -> 16639.539 | J63: {=_xlfn.IFS( AND(Table1[[#This Row],[Party Name]]="Faizan",Table1[[#This Row],[Quality]]="Silky"),Table1[[#This Row],[tiyar/meters]]*13, AND(Table1[[#This Row],[Party Name]]="Shehzad Kamoki",Table1[[#This Row],[Quality]]="Chamki"),Table1[[#This Row],[tiyar/meters]]*10.5, AND(Table1[[#This Row],[Party Name]]="Sajad Khan",Table1[[#This Row],[Quality]]="Slub"),Table1[[#This Row],[tiyar/meters]]*13, AND(Table1[[#This Row],[Party Name]]="Faizan",Table1[[#This Row],[Quality]]="Slub"),Table1[[#This Row],[tiyar/meters]]*15, AND(Table1[[#This Row],[Party Name]]="Shafique Ansari",Table1[[#This Row],[Quality]]="Satin"),Table1[[#This Row],[tiyar/meters]]*28,AND(Table1[[#This Row],[Party Name]]="Badshah Fabrics",Table1[[#This Row],[Quality]]="Crinkle"),Table1[[#This Row],[tiyar/meters]]*11,AND(Table1[[#This Row],[Party Name]]="Salman Zaffar",Table1[[#This Row],[Quality]]="Kataan"),Table1[[#This Row],[tiyar/meters]]*10, Table1[[#This Row],[Quality]]="Chamki",Table1[[#This Row],[tiyar/meters]]*10, Table1[[#This Row],[Quality]]="Black-Chamki",Table1[[#This Row],[tiyar/meters]]*12, Table1[[#This Row],[Quality]]="Silky",Table1[[#This Row],[tiyar/meters]]*13, Table1[[#This Row],[Quality]]="Crinkle",Table1[[#This Row],[tiyar/meters]]*10,Table1[[#This Row],[Quality]]="Kataan",Table1[[#This Row],[tiyar/meters]]*11,Table1[[#This Row],[Quality]]="Munaar",Table1[[#This Row],[tiyar/meters]]*13,Table1[[#This Row],[Quality]]="Satin",Table1[[#This Row],[tiyar/meters]]*10 )} -> 216314.01
A64: 46043 | B64: Azam | C64: 1376 | D64: Silky | E64: 2023 | F64: 20503 | G64: 10968 | H64: =_xlfn.XLOOKUP(Table1[[#This Row],[Shipment Number]], 'pivot '!A:A,'pivot '!G:G, "NF") -> 51.083933 | I64: =Table1[[#This Row],[Tiyaar/gaz]]/1.0936 -> 10029.261 | J64: {=_xlfn.IFS( AND(Table1[[#This Row],[Party Name]]="Faizan",Table1[[#This Row],[Quality]]="Silky"),Table1[[#This Row],[tiyar/meters]]*13, AND(Table1[[#This Row],[Party Name]]="Shehzad Kamoki",Table1[[#This Row],[Quality]]="Chamki"),Table1[[#This Row],[tiyar/meters]]*10.5, AND(Table1[[#This Row],[Party Name]]="Sajad Khan",Table1[[#This Row],[Quality]]="Slub"),Table1[[#This Row],[tiyar/meters]]*13, AND(Table1[[#This Row],[Party Name]]="Faizan",Table1[[#This Row],[Quality]]="Slub"),Table1[[#This Row],[tiyar/meters]]*15, AND(Table1[[#This Row],[Party Name]]="Shafique Ansari",Table1[[#This Row],[Quality]]="Satin"),Table1[[#This Row],[tiyar/meters]]*28,AND(Table1[[#This Row],[Party Name]]="Badshah Fabrics",Table1[[#This Row],[Quality]]="Crinkle"),Table1[[#This Row],[tiyar/meters]]*11,AND(Table1[[#This Row],[Party Name]]="Salman Zaffar",Table1[[#This Row],[Quality]]="Kataan"),Table1[[#This Row],[tiyar/meters]]*10, Table1[[#This Row],[Quality]]="Chamki",Table1[[#This Row],[tiyar/meters]]*10, Table1[[#This Row],[Quality]]="Black-Chamki",Table1[[#This Row],[tiyar/meters]]*12, Table1[[#This Row],[Quality]]="Silky",Table1[[#This Row],[tiyar/meters]]*13, Table1[[#This Row],[Quality]]="Crinkle",Table1[[#This Row],[tiyar/meters]]*10,Table1[[#This Row],[Quality]]="Kataan",Table1[[#This Row],[tiyar/meters]]*11,Table1[[#This Row],[Quality]]="Munaar",Table1[[#This Row],[tiyar/meters]]*13,Table1[[#This Row],[Quality]]="Satin",Table1[[#This Row],[tiyar/meters]]*10 )} -> 130380.4
A65: 46043 | B65: Azam | C65: 1377 | D65: Silky | E65: 2025 | F65: 6991 | G65: 7531 | H65: =_xlfn.XLOOKUP(Table1[[#This Row],[Shipment Number]], 'pivot '!A:A,'pivot '!G:G, "NF") -> 1.4957783 | I65: =Table1[[#This Row],[Tiyaar/gaz]]/1.0936 -> 6886.4301 | J65: {=_xlfn.IFS( AND(Table1[[#This Row],[Party Name]]="Faizan",Table1[[#This Row],[Quality]]="Silky"),Table1[[#This Row],[tiyar/meters]]*13, AND(Table1[[#This Row],[Party Name]]="Shehzad Kamoki",Table1[[#This Row],[Quality]]="Chamki"),Table1[[#This Row],[tiyar/meters]]*10.5, AND(Table1[[#This Row],[Party Name]]="Sajad Khan",Table1[[#This Row],[Quality]]="Slub"),Table1[[#This Row],[tiyar/meters]]*13, AND(Table1[[#This Row],[Party Name]]="Faizan",Table1[[#This Row],[Quality]]="Slub"),Table1[[#This Row],[tiyar/meters]]*15, AND(Table1[[#This Row],[Party Name]]="Shafique Ansari",Table1[[#This Row],[Quality]]="Satin"),Table1[[#This Row],[tiyar/meters]]*28,AND(Table1[[#This Row],[Party Name]]="Badshah Fabrics",Table1[[#This Row],[Quality]]="Crinkle"),Table1[[#This Row],[tiyar/meters]]*11,AND(Table1[[#This Row],[Party Name]]="Salman Zaffar",Table1[[#This Row],[Quality]]="Kataan"),Table1[[#This Row],[tiyar/meters]]*10, Table1[[#This Row],[Quality]]="Chamki",Table1[[#This Row],[tiyar/meters]]*10, Table1[[#This Row],[Quality]]="Black-Chamki",Table1[[#This Row],[tiyar/meters]]*12, Table1[[#This Row],[Quality]]="Silky",Table1[[#This Row],[tiyar/meters]]*13, Table1[[#This Row],[Quality]]="Crinkle",Table1[[#This Row],[tiyar/meters]]*10,Table1[[#This Row],[Quality]]="Kataan",Table1[[#This Row],[tiyar/meters]]*11,Table1[[#This Row],[Quality]]="Munaar",Table1[[#This Row],[tiyar/meters]]*13,Table1[[#This Row],[Quality]]="Satin",Table1[[#This Row],[tiyar/meters]]*10 )} -> 89523.592
A66: 46043 | B66: Ubaidullah | C66: 1378 | D66: Silky | E66: 2039 | F66: 31746 | G66: 15139 | H66: =_xlfn.XLOOKUP(Table1[[#This Row],[Shipment Number]], 'pivot '!A:A,'pivot '!G:G, "NF") -> 56.393656 | I66: =Table1[[#This Row],[Tiyaar/gaz]]/1.0936 -> 13843.27 | J66: {=_xlfn.IFS( AND(Table1[[#This Row],[Party Name]]="Faizan",Table1[[#This Row],[Quality]]="Silky"),Table1[[#This Row],[tiyar/meters]]*13, AND(Table1[[#This Row],[Party Name]]="Shehzad Kamoki",Table1[[#This Row],[Quality]]="Chamki"),Table1[[#This Row],[tiyar/meters]]*10.5, AND(Table1[[#This Row],[Party Name]]="Sajad Khan",Table1[[#This Row],[Quality]]="Slub"),Table1[[#This Row],[tiyar/meters]]*13, AND(Table1[[#This Row],[Party Name]]="Faizan",Table1[[#This Row],[Quality]]="Slub"),Table1[[#This Row],[tiyar/meters]]*15, AND(Table1[[#This Row],[Party Name]]="Shafique Ansari",Table1[[#This Row],[Quality]]="Satin"),Table1[[#This Row],[tiyar/meters]]*28,AND(Table1[[#This Row],[Party Name]]="Badshah Fabrics",Table1[[#This Row],[Quality]]="Crinkle"),Table1[[#This Row],[tiyar/meters]]*11,AND(Table1[[#This Row],[Party Name]]="Salman Zaffar",Table1[[#This Row],[Quality]]="Kataan"),Table1[[#This Row],[tiyar/meters]]*10, Table1[[#This Row],[Quality]]="Chamki",Table1[[#This Row],[tiyar/meters]]*10, Table1[[#This Row],[Quality]]="Black-Chamki",Table1[[#This Row],[tiyar/meters]]*12, Table1[[#This Row],[Quality]]="Silky",Table1[[#This Row],[tiyar/meters]]*13, Table1[[#This Row],[Quality]]="Crinkle",Table1[[#This Row],[tiyar/meters]]*10,Table1[[#This Row],[Quality]]="Kataan",Table1[[#This Row],[tiyar/meters]]*11,Table1[[#This Row],[Quality]]="Munaar",Table1[[#This Row],[tiyar/meters]]*13,Table1[[#This Row],[Quality]]="Satin",Table1[[#This Row],[tiyar/meters]]*10 )} -> 179962.51
A67: 46043 | B67: Ubaidullah | C67: 1379 | D67: Silky | E67: 2037 | F67: 14961 | G67: 1686 | H67: =_xlfn.XLOOKUP(Table1[[#This Row],[Shipment Number]], 'pivot '!A:A,'pivot '!G:G, "NF") -> 89.695227 | I67: =Table1[[#This Row],[Tiyaar/gaz]]/1.0936 -> 1541.6971 | J67: {=_xlfn.IFS( AND(Table1[[#This Row],[Party Name]]="Faizan",Table1[[#This Row],[Quality]]="Silky"),Table1[[#This Row],[tiyar/meters]]*13, AND(Table1[[#This Row],[Party Name]]="Shehzad Kamoki",Table1[[#This Row],[Quality]]="Chamki"),Table1[[#This Row],[tiyar/meters]]*10.5, AND(Table1[[#This Row],[Party Name]]="Sajad Khan",Table1[[#This Row],[Quality]]="Slub"),Table1[[#This Row],[tiyar/meters]]*13, AND(Table1[[#This Row],[Party Name]]="Faizan",Table1[[#This Row],[Quality]]="Slub"),Table1[[#This Row],[tiyar/meters]]*15, AND(Table1[[#This Row],[Party Name]]="Shafique Ansari",Table1[[#This Row],[Quality]]="Satin"),Table1[[#This Row],[tiyar/meters]]*28,AND(Table1[[#This Row],[Party Name]]="Badshah Fabrics",Table1[[#This Row],[Quality]]="Crinkle"),Table1[[#This Row],[tiyar/meters]]*11,AND(Table1[[#This Row],[Party Name]]="Salman Zaffar",Table1[[#This Row],[Quality]]="Kataan"),Table1[[#This Row],[tiyar/meters]]*10, Table1[[#This Row],[Quality]]="Chamki",Table1[[#This Row],[tiyar/meters]]*10, Table1[[#This Row],[Quality]]="Black-Chamki",Table1[[#This Row],[tiyar/meters]]*12, Table1[[#This Row],[Quality]]="Silky",Table1[[#This Row],[tiyar/meters]]*13, Table1[[#This Row],[Quality]]="Crinkle",Table1[[#This Row],[tiyar/meters]]*10,Table1[[#This Row],[Quality]]="Kataan",Table1[[#This Row],[tiyar/meters]]*11,Table1[[#This Row],[Quality]]="Munaar",Table1[[#This Row],[tiyar/meters]]*13,Table1[[#This Row],[Quality]]="Satin",Table1[[#This Row],[tiyar/meters]]*10 )} -> 20042.063
